Workbook

Sheet Inputs -->

Sheet Menu and cost - Russia
H1: Costs of products | P1: Costs of labour
H2: 4 | I2: 6 | J2: 4 | K2: 2 | L2: 3 | P2: 3
B3: ID | C3: Category | D3: Product | E3: Price | F3: Cost | G3: Weight | H3: Dairy Products | I3: Meat / Seafood | J3: Fruits / Veggie | K3: Beverages | L3: Pantry | M3: Total | N3: Portions/hour | O3: Time - min | P3: Time - hrs | Q3: Profit | R3: Производительность
B4: 1 | C4: Appetizer | D4: Salad A | E4: 3 | F4: =SUMPRODUCT(H4:L4,H$2:L$2)*G4 -> 0.78 | G4: 0.2 | H4: 0 | I4: 0 | J4: 0.9 | K4: 0 | L4: 0.1 | M4: =SUM(H4:L4) -> 1 | N4: 20 | O4: =60/N4 -> 3 | P4: =O4/60 -> 0.05 | Q4: =E4-F4-P4*P$2 -> 2.07
B5: =B4+1 -> 2 | C5: Appetizer | D5: Salad B | E5: 3 | F5: =SUMPRODUCT(H5:L5,H$2:L$2)*G5 -> 0.86 | G5: 0.2 | H5: 0 | I5: 0.2 | J5: 0.7 | K5: 0 | L5: 0.1 | M5: =SUM(H5:L5) -> 1 | N5: 20 | O5: =60/N5 -> 3 | P5: =O5/60 -> 0.05 | Q5: =E5-F5-P5*P$2 -> 1.99
B6: =B5+1 -> 3 | C6: Appetizer | D6: Salad C | E6: 3 | F6: =SUMPRODUCT(H6:L6,H$2:L$2)*G6 -> 0.98 | G6: 0.2 | H6: 0 | I6: 0.5 | J6: 0.4 | K6: 0 | L6: 0.1 | M6: =SUM(H6:L6) -> 1 | N6: 20 | O6: =60/N6 -> 3 | P6: =O6/60 -> 0.05 | Q6: =E6-F6-P6*P$2 -> 1.87
B7: =B6+1 -> 4 | C7: Appetizer | D7: Soup A | E7: 2 | F7: =SUMPRODUCT(H7:L7,H$2:L$2)*G7 -> 0.68 | G7: 0.2 | H7: 0.1 | I7: 0 | J7: 0.4 | K7: 0.1 | L7: 0.4 | M7: =SUM(H7:L7) -> 1 | N7: 60 | O7: =60/N7 -> 1 | P7: =O7/60 -> 0.016666667 | Q7: =E7-F7-P7*P$2 -> 1.27
B8: =B7+1 -> 5 | C8: Appetizer | D8: Soup B | E8: 2 | F8: =SUMPRODUCT(H8:L8,H$2:L$2)*G8 -> 0.78 | G8: 0.2 | H8: 0.1 | I8: 0.2 | J8: 0.3 | K8: 0.1 | L8: 0.3 | M8: =SUM(H8:L8) -> 1 | N8: 60 | O8: =60/N8 -> 1 | P8: =O8/60 -> 0.016666667 | Q8: =E8-F8-P8*P$2 -> 1.17
B9: =B8+1 -> 6 | C9: Appetizer | D9: Pirozhok A | E9: 1 | F9: =SUMPRODUCT(H9:L9,H$2:L$2)*G9 -> 0.38 | G9: 0.1 | H9: 0.1 | I9: 0 | J9: 0.75 | K9: 0.05 | L9: 0.1 | M9: =SUM(H9:L9) -> 1 | N9: 30 | O9: =60/N9 -> 2 | P9: =O9/60 -> 0.033333333 | Q9: =E9-F9-P9*P$2 -> 0.52
B10: =B9+1 -> 7 | C10: Appetizer | D10: Pirozhok B | E10: 1 | F10: =SUMPRODUCT(H10:L10,H$2:L$2)*G10 -> 0.48 | G10: 0.1 | H10: 0.1 | I10: 0.5 | J10: 0.25 | K10: 0.05 | L10: 0.1 | M10: =SUM(H10:L10) -> 1 | N10: 30 | O10: =60/N10 -> 2 | P10: =O10/60 -> 0.033333333 | Q10: =E10-F10-P10*P$2 -> 0.42
B11: =B10+1 -> 8 | C11: Entry | D11: Blin A | E11: 3 | F11: =SUMPRODUCT(H11:L11,H$2:L$2)*G11 -> 0.76 | G11: 0.2 | H11: 0.1 | I11: 0 | J11: 0.75 | K11: 0.05 | L11: 0.1 | M11: =SUM(H11:L11) -> 1 | N11: 15 | O11: =60/N11 -> 4 | P11: =O11/60 -> 0.066666667 | Q11: =E11-F11-P11*P$2 -> 2.04
B12: =B11+1 -> 9 | C12: Entry | D12: Blin B | E12: 3 | F12: =SUMPRODUCT(H12:L12,H$2:L$2)*G12 -> 1.14 | G12: 0.3 | H12: 0.3 | I12: 0 | J12: 0.55 | K12: 0.05 | L12: 0.1 | M12: =SUM(H12:L12) -> 1 | N12: 15 | O12: =60/N12 -> 4 | P12: =O12/60 -> 0.066666667 | Q12: =E12-F12-P12*P$2 -> 1.66
B13: =B12+1 -> 10 | C13: Entry | D13: Blin C | E13: 3 | F13: =SUMPRODUCT(H13:L13,H$2:L$2)*G13 -> 1.29 | G13: 0.3 | H13: 0.1 | I13: 0.25 | J13: 0.5 | K13: 0.05 | L13: 0.1 | M13: =SUM(H13:L13) -> 1 | N13: 15 | O13: =60/N13 -> 4 | P13: =O13/60 -> 0.066666667 | Q13: =E13-F13-P13*P$2 -> 1.51
B14: =B13+1 -> 11 | C14: Entry | D14: Blin D | E14: 3 | F14: =SUMPRODUCT(H14:L14,H$2:L$2)*G14 -> 0.92 | G14: 0.2 | H14: 0.2 | I14: 0.4 | J14: 0.25 | K14: 0.05 | L14: 0.1 | M14: =SUM(H14:L14) -> 1 | N14: 10 | O14: =60/N14 -> 6 | P14: =O14/60 -> 0.1 | Q14: =E14-F14-P14*P$2 -> 1.78
B15: =B14+1 -> 12 | C15: Entry | D15: Blin E | E15: 4 | F15: =SUMPRODUCT(H15:L15,H$2:L$2)*G15 -> 1.5 | G15: 0.3 | H15: 0.2 | I15: 0.6 | J15: 0.05 | K15: 0.05 | L15: 0.1 | M15: =SUM(H15:L15) -> 1 | N15: 10 | O15: =60/N15 -> 6 | P15: =O15/60 -> 0.1 | Q15: =E15-F15-P15*P$2 -> 2.2
B16: =B15+1 -> 13 | C16: Entry | D16: Blin F | E16: 4 | F16: =SUMPRODUCT(H16:L16,H$2:L$2)*G16 -> 1.44 | G16: 0.3 | H16: 0.2 | I16: 0.5 | J16: 0.15 | K16: 0.05 | L16: 0.1 | M16: =SUM(H16:L16) -> 1 | N16: 10 | O16: =60/N16 -> 6 | P16: =O16/60 -> 0.1 | Q16: =E16-F16-P16*P$2 -> 2.26
... B29: =B28+1 -> 26 | C29: Beverages | D29: Hot Drink B | E29: 1.5 | F29: =SUMPRODUCT(H29:L29,H$2:L$2)*G29 -> 0.44 | G29: 0.2 | H29: 0 | I29: 0 | J29: 0.1 | K29: 0.9 | L29: 0 | M29: =SUM(H29:L29) -> 1 | N29: 40 | O29: =60/N29 -> 1.5 | P29: =O29/60 -> 0.025 | Q29: =E29-F29-P29*P$2 -> 0.985

Sheet COGS
C2: Dairy Products | D2: Meat / Seafood | E2: Fruits / Veggie | F2: Beverages | G2: Pantry | I2: Labor
B3: Columbus | C3: 8.35 | D3: 14.13 | E3: 12.83 | F3: 5.93 | G3: 5.89 | I3: 10
B4: Cincinnati | C4: 6.79 | D4: 13.56 | E4: 11.34 | F4: 4.56 | G4: 5.34 | I4: 10.5
B5: Cleveland | C5: 6.23 | D5: 13.8 | E5: 12.45 | F5: 5.2 | G5: 5.7 | I5: 11
B6: Las Vegas | C6: 14.56 | D6: 21.88 | E6: 15.54 | F6: 9.83 | G6: 10.78 | I6: 9
B7: Miami | C7: 14.2 | D7: 19.51 | E7: 15.24 | F7: 9.5 | G7: 9.01 | I7: 9.5
B8: Indianapolis | C8: 5.36 | D8: 12.93 | E8: 10.3 | F8: 4.64 | G8: 4.8 | I8: 8
B9: Birmingham | C9: 9.62 | D9: 14.79 | E9: 14.44 | F9: 8.7 | G9: 8.04 | I9: 10
B10: Portland | C10: 9.29 | D10: 14.35 | E10: 13.55 | F10: 8.24 | G10: 6.44 | I10: 14

Sheet Order Composition
C2: Appetizer | D2: Entry | E2: Dessert | F2: Beverages
B3: Columbus | C3: 0.3 | D3: 0.55 | E3: 0.35 | F3: 0.8
B4: Cincinnati | C4: 0.55 | D4: 0.6 | E4: 0.4 | F4: 0.8
B5: Cleveland | C5: 0.4 | D5: 0.85 | E5: 0.55 | F5: 0.75
B6: Las Vegas | C6: 0.55 | D6: 0.9 | E6: 0.7 | F6: 0.9
B7: Miami | C7: 0.5 | D7: 0.85 | E7: 0.8 | F7: 0.95
B8: Indianapolis | C8: 0.4 | D8: 0.6 | E8: 0.65 | F8: 0.8
B9: Birmingham | C9: 0.2 | D9: 0.65 | E9: 0.45 | F9: 0.75
B10: Portland | C10: 0.35 | D10: 0.8 | E10: 0.5 | F10: 0.95
B12: RF | C12: 0.25 | D12: 0.85 | E12: 0.55 | F12: 0.3

Sheet Solution -->
B3: Solution

Sheet Mean order price
M1: Average category price | Q1: Adding average order price
C2: Dairy Products | D2: Meat / Seafood | E2: Fruits / Veggie | F2: Beverages | G2: Pantry | H2: Labor | I2: Appetizer | J2: Entry | K2: Dessert | L2: Beverages | M2: Appetizer | N2: Entry | O2: Dessert | P2: Beverages | Q2: Appetizer | R2: Entry | S2: Dessert | T2: Beverages | V2: Mean order, $
B3: Columbus | C3: =VLOOKUP(B3,COGS!$B$2:$I$10,2,FALSE) -> 8.35 | D3: =VLOOKUP($B3,COGS!$B$2:$I$10,3,FALSE) -> 14.13 | E3: =VLOOKUP($B3,COGS!$B$2:$I$10,4,FALSE) -> 12.83 | F3: =VLOOKUP($B3,COGS!$B$2:$I$10,5,FALSE) -> 5.93 | G3: =VLOOKUP($B3,COGS!$B$2:$I$10,6,FALSE) -> 5.89 | H3: =VLOOKUP($B3,COGS!$B$2:$I$10,8,FALSE) -> 10 | I3: 0.3 | J3: 0.55 | K3: 0.35 | L3: 0.8 | M3: =AVERAGEIFS('Menu and cost - USA by city'!$E:$E,'Menu and cost - USA by city'!$A:$A,'Mean order price'!$B3,'Menu and cost - USA by city'!$C:$C,'Mean order price'!I$2) -> 2.8571429 | N3: =AVERAGEIFS('Menu and cost - USA by city'!$E:$E,'Menu and cost - USA by city'!$A:$A,'Mean order price'!$B3,'Menu and cost - USA by city'!$C:$C,'Mean order price'!J$2) -> 4.8 | O3: =AVERAGEIFS('Menu and cost - USA by city'!$E:$E,'Menu and cost - USA by city'!$A:$A,'Mean order price'!$B3,'Menu and cost - USA by city'!$C:$C,'Mean order price'!K$2) -> 3.3333333 | P3: =AVERAGEIFS('Menu and cost - USA by city'!$E:$E,'Menu and cost - USA by city'!$A:$A,'Mean order price'!$B3,'Menu and cost - USA by city'!$C:$C,'Mean order price'!L$2) -> 2.2222222 | Q3: =I3*M3 -> 0.85714286 | R3: =J3*N3 -> 2.64 | S3: =K3*O3 -> 1.1666667 | T3: =L3*P3 -> 1.7777778 | V3: =SUMPRODUCT(I3:L3,M3:P3) -> 6.4415873
B4: Cincinnati | C4: =VLOOKUP(B4,COGS!$B$2:$I$10,2,FALSE) -> 6.79 | D4: =VLOOKUP($B4,COGS!$B$2:$I$10,3,FALSE) -> 13.56 | E4: =VLOOKUP($B4,COGS!$B$2:$I$10,4,FALSE) -> 11.34 | F4: =VLOOKUP($B4,COGS!$B$2:$I$10,5,FALSE) -> 4.56 | G4: =VLOOKUP($B4,COGS!$B$2:$I$10,6,FALSE) -> 5.34 | H4: =VLOOKUP($B4,COGS!$B$2:$I$10,8,FALSE) -> 10.5 | I4: 0.55 | J4: 0.6 | K4: 0.4 | L4: 0.8 | M4: =AVERAGEIFS('Menu and cost - USA by city'!$E:$E,'Menu and cost - USA by city'!$A:$A,'Mean order price'!$B4,'Menu and cost - USA by city'!$C:$C,'Mean order price'!I$2) -> 3 | N4: =AVERAGEIFS('Menu and cost - USA by city'!$E:$E,'Menu and cost - USA by city'!$A:$A,'Mean order price'!$B4,'Menu and cost - USA by city'!$C:$C,'Mean order price'!J$2) -> 5.04 | O4: =AVERAGEIFS('Menu and cost - USA by city'!$E:$E,'Menu and cost - USA by city'!$A:$A,'Mean order price'!$B4,'Menu and cost - USA by city'!$C:$C,'Mean order price'!K$2) -> 3.5 | P4: =AVERAGEIFS('Menu and cost - USA by city'!$E:$E,'Menu and cost - USA by city'!$A:$A,'Mean order price'!$B4,'Menu and cost - USA by city'!$C:$C,'Mean order price'!L$2) -> 2.3333333 | Q4: =I4*M4 -> 1.65 | R4: =J4*N4 -> 3.024 | S4: =K4*O4 -> 1.4 | T4: =L4*P4 -> 1.8666667 | V4: =SUMPRODUCT(I4:L4,M4:P4) -> 7.9406667
B5: Cleveland | C5: =VLOOKUP(B5,COGS!$B$2:$I$10,2,FALSE) -> 6.23 | D5: =VLOOKUP($B5,COGS!$B$2:$I$10,3,FALSE) -> 13.8 | E5: =VLOOKUP($B5,COGS!$B$2:$I$10,4,FALSE) -> 12.45 | F5: =VLOOKUP($B5,COGS!$B$2:$I$10,5,FALSE) -> 5.2 | G5: =VLOOKUP($B5,COGS!$B$2:$I$10,6,FALSE) -> 5.7 | H5: =VLOOKUP($B5,COGS!$B$2:$I$10,8,FALSE) -> 11 | I5: 0.4 | J5: 0.85 | K5: 0.55 | L5: 0.75 | M5: =AVERAGEIFS('Menu and cost - USA by city'!$E:$E,'Menu and cost - USA by city'!$A:$A,'Mean order price'!$B5,'Menu and cost - USA by city'!$C:$C,'Mean order price'!I$2) -> 3.1428571 | N5: =AVERAGEIFS('Menu and cost - USA by city'!$E:$E,'Menu and cost - USA by city'!$A:$A,'Mean order price'!$B5,'Menu and cost - USA by city'!$C:$C,'Mean order price'!J$2) -> 5.28 | O5: =AVERAGEIFS('Menu and cost - USA by city'!$E:$E,'Menu and cost - USA by city'!$A:$A,'Mean order price'!$B5,'Menu and cost - USA by city'!$C:$C,'Mean order price'!K$2) -> 3.6666667 | P5: =AVERAGEIFS('Menu and cost - USA by city'!$E:$E,'Menu and cost - USA by city'!$A:$A,'Mean order price'!$B5,'Menu and cost - USA by city'!$C:$C,'Mean order price'!L$2) -> 2.4444444 | Q5: =I5*M5 -> 1.2571429 | R5: =J5*N5 -> 4.488 | S5: =K5*O5 -> 2.0166667 | T5: =L5*P5 -> 1.8333333 | V5: =SUMPRODUCT(I5:L5,M5:P5) -> 9.5951429
B6: Las Vegas | C6: =VLOOKUP(B6,COGS!$B$2:$I$10,2,FALSE) -> 14.56 | D6: =VLOOKUP($B6,COGS!$B$2:$I$10,3,FALSE) -> 21.88 | E6: =VLOOKUP($B6,COGS!$B$2:$I$10,4,FALSE) -> 15.54 | F6: =VLOOKUP($B6,COGS!$B$2:$I$10,5,FALSE) -> 9.83 | G6: =VLOOKUP($B6,COGS!$B$2:$I$10,6,FALSE) -> 10.78 | H6: =VLOOKUP($B6,COGS!$B$2:$I$10,8,FALSE) -> 9 | I6: 0.55 | J6: 0.9 | K6: 0.7 | L6: 0.9 | M6: =AVERAGEIFS('Menu and cost - USA by city'!$E:$E,'Menu and cost - USA by city'!$A:$A,'Mean order price'!$B6,'Menu and cost - USA by city'!$C:$C,'Mean order price'!I$2) -> 2.5714286 | N6: =AVERAGEIFS('Menu and cost - USA by city'!$E:$E,'Menu and cost - USA by city'!$A:$A,'Mean order price'!$B6,'Menu and cost - USA by city'!$C:$C,'Mean order price'!J$2) -> 4.32 | O6: =AVERAGEIFS('Menu and cost - USA by city'!$E:$E,'Menu and cost - USA by city'!$A:$A,'Mean order price'!$B6,'Menu and cost - USA by city'!$C:$C,'Mean order price'!K$2) -> 3 | P6: =AVERAGEIFS('Menu and cost - USA by city'!$E:$E,'Menu and cost - USA by city'!$A:$A,'Mean order price'!$B6,'Menu and cost - USA by city'!$C:$C,'Mean order price'!L$2) -> 2 | Q6: =I6*M6 -> 1.4142857 | R6: =J6*N6 -> 3.888 | S6: =K6*O6 -> 2.1 | T6: =L6*P6 -> 1.8 | V6: =SUMPRODUCT(I6:L6,M6:P6) -> 9.2022857
B7: Miami | C7: =VLOOKUP(B7,COGS!$B$2:$I$10,2,FALSE) -> 14.2 | D7: =VLOOKUP($B7,COGS!$B$2:$I$10,3,FALSE) -> 19.51 | E7: =VLOOKUP($B7,COGS!$B$2:$I$10,4,FALSE) -> 15.24 | F7: =VLOOKUP($B7,COGS!$B$2:$I$10,5,FALSE) -> 9.5 | G7: =VLOOKUP($B7,COGS!$B$2:$I$10,6,FALSE) -> 9.01 | H7: =VLOOKUP($B7,COGS!$B$2:$I$10,8,FALSE) -> 9.5 | I7: 0.5 | J7: 0.85 | K7: 0.8 | L7: 0.95 | M7: =AVERAGEIFS('Menu and cost - USA by city'!$E:$E,'Menu and cost - USA by city'!$A:$A,'Mean order price'!$B7,'Menu and cost - USA by city'!$C:$C,'Mean order price'!I$2) -> 2.7142857 | N7: =AVERAGEIFS('Menu and cost - USA by city'!$E:$E,'Menu and cost - USA by city'!$A:$A,'Mean order price'!$B7,'Menu and cost - USA by city'!$C:$C,'Mean order price'!J$2) -> 4.56 | O7: =AVERAGEIFS('Menu and cost - USA by city'!$E:$E,'Menu and cost - USA by city'!$A:$A,'Mean order price'!$B7,'Menu and cost - USA by city'!$C:$C,'Mean order price'!K$2) -> 3.1666667 | P7: =AVERAGEIFS('Menu and cost - USA by city'!$E:$E,'Menu and cost - USA by city'!$A:$A,'Mean order price'!$B7,'Menu and cost - USA by city'!$C:$C,'Mean order price'!L$2) -> 2.1111111 | Q7: =I7*M7 -> 1.3571429 | R7: =J7*N7 -> 3.876 | S7: =K7*O7 -> 2.5333333 | T7: =L7*P7 -> 2.0055556 | V7: =SUMPRODUCT(I7:L7,M7:P7) -> 9.7720317
B8: Indianapolis | C8: =VLOOKUP(B8,COGS!$B$2:$I$10,2,FALSE) -> 5.36 | D8: =VLOOKUP($B8,COGS!$B$2:$I$10,3,FALSE) -> 12.93 | E8: =VLOOKUP($B8,COGS!$B$2:$I$10,4,FALSE) -> 10.3 | F8: =VLOOKUP($B8,COGS!$B$2:$I$10,5,FALSE) -> 4.64 | G8: =VLOOKUP($B8,COGS!$B$2:$I$10,6,FALSE) -> 4.8 | H8: =VLOOKUP($B8,COGS!$B$2:$I$10,8,FALSE) -> 8 | I8: 0.4 | J8: 0.6 | K8: 0.65 | L8: 0.8 | M8: =AVERAGEIFS('Menu and cost - USA by city'!$E:$E,'Menu and cost - USA by city'!$A:$A,'Mean order price'!$B8,'Menu and cost - USA by city'!$C:$C,'Mean order price'!I$2) -> 2.2857143 | N8: =AVERAGEIFS('Menu and cost - USA by city'!$E:$E,'Menu and cost - USA by city'!$A:$A,'Mean order price'!$B8,'Menu and cost - USA by city'!$C:$C,'Mean order price'!J$2) -> 3.84 | O8: =AVERAGEIFS('Menu and cost - USA by city'!$E:$E,'Menu and cost - USA by city'!$A:$A,'Mean order price'!$B8,'Menu and cost - USA by city'!$C:$C,'Mean order price'!K$2) -> 2.6666667 | P8: =AVERAGEIFS('Menu and cost - USA by city'!$E:$E,'Menu and cost - USA by city'!$A:$A,'Mean order price'!$B8,'Menu and cost - USA by city'!$C:$C,'Mean order price'!L$2) -> 1.7777778 | Q8: =I8*M8 -> 0.91428571 | R8: =J8*N8 -> 2.304 | S8: =K8*O8 -> 1.7333333 | T8: =L8*P8 -> 1.4222222 | V8: =SUMPRODUCT(I8:L8,M8:P8) -> 6.3738413
B9: Birmingham | C9: =VLOOKUP(B9,COGS!$B$2:$I$10,2,FALSE) -> 9.62 | D9: =VLOOKUP($B9,COGS!$B$2:$I$10,3,FALSE) -> 14.79 | E9: =VLOOKUP($B9,COGS!$B$2:$I$10,4,FALSE) -> 14.44 | F9: =VLOOKUP($B9,COGS!$B$2:$I$10,5,FALSE) -> 8.7 | G9: =VLOOKUP($B9,COGS!$B$2:$I$10,6,FALSE) -> 8.04 | H9: =VLOOKUP($B9,COGS!$B$2:$I$10,8,FALSE) -> 10 | I9: 0.2 | J9: 0.65 | K9: 0.45 | L9: 0.75 | M9: =AVERAGEIFS('Menu and cost - USA by city'!$E:$E,'Menu and cost - USA by city'!$A:$A,'Mean order price'!$B9,'Menu and cost - USA by city'!$C:$C,'Mean order price'!I$2) -> 2.8571429 | N9: =AVERAGEIFS('Menu and cost - USA by city'!$E:$E,'Menu and cost - USA by city'!$A:$A,'Mean order price'!$B9,'Menu and cost - USA by city'!$C:$C,'Mean order price'!J$2) -> 4.8 | O9: =AVERAGEIFS('Menu and cost - USA by city'!$E:$E,'Menu and cost - USA by city'!$A:$A,'Mean order price'!$B9,'Menu and cost - USA by city'!$C:$C,'Mean order price'!K$2) -> 3.3333333 | P9: =AVERAGEIFS('Menu and cost - USA by city'!$E:$E,'Menu and cost - USA by city'!$A:$A,'Mean order price'!$B9,'Menu and cost - USA by city'!$C:$C,'Mean order price'!L$2) -> 2.2222222 | Q9: =I9*M9 -> 0.57142857 | R9: =J9*N9 -> 3.12 | S9: =K9*O9 -> 1.5 | T9: =L9*P9 -> 1.6666667 | V9: =SUMPRODUCT(I9:L9,M9:P9) -> 6.8580952
B10: Portland | C10: =VLOOKUP(B10,COGS!$B$2:$I$10,2,FALSE) -> 9.29 | D10: =VLOOKUP($B10,COGS!$B$2:$I$10,3,FALSE) -> 14.35 | E10: =VLOOKUP($B10,COGS!$B$2:$I$10,4,FALSE) -> 13.55 | F10: =VLOOKUP($B10,COGS!$B$2:$I$10,5,FALSE) -> 8.24 | G10: =VLOOKUP($B10,COGS!$B$2:$I$10,6,FALSE) -> 6.44 | H10: =VLOOKUP($B10,COGS!$B$2:$I$10,8,FALSE) -> 14 | I10: 0.35 | J10: 0.8 | K10: 0.5 | L10: 0.95 | M10: =AVERAGEIFS('Menu and cost - USA by city'!$E:$E,'Menu and cost - USA by city'!$A:$A,'Mean order price'!$B10,'Menu and cost - USA by city'!$C:$C,'Mean order price'!I$2) -> 4 | N10: =AVERAGEIFS('Menu and cost - USA by city'!$E:$E,'Menu and cost - USA by city'!$A:$A,'Mean order price'!$B10,'Menu and cost - USA by city'!$C:$C,'Mean order price'!J$2) -> 6.72 | O10: =AVERAGEIFS('Menu and cost - USA by city'!$E:$E,'Menu and cost - USA by city'!$A:$A,'Mean order price'!$B10,'Menu and cost - USA by city'!$C:$C,'Mean order price'!K$2) -> 4.6666667 | P10: =AVERAGEIFS('Menu and cost - USA by city'!$E:$E,'Menu and cost - USA by city'!$A:$A,'Mean order price'!$B10,'Menu and cost - USA by city'!$C:$C,'Mean order price'!L$2) -> 3.1111111 | Q10: =I10*M10 -> 1.4 | R10: =J10*N10 -> 5.376 | S10: =K10*O10 -> 2.3333333 | T10: =L10*P10 -> 2.9555556 | V10: =SUMPRODUCT(I10:L10,M10:P10) -> 12.064889
B12: RF | I12: 0.25 | J12: 0.85 | K12: 0.55 | L12: 0.3

Sheet Menu and cost - USA by city
A3: City | B3: ID | C3: Category | D3: Product | E3: Price | F3: Cost(with labour) | G3: Weight | H3: Dairy Products | I3: Meat / Seafood | J3: Fruits / Veggie | K3: Beverages | L3: Pantry | M3: Total | N3: Portions/hour | O3: Time - min | P3: Time - hrs | Q3: Profit | R3: Gross profit | S3: Order | T3: Order * Profit | U3: Gross Profit per Average Order | V3: Costs (with labor) per Average Order | W3: Labour cost, $ | X3: Labor costs per avg order
A4: Columbus | B4: 1 | C4: Appetizer | D4: Salad A | E4: ='Menu and cost - Russia'!E4*(COGS!I3/'Menu and cost - Russia'!$P$2)*0.4 -> 4 | F4: =SUMPRODUCT(H4:L4,'Mean order price'!$C$3:$G$3)*G4+P4*'Mean order price'!$H$3 -> 2.9272 | G4: 0.2 | H4: 0 | I4: 0 | J4: 0.9 | K4: 0 | L4: 0.1 | M4: =SUM(H4:L4) -> 1 | N4: 20 | O4: =60/N4 -> 3 | P4: =O4/60 -> 0.05 | Q4: =E4-F4 -> 1.0728 | R4: =Таблица1[[#This Row],[Profit]]/Таблица1[[#This Row],[Price]] -> 0.2682 | S4: =VLOOKUP($A4,'Order Composition'!$B$2:$F$10,MATCH($C4,'Order Composition'!$B$2:$F$2,0),0) -> 0.3 | T4: =S4*Q4 -> 0.32184 | U4: =Таблица1[[#This Row],[Price]]*Таблица1[[#This Row],[Order]] -> 1.2 | V4: =Таблица1[[#This Row],[Cost(with labour)]]*Таблица1[[#This Row],[Order]] -> 0.87816 | W4: =VLOOKUP($A4,'Mean order price'!$B$2:$H$10,7,0) -> 10 | X4: =W4*P4 -> 0.5
A5: Columbus | B5: =B4+1 -> 2 | C5: Appetizer | D5: Salad B | E5: =VLOOKUP('Menu and cost - USA by city'!D5,'Menu and cost - Russia'!$D$4:$P$29,2,FALSE)*(VLOOKUP('Menu and cost - USA by city'!A5,COGS!$B$3:$I$10,8,FALSE)/3)*0.4 -> 4 | F5: =SUMPRODUCT(H5:L5,'Mean order price'!$C$3:$G$3)*G5+P5*'Mean order price'!$H$3 -> 2.9792 | G5: 0.2 | H5: 0 | I5: 0.2 | J5: 0.7 | K5: 0 | L5: 0.1 | M5: =SUM(H5:L5) -> 1 | N5: 20 | O5: =60/N5 -> 3 | P5: =O5/60 -> 0.05 | Q5: =E5-F5 -> 1.0208 | R5: =Таблица1[[#This Row],[Profit]]/Таблица1[[#This Row],[Price]] -> 0.2552 | S5: =VLOOKUP($A5,'Order Composition'!$B$2:$F$10,MATCH($C5,'Order Composition'!$B$2:$F$2,0),0) -> 0.3 | T5: =S5*Q5 -> 0.30624 | U5: =Таблица1[[#This Row],[Price]]*Таблица1[[#This Row],[Order]] -> 1.2 | V5: =Таблица1[[#This Row],[Cost(with labour)]]*Таблица1[[#This Row],[Order]] -> 0.89376 | W5: =VLOOKUP($A5,'Mean order price'!$B$2:$H$10,7,0) -> 10 | X5: =W5*P5 -> 0.5
A6: Columbus | B6: =B5+1 -> 3 | C6: Appetizer | D6: Salad C | E6: =VLOOKUP('Menu and cost - USA by city'!D6,'Menu and cost - Russia'!$D$4:$P$29,2,FALSE)*(VLOOKUP('Menu and cost - USA by city'!A6,COGS!$B$3:$I$10,8,FALSE)/3)*0.4 -> 4 | F6: =SUMPRODUCT(H6:L6,'Mean order price'!$C$3:$G$3)*G6+P6*'Mean order price'!$H$3 -> 3.0572 | G6: 0.2 | H6: 0 | I6: 0.5 | J6: 0.4 | K6: 0 | L6: 0.1 | M6: =SUM(H6:L6) -> 1 | N6: 20 | O6: =60/N6 -> 3 | P6: =O6/60 -> 0.05 | Q6: =E6-F6 -> 0.9428 | R6: =Таблица1[[#This Row],[Profit]]/Таблица1[[#This Row],[Price]] -> 0.2357 | S6: =VLOOKUP($A6,'Order Composition'!$B$2:$F$10,MATCH($C6,'Order Composition'!$B$2:$F$2,0),0) -> 0.3 | T6: =S6*Q6 -> 0.28284 | U6: =Таблица1[[#This Row],[Price]]*Таблица1[[#This Row],[Order]] -> 1.2 | V6: =Таблица1[[#This Row],[Cost(with labour)]]*Таблица1[[#This Row],[Order]] -> 0.91716 | W6: =VLOOKUP($A6,'Mean order price'!$B$2:$H$10,7,0) -> 10 | X6: =W6*P6 -> 0.5
A7: Columbus | B7: =B6+1 -> 4 | C7: Appetizer | D7: Soup A | E7: =VLOOKUP('Menu and cost - USA by city'!D7,'Menu and cost - Russia'!$D$4:$P$29,2,FALSE)*(VLOOKUP('Menu and cost - USA by city'!A7,COGS!$B$3:$I$10,8,FALSE)/3)*0.4 -> 2.6666667 | F7: =SUMPRODUCT(H7:L7,'Mean order price'!$C$3:$G$3)*G7+P7*'Mean order price'!$H$3 -> 1.9498667 | G7: 0.2 | H7: 0.1 | I7: 0 | J7: 0.4 | K7: 0.1 | L7: 0.4 | M7: =SUM(H7:L7) -> 1 | N7: 60 | O7: =60/N7 -> 1 | P7: =O7/60 -> 0.016666667 | Q7: =E7-F7 -> 0.7168 | R7: =Таблица1[[#This Row],[Profit]]/Таблица1[[#This Row],[Price]] -> 0.2688 | S7: =VLOOKUP($A7,'Order Composition'!$B$2:$F$10,MATCH($C7,'Order Composition'!$B$2:$F$2,0),0) -> 0.3 | T7: =S7*Q7 -> 0.21504 | U7: =Таблица1[[#This Row],[Price]]*Таблица1[[#This Row],[Order]] -> 0.8 | V7: =Таблица1[[#This Row],[Cost(with labour)]]*Таблица1[[#This Row],[Order]] -> 0.58496 | W7: =VLOOKUP($A7,'Mean order price'!$B$2:$H$10,7,0) -> 10 | X7: =W7*P7 -> 0.16666667
A8: Columbus | B8: =B7+1 -> 5 | C8: Appetizer | D8: Soup B | E8: =VLOOKUP('Menu and cost - USA by city'!D8,'Menu and cost - Russia'!$D$4:$P$29,2,FALSE)*(VLOOKUP('Menu and cost - USA by city'!A8,COGS!$B$3:$I$10,8,FALSE)/3)*0.4 -> 2.6666667 | F8: =SUMPRODUCT(H8:L8,'Mean order price'!$C$3:$G$3)*G8+P8*'Mean order price'!$H$3 -> 2.1406667 | G8: 0.2 | H8: 0.1 | I8: 0.2 | J8: 0.3 | K8: 0.1 | L8: 0.3 | M8: =SUM(H8:L8) -> 1 | N8: 60 | O8: =60/N8 -> 1 | P8: =O8/60 -> 0.016666667 | Q8: =E8-F8 -> 0.526 | R8: =Таблица1[[#This Row],[Profit]]/Таблица1[[#This Row],[Price]] -> 0.19725 | S8: =VLOOKUP($A8,'Order Composition'!$B$2:$F$10,MATCH($C8,'Order Composition'!$B$2:$F$2,0),0) -> 0.3 | T8: =S8*Q8 -> 0.1578 | U8: =Таблица1[[#This Row],[Price]]*Таблица1[[#This Row],[Order]] -> 0.8 | V8: =Таблица1[[#This Row],[Cost(with labour)]]*Таблица1[[#This Row],[Order]] -> 0.6422 | W8: =VLOOKUP($A8,'Mean order price'!$B$2:$H$10,7,0) -> 10 | X8: =W8*P8 -> 0.16666667
A9: Columbus | B9: =B8+1 -> 6 | C9: Appetizer | D9: Pirozhok A | E9: =VLOOKUP('Menu and cost - USA by city'!D9,'Menu and cost - Russia'!$D$4:$P$29,2,FALSE)*(VLOOKUP('Menu and cost - USA by city'!A9,COGS!$B$3:$I$10,8,FALSE)/3)*0.4 -> 1.3333333 | F9: =SUMPRODUCT(H9:L9,'Mean order price'!$C$3:$G$3)*G9+P9*'Mean order price'!$H$3 -> 1.4676333 | G9: 0.1 | H9: 0.1 | I9: 0 | J9: 0.75 | K9: 0.05 | L9: 0.1 | M9: =SUM(H9:L9) -> 1 | N9: 30 | O9: =60/N9 -> 2 | P9: =O9/60 -> 0.033333333 | Q9: =E9-F9 -> -0.1343 | R9: =Таблица1[[#This Row],[Profit]]/Таблица1[[#This Row],[Price]] -> -0.100725 | S9: =VLOOKUP($A9,'Order Composition'!$B$2:$F$10,MATCH($C9,'Order Composition'!$B$2:$F$2,0),0) -> 0.3 | T9: =S9*Q9 -> -0.04029 | U9: =Таблица1[[#This Row],[Price]]*Таблица1[[#This Row],[Order]] -> 0.4 | V9: =Таблица1[[#This Row],[Cost(with labour)]]*Таблица1[[#This Row],[Order]] -> 0.44029 | W9: =VLOOKUP($A9,'Mean order price'!$B$2:$H$10,7,0) -> 10 | X9: =W9*P9 -> 0.33333333
A10: Columbus | B10: =B9+1 -> 7 | C10: Appetizer | D10: Pirozhok B | E10: =VLOOKUP('Menu and cost - USA by city'!D10,'Menu and cost - Russia'!$D$4:$P$29,2,FALSE)*(VLOOKUP('Menu and cost - USA by city'!A10,COGS!$B$3:$I$10,8,FALSE)/3)*0.4 -> 1.3333333 | F10: =SUMPRODUCT(H10:L10,'Mean order price'!$C$3:$G$3)*G10+P10*'Mean order price'!$H$3 -> 1.5326333 | G10: 0.1 | H10: 0.1 | I10: 0.5 | J10: 0.25 | K10: 0.05 | L10: 0.1 | M10: =SUM(H10:L10) -> 1 | N10: 30 | O10: =60/N10 -> 2 | P10: =O10/60 -> 0.033333333 | Q10: =E10-F10 -> -0.1993 | R10: =Таблица1[[#This Row],[Profit]]/Таблица1[[#This Row],[Price]] -> -0.149475 | S10: =VLOOKUP($A10,'Order Composition'!$B$2:$F$10,MATCH($C10,'Order Composition'!$B$2:$F$2,0),0) -> 0.3 | T10: =S10*Q10 -> -0.05979 | U10: =Таблица1[[#This Row],[Price]]*Таблица1[[#This Row],[Order]] -> 0.4 | V10: =Таблица1[[#This Row],[Cost(with labour)]]*Таблица1[[#This Row],[Order]] -> 0.45979 | W10: =VLOOKUP($A10,'Mean order price'!$B$2:$H$10,7,0) -> 10 | X10: =W10*P10 -> 0.33333333
A11: Columbus | B11: =B10+1 -> 8 | C11: Entry | D11: Blin A | E11: =VLOOKUP('Menu and cost - USA by city'!D11,'Menu and cost - Russia'!$D$4:$P$29,2,FALSE)*(VLOOKUP('Menu and cost - USA by city'!A11,COGS!$B$3:$I$10,8,FALSE)/3)*0.4 -> 4 | F11: =SUMPRODUCT(H11:L11,'Mean order price'!$C$3:$G$3)*G11+P11*'Mean order price'!$H$3 -> 2.9352667 | G11: 0.2 | H11: 0.1 | I11: 0 | J11: 0.75 | K11: 0.05 | L11: 0.1 | M11: =SUM(H11:L11) -> 1 | N11: 15 | O11: =60/N11 -> 4 | P11: =O11/60 -> 0.066666667 | Q11: =E11-F11 -> 1.0647333 | R11: =Таблица1[[#This Row],[Profit]]/Таблица1[[#This Row],[Price]] -> 0.26618333 | S11: =VLOOKUP($A11,'Order Composition'!$B$2:$F$10,MATCH($C11,'Order Composition'!$B$2:$F$2,0),0) -> 0.55 | T11: =S11*Q11 -> 0.58560333 | U11: =Таблица1[[#This Row],[Price]]*Таблица1[[#This Row],[Order]] -> 2.2 | V11: =Таблица1[[#This Row],[Cost(with labour)]]*Таблица1[[#This Row],[Order]] -> 1.6143967 | W11: =VLOOKUP($A11,'Mean order price'!$B$2:$H$10,7,0) -> 10 | X11: =W11*P11 -> 0.66666667
A12: Columbus | B12: =B11+1 -> 9 | C12: Entry | D12: Blin B | E12: =VLOOKUP('Menu and cost - USA by city'!D12,'Menu and cost - Russia'!$D$4:$P$29,2,FALSE)*(VLOOKUP('Menu and cost - USA by city'!A12,COGS!$B$3:$I$10,8,FALSE)/3)*0.4 -> 4 | F12: =SUMPRODUCT(H12:L12,'Mean order price'!$C$3:$G$3)*G12+P12*'Mean order price'!$H$3 -> 3.8007667 | G12: 0.3 | H12: 0.3 | I12: 0 | J12: 0.55 | K12: 0.05 | L12: 0.1 | M12: =SUM(H12:L12) -> 1 | N12: 15 | O12: =60/N12 -> 4 | P12: =O12/60 -> 0.066666667 | Q12: =E12-F12 -> 0.19923333 | R12: =Таблица1[[#This Row],[Profit]]/Таблица1[[#This Row],[Price]] -> 0.049808333 | S12: =VLOOKUP($A12,'Order Composition'!$B$2:$F$10,MATCH($C12,'Order Composition'!$B$2:$F$2,0),0) -> 0.55 | T12: =S12*Q12 -> 0.10957833 | U12: =Таблица1[[#This Row],[Price]]*Таблица1[[#This Row],[Order]] -> 2.2 | V12: =Таблица1[[#This Row],[Cost(with labour)]]*Таблица1[[#This Row],[Order]] -> 2.0904217 | W12: =VLOOKUP($A12,'Mean order price'!$B$2:$H$10,7,0) -> 10 | X12: =W12*P12 -> 0.66666667
A13: Columbus | B13: =B12+1 -> 10 | C13: Entry | D13: Blin C | E13: =VLOOKUP('Menu and cost - USA by city'!D13,'Menu and cost - Russia'!$D$4:$P$29,2,FALSE)*(VLOOKUP('Menu and cost - USA by city'!A13,COGS!$B$3:$I$10,8,FALSE)/3)*0.4 -> 4 | F13: =SUMPRODUCT(H13:L13,'Mean order price'!$C$3:$G$3)*G13+P13*'Mean order price'!$H$3 -> 4.1670667 | G13: 0.3 | H13: 0.1 | I13: 0.25 | J13: 0.5 | K13: 0.05 | L13: 0.1 | M13: =SUM(H13:L13) -> 1 | N13: 15 | O13: =60/N13 -> 4 | P13: =O13/60 -> 0.066666667 | Q13: =E13-F13 -> -0.16706667 | R13: =Таблица1[[#This Row],[Profit]]/Таблица1[[#This Row],[Price]] -> -0.041766667 | S13: =VLOOKUP($A13,'Order Composition'!$B$2:$F$10,MATCH($C13,'Order Composition'!$B$2:$F$2,0),0) -> 0.55 | T13: =S13*Q13 -> -0.091886667 | U13: =Таблица1[[#This Row],[Price]]*Таблица1[[#This Row],[Order]] -> 2.2 | V13: =Таблица1[[#This Row],[Cost(with labour)]]*Таблица1[[#This Row],[Order]] -> 2.2918867 | W13: =VLOOKUP($A13,'Mean order price'!$B$2:$H$10,7,0) -> 10 | X13: =W13*P13 -> 0.66666667
A14: Columbus | B14: =B13+1 -> 11 | C14: Entry | D14: Blin D | E14: =VLOOKUP('Menu and cost - USA by city'!D14,'Menu and cost - Russia'!$D$4:$P$29,2,FALSE)*(VLOOKUP('Menu and cost - USA by city'!A14,COGS!$B$3:$I$10,8,FALSE)/3)*0.4 -> 4 | F14: =SUMPRODUCT(H14:L14,'Mean order price'!$C$3:$G$3)*G14+P14*'Mean order price'!$H$3 -> 3.283 | G14: 0.2 | H14: 0.2 | I14: 0.4 | J14: 0.25 | K14: 0.05 | L14: 0.1 | M14: =SUM(H14:L14) -> 1 | N14: 10 | O14: =60/N14 -> 6 | P14: =O14/60 -> 0.1 | Q14: =E14-F14 -> 0.717 | R14: =Таблица1[[#This Row],[Profit]]/Таблица1[[#This Row],[Price]] -> 0.17925 | S14: =VLOOKUP($A14,'Order Composition'!$B$2:$F$10,MATCH($C14,'Order Composition'!$B$2:$F$2,0),0) -> 0.55 | T14: =S14*Q14 -> 0.39435 | U14: =Таблица1[[#This Row],[Price]]*Таблица1[[#This Row],[Order]] -> 2.2 | V14: =Таблица1[[#This Row],[Cost(with labour)]]*Таблица1[[#This Row],[Order]] -> 1.80565 | W14: =VLOOKUP($A14,'Mean order price'!$B$2:$H$10,7,0) -> 10 | X14: =W14*P14 -> 1
A15: Columbus | B15: =B14+1 -> 12 | C15: Entry | D15: Blin E | E15: =VLOOKUP('Menu and cost - USA by city'!D15,'Menu and cost - Russia'!$D$4:$P$29,2,FALSE)*(VLOOKUP('Menu and cost - USA by city'!A15,COGS!$B$3:$I$10,8,FALSE)/3)*0.4 -> 5.3333333 | F15: =SUMPRODUCT(H15:L15,'Mean order price'!$C$3:$G$3)*G15+P15*'Mean order price'!$H$3 -> 4.5025 | G15: 0.3 | H15: 0.2 | I15: 0.6 | J15: 0.05 | K15: 0.05 | L15: 0.1 | M15: =SUM(H15:L15) -> 1 | N15: 10 | O15: =60/N15 -> 6 | P15: =O15/60 -> 0.1 | Q15: =E15-F15 -> 0.83083333 | R15: =Таблица1[[#This Row],[Profit]]/Таблица1[[#This Row],[Price]] -> 0.15578125 | S15: =VLOOKUP($A15,'Order Composition'!$B$2:$F$10,MATCH($C15,'Order Composition'!$B$2:$F$2,0),0) -> 0.55 | T15: =S15*Q15 -> 0.45695833 | U15: =Таблица1[[#This Row],[Price]]*Таблица1[[#This Row],[Order]] -> 2.9333333 | V15: =Таблица1[[#This Row],[Cost(with labour)]]*Таблица1[[#This Row],[Order]] -> 2.476375 | W15: =VLOOKUP($A15,'Mean order price'!$B$2:$H$10,7,0) -> 10 | X15: =W15*P15 -> 1
A16: Columbus | B16: =B15+1 -> 13 | C16: Entry | D16: Blin F | E16: =VLOOKUP('Menu and cost - USA by city'!D16,'Menu and cost - Russia'!$D$4:$P$29,2,FALSE)*(VLOOKUP('Menu and cost - USA by city'!A16,COGS!$B$3:$I$10,8,FALSE)/3)*0.4 -> 5.3333333 | F16: =SUMPRODUCT(H16:L16,'Mean order price'!$C$3:$G$3)*G16+P16*'Mean order price'!$H$3 -> 4.4635 | G16: 0.3 | H16: 0.2 | I16: 0.5 | J16: 0.15 | K16: 0.05 | L16: 0.1 | M16: =SUM(H16:L16) -> 1 | N16: 10 | O16: =60/N16 -> 6 | P16: =O16/60 -> 0.1 | Q16: =E16-F16 -> 0.86983333 | R16: =Таблица1[[#This Row],[Profit]]/Таблица1[[#This Row],[Price]] -> 0.16309375 | S16: =VLOOKUP($A16,'Order Composition'!$B$2:$F$10,MATCH($C16,'Order Composition'!$B$2:$F$2,0),0) -> 0.55 | T16: =S16*Q16 -> 0.47840833 | U16: =Таблица1[[#This Row],[Price]]*Таблица1[[#This Row],[Order]] -> 2.9333333 | V16: =Таблица1[[#This Row],[Cost(with labour)]]*Таблица1[[#This Row],[Order]] -> 2.454925 | W16: =VLOOKUP($A16,'Mean order price'!$B$2:$H$10,7,0) -> 10 | X16: =W16*P16 -> 1
... A29: Columbus | B29: =B28+1 -> 26 | C29: Beverages | D29: Hot Drink B | E29: =VLOOKUP('Menu and cost - USA by city'!D29,'Menu and cost - Russia'!$D$4:$P$29,2,FALSE)*(VLOOKUP('Menu and cost - USA by city'!A29,COGS!$B$3:$I$10,8,FALSE)/3)*0.4 -> 2 | F29: =SUMPRODUCT(H29:L29,'Mean order price'!$C$3:$G$3)*G29+P29*'Mean order price'!$H$3 -> 1.574 | G29: 0.2 | H29: 0 | I29: 0 | J29: 0.1 | K29: 0.9 | L29: 0 | M29: =SUM(H29:L29) -> 1 | N29: 40 | O29: =60/N29 -> 1.5 | P29: =O29/60 -> 0.025 | Q29: =E29-F29 -> 0.426 | R29: =Таблица1[[#This Row],[Profit]]/Таблица1[[#This Row],[Price]] -> 0.213 | S29: =VLOOKUP($A29,'Order Composition'!$B$2:$F$10,MATCH($C29,'Order Composition'!$B$2:$F$2,0),0) -> 0.8 | T29: =S29*Q29 -> 0.3408 | U29: =Таблица1[[#This Row],[Price]]*Таблица1[[#This Row],[Order]] -> 1.6 | V29: =Таблица1[[#This Row],[Cost(with labour)]]*Таблица1[[#This Row],[Order]] -> 1.2592 | W29: =VLOOKUP($A29,'Mean order price'!$B$2:$H$10,7,0) -> 10 | X29: =W29*P29 -> 0.25
A30: Cincinnati | B30: =B29+1 -> 27 | C30: Appetizer | D30: Salad A | E30: =VLOOKUP('Menu and cost - USA by city'!D30,'Menu and cost - Russia'!$D$4:$P$29,2,FALSE)*(VLOOKUP('Menu and cost - USA by city'!A30,COGS!$B$3:$I$10,8,FALSE)/3)*0.4 -> 4.2 | F30: =SUMPRODUCT(H30:L30,'Mean order price'!$C$4:$G$4)*G30+P30*'Mean order price'!$H$4 -> 2.673 | G30: 0.2 | H30: 0 | I30: 0 | J30: 0.9 | K30: 0 | L30: 0.1 | M30: =SUM(H30:L30) -> 1 | N30: 20 | O30: =60/N30 -> 3 | P30: =O30/60 -> 0.05 | Q30: =E30-F30 -> 1.527 | R30: =Таблица1[[#This Row],[Profit]]/Таблица1[[#This Row],[Price]] -> 0.36357143 | S30: =VLOOKUP($A30,'Order Composition'!$B$2:$F$10,MATCH($C30,'Order Composition'!$B$2:$F$2,0),0) -> 0.55 | T30: =S30*Q30 -> 0.83985 | U30: =Таблица1[[#This Row],[Price]]*Таблица1[[#This Row],[Order]] -> 2.31 | V30: =Таблица1[[#This Row],[Cost(with labour)]]*Таблица1[[#This Row],[Order]] -> 1.47015 | W30: =VLOOKUP($A30,'Mean order price'!$B$2:$H$10,7,0) -> 10.5 | X30: =W30*P30 -> 0.525
A31: Cincinnati | B31: =B30+1 -> 28 | C31: Appetizer | D31: Salad B | E31: =VLOOKUP('Menu and cost - USA by city'!D31,'Menu and cost - Russia'!$D$4:$P$29,2,FALSE)*(VLOOKUP('Menu and cost - USA by city'!A31,COGS!$B$3:$I$10,8,FALSE)/3)*0.4 -> 4.2 | F31: =SUMPRODUCT(H31:L31,'Mean order price'!$C$4:$G$4)*G31+P31*'Mean order price'!$H$4 -> 2.7618 | G31: 0.2 | H31: 0 | I31: 0.2 | J31: 0.7 | K31: 0 | L31: 0.1 | M31: =SUM(H31:L31) -> 1 | N31: 20 | O31: =60/N31 -> 3 | P31: =O31/60 -> 0.05 | Q31: =E31-F31 -> 1.4382 | R31: =Таблица1[[#This Row],[Profit]]/Таблица1[[#This Row],[Price]] -> 0.34242857 | S31: =VLOOKUP($A31,'Order Composition'!$B$2:$F$10,MATCH($C31,'Order Composition'!$B$2:$F$2,0),0) -> 0.55 | T31: =S31*Q31 -> 0.79101 | U31: =Таблица1[[#This Row],[Price]]*Таблица1[[#This Row],[Order]] -> 2.31 | V31: =Таблица1[[#This Row],[Cost(with labour)]]*Таблица1[[#This Row],[Order]] -> 1.51899 | W31: =VLOOKUP($A31,'Mean order price'!$B$2:$H$10,7,0) -> 10.5 | X31: =W31*P31 -> 0.525
A32: Cincinnati | B32: =B31+1 -> 29 | C32: Appetizer | D32: Salad C | E32: =VLOOKUP('Menu and cost - USA by city'!D32,'Menu and cost - Russia'!$D$4:$P$29,2,FALSE)*(VLOOKUP('Menu and cost - USA by city'!A32,COGS!$B$3:$I$10,8,FALSE)/3)*0.4 -> 4.2 | F32: =SUMPRODUCT(H32:L32,'Mean order price'!$C$4:$G$4)*G32+P32*'Mean order price'!$H$4 -> 2.895 | G32: 0.2 | H32: 0 | I32: 0.5 | J32: 0.4 | K32: 0 | L32: 0.1 | M32: =SUM(H32:L32) -> 1 | N32: 20 | O32: =60/N32 -> 3 | P32: =O32/60 -> 0.05 | Q32: =E32-F32 -> 1.305 | R32: =Таблица1[[#This Row],[Profit]]/Таблица1[[#This Row],[Price]] -> 0.31071429 | S32: =VLOOKUP($A32,'Order Composition'!$B$2:$F$10,MATCH($C32,'Order Composition'!$B$2:$F$2,0),0) -> 0.55 | T32: =S32*Q32 -> 0.71775 | U32: =Таблица1[[#This Row],[Price]]*Таблица1[[#This Row],[Order]] -> 2.31 | V32: =Таблица1[[#This Row],[Cost(with labour)]]*Таблица1[[#This Row],[Order]] -> 1.59225 | W32: =VLOOKUP($A32,'Mean order price'!$B$2:$H$10,7,0) -> 10.5 | X32: =W32*P32 -> 0.525
A33: Cincinnati | B33: =B32+1 -> 30 | C33: Appetizer | D33: Soup A | E33: =VLOOKUP('Menu and cost - USA by city'!D33,'Menu and cost - Russia'!$D$4:$P$29,2,FALSE)*(VLOOKUP('Menu and cost - USA by city'!A33,COGS!$B$3:$I$10,8,FALSE)/3)*0.4 -> 2.8 | F33: =SUMPRODUCT(H33:L33,'Mean order price'!$C$4:$G$4)*G33+P33*'Mean order price'!$H$4 -> 1.7364 | G33: 0.2 | H33: 0.1 | I33: 0 | J33: 0.4 | K33: 0.1 | L33: 0.4 | M33: =SUM(H33:L33) -> 1 | N33: 60 | O33: =60/N33 -> 1 | P33: =O33/60 -> 0.016666667 | Q33: =E33-F33 -> 1.0636 | R33: =Таблица1[[#This Row],[Profit]]/Таблица1[[#This Row],[Price]] -> 0.37985714 | S33: =VLOOKUP($A33,'Order Composition'!$B$2:$F$10,MATCH($C33,'Order Composition'!$B$2:$F$2,0),0) -> 0.55 | T33: =S33*Q33 -> 0.58498 | U33: =Таблица1[[#This Row],[Price]]*Таблица1[[#This Row],[Order]] -> 1.54 | V33: =Таблица1[[#This Row],[Cost(with labour)]]*Таблица1[[#This Row],[Order]] -> 0.95502 | W33: =VLOOKUP($A33,'Mean order price'!$B$2:$H$10,7,0) -> 10.5 | X33: =W33*P33 -> 0.175
A34: Cincinnati | B34: =B33+1 -> 31 | C34: Appetizer | D34: Soup B | E34: =VLOOKUP('Menu and cost - USA by city'!D34,'Menu and cost - Russia'!$D$4:$P$29,2,FALSE)*(VLOOKUP('Menu and cost - USA by city'!A34,COGS!$B$3:$I$10,8,FALSE)/3)*0.4 -> 2.8 | F34: =SUMPRODUCT(H34:L34,'Mean order price'!$C$4:$G$4)*G34+P34*'Mean order price'!$H$4 -> 1.9452 | G34: 0.2 | H34: 0.1 | I34: 0.2 | J34: 0.3 | K34: 0.1 | L34: 0.3 | M34: =SUM(H34:L34) -> 1 | N34: 60 | O34: =60/N34 -> 1 | P34: =O34/60 -> 0.016666667 | Q34: =E34-F34 -> 0.8548 | R34: =Таблица1[[#This Row],[Profit]]/Таблица1[[#This Row],[Price]] -> 0.30528571 | S34: =VLOOKUP($A34,'Order Composition'!$B$2:$F$10,MATCH($C34,'Order Composition'!$B$2:$F$2,0),0) -> 0.55 | T34: =S34*Q34 -> 0.47014 | U34: =Таблица1[[#This Row],[Price]]*Таблица1[[#This Row],[Order]] -> 1.54 | V34: =Таблица1[[#This Row],[Cost(with labour)]]*Таблица1[[#This Row],[Order]] -> 1.06986 | W34: =VLOOKUP($A34,'Mean order price'!$B$2:$H$10,7,0) -> 10.5 | X34: =W34*P34 -> 0.175
A35: Cincinnati | B35: =B34+1 -> 32 | C35: Appetizer | D35: Pirozhok A | E35: =VLOOKUP('Menu and cost - USA by city'!D35,'Menu and cost - Russia'!$D$4:$P$29,2,FALSE)*(VLOOKUP('Menu and cost - USA by city'!A35,COGS!$B$3:$I$10,8,FALSE)/3)*0.4 -> 1.4 | F35: =SUMPRODUCT(H35:L35,'Mean order price'!$C$4:$G$4)*G35+P35*'Mean order price'!$H$4 -> 1.3446 | G35: 0.1 | H35: 0.1 | I35: 0 | J35: 0.75 | K35: 0.05 | L35: 0.1 | M35: =SUM(H35:L35) -> 1 | N35: 30 | O35: =60/N35 -> 2 | P35: =O35/60 -> 0.033333333 | Q35: =E35-F35 -> 0.0554 | R35: =Таблица1[[#This Row],[Profit]]/Таблица1[[#This Row],[Price]] -> 0.039571429 | S35: =VLOOKUP($A35,'Order Composition'!$B$2:$F$10,MATCH($C35,'Order Composition'!$B$2:$F$2,0),0) -> 0.55 | T35: =S35*Q35 -> 0.03047 | U35: =Таблица1[[#This Row],[Price]]*Таблица1[[#This Row],[Order]] -> 0.77 | V35: =Таблица1[[#This Row],[Cost(with labour)]]*Таблица1[[#This Row],[Order]] -> 0.73953 | W35: =VLOOKUP($A35,'Mean order price'!$B$2:$H$10,7,0) -> 10.5 | X35: =W35*P35 -> 0.35
A36: Cincinnati | B36: =B35+1 -> 33 | C36: Appetizer | D36: Pirozhok B | E36: =VLOOKUP('Menu and cost - USA by city'!D36,'Menu and cost - Russia'!$D$4:$P$29,2,FALSE)*(VLOOKUP('Menu and cost - USA by city'!A36,COGS!$B$3:$I$10,8,FALSE)/3)*0.4 -> 1.4 | F36: =SUMPRODUCT(H36:L36,'Mean order price'!$C$4:$G$4)*G36+P36*'Mean order price'!$H$4 -> 1.4556 | G36: 0.1 | H36: 0.1 | I36: 0.5 | J36: 0.25 | K36: 0.05 | L36: 0.1 | M36: =SUM(H36:L36) -> 1 | N36: 30 | O36: =60/N36 -> 2 | P36: =O36/60 -> 0.033333333 | Q36: =E36-F36 -> -0.0556 | R36: =Таблица1[[#This Row],[Profit]]/Таблица1[[#This Row],[Price]] -> -0.039714286 | S36: =VLOOKUP($A36,'Order Composition'!$B$2:$F$10,MATCH($C36,'Order Composition'!$B$2:$F$2,0),0) -> 0.55 | T36: =S36*Q36 -> -0.03058 | U36: =Таблица1[[#This Row],[Price]]*Таблица1[[#This Row],[Order]] -> 0.77 | V36: =Таблица1[[#This Row],[Cost(with labour)]]*Таблица1[[#This Row],[Order]] -> 0.80058 | W36: =VLOOKUP($A36,'Mean order price'!$B$2:$H$10,7,0) -> 10.5 | X36: =W36*P36 -> 0.35
A37: Cincinnati | B37: =B36+1 -> 34 | C37: Entry | D37: Blin A | E37: =VLOOKUP('Menu and cost - USA by city'!D37,'Menu and cost - Russia'!$D$4:$P$29,2,FALSE)*(VLOOKUP('Menu and cost - USA by city'!A37,COGS!$B$3:$I$10,8,FALSE)/3)*0.4 -> 4.2 | F37: =SUMPRODUCT(H37:L37,'Mean order price'!$C$4:$G$4)*G37+P37*'Mean order price'!$H$4 -> 2.6892 | G37: 0.2 | H37: 0.1 | I37: 0 | J37: 0.75 | K37: 0.05 | L37: 0.1 | M37: =SUM(H37:L37) -> 1 | N37: 15 | O37: =60/N37 -> 4 | P37: =O37/60 -> 0.066666667 | Q37: =E37-F37 -> 1.5108 | R37: =Таблица1[[#This Row],[Profit]]/Таблица1[[#This Row],[Price]] -> 0.35971429 | S37: =VLOOKUP($A37,'Order Composition'!$B$2:$F$10,MATCH($C37,'Order Composition'!$B$2:$F$2,0),0) -> 0.6 | T37: =S37*Q37 -> 0.90648 | U37: =Таблица1[[#This Row],[Price]]*Таблица1[[#This Row],[Order]] -> 2.52 | V37: =Таблица1[[#This Row],[Cost(with labour)]]*Таблица1[[#This Row],[Order]] -> 1.61352 | W37: =VLOOKUP($A37,'Mean order price'!$B$2:$H$10,7,0) -> 10.5 | X37: =W37*P37 -> 0.7
A38: Cincinnati | B38: =B37+1 -> 35 | C38: Entry | D38: Blin B | E38: =VLOOKUP('Menu and cost - USA by city'!D38,'Menu and cost - Russia'!$D$4:$P$29,2,FALSE)*(VLOOKUP('Menu and cost - USA by city'!A38,COGS!$B$3:$I$10,8,FALSE)/3)*0.4 -> 4.2 | F38: =SUMPRODUCT(H38:L38,'Mean order price'!$C$4:$G$4)*G38+P38*'Mean order price'!$H$4 -> 3.4108 | G38: 0.3 | H38: 0.3 | I38: 0 | J38: 0.55 | K38: 0.05 | L38: 0.1 | M38: =SUM(H38:L38) -> 1 | N38: 15 | O38: =60/N38 -> 4 | P38: =O38/60 -> 0.066666667 | Q38: =E38-F38 -> 0.7892 | R38: =Таблица1[[#This Row],[Profit]]/Таблица1[[#This Row],[Price]] -> 0.18790476 | S38: =VLOOKUP($A38,'Order Composition'!$B$2:$F$10,MATCH($C38,'Order Composition'!$B$2:$F$2,0),0) -> 0.6 | T38: =S38*Q38 -> 0.47352 | U38: =Таблица1[[#This Row],[Price]]*Таблица1[[#This Row],[Order]] -> 2.52 | V38: =Таблица1[[#This Row],[Cost(with labour)]]*Таблица1[[#This Row],[Order]] -> 2.04648 | W38: =VLOOKUP($A38,'Mean order price'!$B$2:$H$10,7,0) -> 10.5 | X38: =W38*P38 -> 0.7
A39: Cincinnati | B39: =B38+1 -> 36 | C39: Entry | D39: Blin C | E39: =VLOOKUP('Menu and cost - USA by city'!D39,'Menu and cost - Russia'!$D$4:$P$29,2,FALSE)*(VLOOKUP('Menu and cost - USA by city'!A39,COGS!$B$3:$I$10,8,FALSE)/3)*0.4 -> 4.2 | F39: =SUMPRODUCT(H39:L39,'Mean order price'!$C$4:$G$4)*G39+P39*'Mean order price'!$H$4 -> 3.8503 | G39: 0.3 | H39: 0.1 | I39: 0.25 | J39: 0.5 | K39: 0.05 | L39: 0.1 | M39: =SUM(H39:L39) -> 1 | N39: 15 | O39: =60/N39 -> 4 | P39: =O39/60 -> 0.066666667 | Q39: =E39-F39 -> 0.3497 | R39: =Таблица1[[#This Row],[Profit]]/Таблица1[[#This Row],[Price]] -> 0.083261905 | S39: =VLOOKUP($A39,'Order Composition'!$B$2:$F$10,MATCH($C39,'Order Composition'!$B$2:$F$2,0),0) -> 0.6 | T39: =S39*Q39 -> 0.20982 | U39: =Таблица1[[#This Row],[Price]]*Таблица1[[#This Row],[Order]] -> 2.52 | V39: =Таблица1[[#This Row],[Cost(with labour)]]*Таблица1[[#This Row],[Order]] -> 2.31018 | W39: =VLOOKUP($A39,'Mean order price'!$B$2:$H$10,7,0) -> 10.5 | X39: =W39*P39 -> 0.7
A40: Cincinnati | B40: =B39+1 -> 37 | C40: Entry | D40: Blin D | E40: =VLOOKUP('Menu and cost - USA by city'!D40,'Menu and cost - Russia'!$D$4:$P$29,2,FALSE)*(VLOOKUP('Menu and cost - USA by city'!A40,COGS!$B$3:$I$10,8,FALSE)/3)*0.4 -> 4.2 | F40: =SUMPRODUCT(H40:L40,'Mean order price'!$C$4:$G$4)*G40+P40*'Mean order price'!$H$4 -> 3.1258 | G40: 0.2 | H40: 0.2 | I40: 0.4 | J40: 0.25 | K40: 0.05 | L40: 0.1 | M40: =SUM(H40:L40) -> 1 | N40: 10 | O40: =60/N40 -> 6 | P40: =O40/60 -> 0.1 | Q40: =E40-F40 -> 1.0742 | R40: =Таблица1[[#This Row],[Profit]]/Таблица1[[#This Row],[Price]] -> 0.2557619 | S40: =VLOOKUP($A40,'Order Composition'!$B$2:$F$10,MATCH($C40,'Order Composition'!$B$2:$F$2,0),0) -> 0.6 | T40: =S40*Q40 -> 0.64452 | U40: =Таблица1[[#This Row],[Price]]*Таблица1[[#This Row],[Order]] -> 2.52 | V40: =Таблица1[[#This Row],[Cost(with labour)]]*Таблица1[[#This Row],[Order]] -> 1.87548 | W40: =VLOOKUP($A40,'Mean order price'!$B$2:$H$10,7,0) -> 10.5 | X40: =W40*P40 -> 1.05
A41: Cincinnati | B41: =B40+1 -> 38 | C41: Entry | D41: Blin E | E41: =VLOOKUP('Menu and cost - USA by city'!D41,'Menu and cost - Russia'!$D$4:$P$29,2,FALSE)*(VLOOKUP('Menu and cost - USA by city'!A41,COGS!$B$3:$I$10,8,FALSE)/3)*0.4 -> 5.6 | F41: =SUMPRODUCT(H41:L41,'Mean order price'!$C$4:$G$4)*G41+P41*'Mean order price'!$H$4 -> 4.2969 | G41: 0.3 | H41: 0.2 | I41: 0.6 | J41: 0.05 | K41: 0.05 | L41: 0.1 | M41: =SUM(H41:L41) -> 1 | N41: 10 | O41: =60/N41 -> 6 | P41: =O41/60 -> 0.1 | Q41: =E41-F41 -> 1.3031 | R41: =Таблица1[[#This Row],[Profit]]/Таблица1[[#This Row],[Price]] -> 0.23269643 | S41: =VLOOKUP($A41,'Order Composition'!$B$2:$F$10,MATCH($C41,'Order Composition'!$B$2:$F$2,0),0) -> 0.6 | T41: =S41*Q41 -> 0.78186 | U41: =Таблица1[[#This Row],[Price]]*Таблица1[[#This Row],[Order]] -> 3.36 | V41: =Таблица1[[#This Row],[Cost(with labour)]]*Таблица1[[#This Row],[Order]] -> 2.57814 | W41: =VLOOKUP($A41,'Mean order price'!$B$2:$H$10,7,0) -> 10.5 | X41: =W41*P41 -> 1.05
... A55: Cincinnati | B55: =B54+1 -> 52 | C55: Beverages | D55: Hot Drink B | E55: =VLOOKUP('Menu and cost - USA by city'!D55,'Menu and cost - Russia'!$D$4:$P$29,2,FALSE)*(VLOOKUP('Menu and cost - USA by city'!A55,COGS!$B$3:$I$10,8,FALSE)/3)*0.4 -> 2.1 | F55: =SUMPRODUCT(H55:L55,'Mean order price'!$C$4:$G$4)*G55+P55*'Mean order price'!$H$4 -> 1.3101 | G55: 0.2 | H55: 0 | I55: 0 | J55: 0.1 | K55: 0.9 | L55: 0 | M55: =SUM(H55:L55) -> 1 | N55: 40 | O55: =60/N55 -> 1.5 | P55: =O55/60 -> 0.025 | Q55: =E55-F55 -> 0.7899 | R55: =Таблица1[[#This Row],[Profit]]/Таблица1[[#This Row],[Price]] -> 0.37614286 | S55: =VLOOKUP($A55,'Order Composition'!$B$2:$F$10,MATCH($C55,'Order Composition'!$B$2:$F$2,0),0) -> 0.8 | T55: =S55*Q55 -> 0.63192 | U55: =Таблица1[[#This Row],[Price]]*Таблица1[[#This Row],[Order]] -> 1.68 | V55: =Таблица1[[#This Row],[Cost(with labour)]]*Таблица1[[#This Row],[Order]] -> 1.04808 | W55: =VLOOKUP($A55,'Mean order price'!$B$2:$H$10,7,0) -> 10.5 | X55: =W55*P55 -> 0.2625
A56: Cleveland | B56: =B55+1 -> 53 | C56: Appetizer | D56: Salad A | E56: =VLOOKUP('Menu and cost - USA by city'!D56,'Menu and cost - Russia'!$D$4:$P$29,2,FALSE)*(VLOOKUP('Menu and cost - USA by city'!A56,COGS!$B$3:$I$10,8,FALSE)/3)*0.4 -> 4.4 | F56: =SUMPRODUCT(H56:L56,'Mean order price'!$C$5:$G$5)*G56+P56*'Mean order price'!$H$5 -> 2.905 | G56: 0.2 | H56: 0 | I56: 0 | J56: 0.9 | K56: 0 | L56: 0.1 | M56: =SUM(H56:L56) -> 1 | N56: 20 | O56: =60/N56 -> 3 | P56: =O56/60 -> 0.05 | Q56: =E56-F56 -> 1.495 | R56: =Таблица1[[#This Row],[Profit]]/Таблица1[[#This Row],[Price]] -> 0.33977273 | S56: =VLOOKUP($A56,'Order Composition'!$B$2:$F$10,MATCH($C56,'Order Composition'!$B$2:$F$2,0),0) -> 0.4 | T56: =S56*Q56 -> 0.598 | U56: =Таблица1[[#This Row],[Price]]*Таблица1[[#This Row],[Order]] -> 1.76 | V56: =Таблица1[[#This Row],[Cost(with labour)]]*Таблица1[[#This Row],[Order]] -> 1.162 | W56: =VLOOKUP($A56,'Mean order price'!$B$2:$H$10,7,0) -> 11 | X56: =W56*P56 -> 0.55
A57: Cleveland | B57: =B56+1 -> 54 | C57: Appetizer | D57: Salad B | E57: =VLOOKUP('Menu and cost - USA by city'!D57,'Menu and cost - Russia'!$D$4:$P$29,2,FALSE)*(VLOOKUP('Menu and cost - USA by city'!A57,COGS!$B$3:$I$10,8,FALSE)/3)*0.4 -> 4.4 | F57: =SUMPRODUCT(H57:L57,'Mean order price'!$C$5:$G$5)*G57+P57*'Mean order price'!$H$5 -> 2.959 | G57: 0.2 | H57: 0 | I57: 0.2 | J57: 0.7 | K57: 0 | L57: 0.1 | M57: =SUM(H57:L57) -> 1 | N57: 20 | O57: =60/N57 -> 3 | P57: =O57/60 -> 0.05 | Q57: =E57-F57 -> 1.441 | R57: =Таблица1[[#This Row],[Profit]]/Таблица1[[#This Row],[Price]] -> 0.3275 | S57: =VLOOKUP($A57,'Order Composition'!$B$2:$F$10,MATCH($C57,'Order Composition'!$B$2:$F$2,0),0) -> 0.4 | T57: =S57*Q57 -> 0.5764 | U57: =Таблица1[[#This Row],[Price]]*Таблица1[[#This Row],[Order]] -> 1.76 | V57: =Таблица1[[#This Row],[Cost(with labour)]]*Таблица1[[#This Row],[Order]] -> 1.1836 | W57: =VLOOKUP($A57,'Mean order price'!$B$2:$H$10,7,0) -> 11 | X57: =W57*P57 -> 0.55
A58: Cleveland | B58: =B57+1 -> 55 | C58: Appetizer | D58: Salad C | E58: =VLOOKUP('Menu and cost - USA by city'!D58,'Menu and cost - Russia'!$D$4:$P$29,2,FALSE)*(VLOOKUP('Menu and cost - USA by city'!A58,COGS!$B$3:$I$10,8,FALSE)/3)*0.4 -> 4.4 | F58: =SUMPRODUCT(H58:L58,'Mean order price'!$C$5:$G$5)*G58+P58*'Mean order price'!$H$5 -> 3.04 | G58: 0.2 | H58: 0 | I58: 0.5 | J58: 0.4 | K58: 0 | L58: 0.1 | M58: =SUM(H58:L58) -> 1 | N58: 20 | O58: =60/N58 -> 3 | P58: =O58/60 -> 0.05 | Q58: =E58-F58 -> 1.36 | R58: =Таблица1[[#This Row],[Profit]]/Таблица1[[#This Row],[Price]] -> 0.30909091 | S58: =VLOOKUP($A58,'Order Composition'!$B$2:$F$10,MATCH($C58,'Order Composition'!$B$2:$F$2,0),0) -> 0.4 | T58: =S58*Q58 -> 0.544 | U58: =Таблица1[[#This Row],[Price]]*Таблица1[[#This Row],[Order]] -> 1.76 | V58: =Таблица1[[#This Row],[Cost(with labour)]]*Таблица1[[#This Row],[Order]] -> 1.216 | W58: =VLOOKUP($A58,'Mean order price'!$B$2:$H$10,7,0) -> 11 | X58: =W58*P58 -> 0.55
A59: Cleveland | B59: =B58+1 -> 56 | C59: Appetizer | D59: Soup A | E59: =VLOOKUP('Menu and cost - USA by city'!D59,'Menu and cost - Russia'!$D$4:$P$29,2,FALSE)*(VLOOKUP('Menu and cost - USA by city'!A59,COGS!$B$3:$I$10,8,FALSE)/3)*0.4 -> 2.9333333 | F59: =SUMPRODUCT(H59:L59,'Mean order price'!$C$5:$G$5)*G59+P59*'Mean order price'!$H$5 -> 1.8639333 | G59: 0.2 | H59: 0.1 | I59: 0 | J59: 0.4 | K59: 0.1 | L59: 0.4 | M59: =SUM(H59:L59) -> 1 | N59: 60 | O59: =60/N59 -> 1 | P59: =O59/60 -> 0.016666667 | Q59: =E59-F59 -> 1.0694 | R59: =Таблица1[[#This Row],[Profit]]/Таблица1[[#This Row],[Price]] -> 0.36456818 | S59: =VLOOKUP($A59,'Order Composition'!$B$2:$F$10,MATCH($C59,'Order Composition'!$B$2:$F$2,0),0) -> 0.4 | T59: =S59*Q59 -> 0.42776 | U59: =Таблица1[[#This Row],[Price]]*Таблица1[[#This Row],[Order]] -> 1.1733333 | V59: =Таблица1[[#This Row],[Cost(with labour)]]*Таблица1[[#This Row],[Order]] -> 0.74557333 | W59: =VLOOKUP($A59,'Mean order price'!$B$2:$H$10,7,0) -> 11 | X59: =W59*P59 -> 0.18333333
A60: Cleveland | B60: =B59+1 -> 57 | C60: Appetizer | D60: Soup B | E60: =VLOOKUP('Menu and cost - USA by city'!D60,'Menu and cost - Russia'!$D$4:$P$29,2,FALSE)*(VLOOKUP('Menu and cost - USA by city'!A60,COGS!$B$3:$I$10,8,FALSE)/3)*0.4 -> 2.9333333 | F60: =SUMPRODUCT(H60:L60,'Mean order price'!$C$5:$G$5)*G60+P60*'Mean order price'!$H$5 -> 2.0529333 | G60: 0.2 | H60: 0.1 | I60: 0.2 | J60: 0.3 | K60: 0.1 | L60: 0.3 | M60: =SUM(H60:L60) -> 1 | N60: 60 | O60: =60/N60 -> 1 | P60: =O60/60 -> 0.016666667 | Q60: =E60-F60 -> 0.8804 | R60: =Таблица1[[#This Row],[Profit]]/Таблица1[[#This Row],[Price]] -> 0.30013636 | S60: =VLOOKUP($A60,'Order Composition'!$B$2:$F$10,MATCH($C60,'Order Composition'!$B$2:$F$2,0),0) -> 0.4 | T60: =S60*Q60 -> 0.35216 | U60: =Таблица1[[#This Row],[Price]]*Таблица1[[#This Row],[Order]] -> 1.1733333 | V60: =Таблица1[[#This Row],[Cost(with labour)]]*Таблица1[[#This Row],[Order]] -> 0.82117333 | W60: =VLOOKUP($A60,'Mean order price'!$B$2:$H$10,7,0) -> 11 | X60: =W60*P60 -> 0.18333333
A61: Cleveland | B61: =B60+1 -> 58 | C61: Appetizer | D61: Pirozhok A | E61: =VLOOKUP('Menu and cost - USA by city'!D61,'Menu and cost - Russia'!$D$4:$P$29,2,FALSE)*(VLOOKUP('Menu and cost - USA by city'!A61,COGS!$B$3:$I$10,8,FALSE)/3)*0.4 -> 1.4666667 | F61: =SUMPRODUCT(H61:L61,'Mean order price'!$C$5:$G$5)*G61+P61*'Mean order price'!$H$5 -> 1.4457167 | G61: 0.1 | H61: 0.1 | I61: 0 | J61: 0.75 | K61: 0.05 | L61: 0.1 | M61: =SUM(H61:L61) -> 1 | N61: 30 | O61: =60/N61 -> 2 | P61: =O61/60 -> 0.033333333 | Q61: =E61-F61 -> 0.02095 | R61: =Таблица1[[#This Row],[Profit]]/Таблица1[[#This Row],[Price]] -> 0.014284091 | S61: =VLOOKUP($A61,'Order Composition'!$B$2:$F$10,MATCH($C61,'Order Composition'!$B$2:$F$2,0),0) -> 0.4 | T61: =S61*Q61 -> 0.00838 | U61: =Таблица1[[#This Row],[Price]]*Таблица1[[#This Row],[Order]] -> 0.58666667 | V61: =Таблица1[[#This Row],[Cost(with labour)]]*Таблица1[[#This Row],[Order]] -> 0.57828667 | W61: =VLOOKUP($A61,'Mean order price'!$B$2:$H$10,7,0) -> 11 | X61: =W61*P61 -> 0.36666667
A62: Cleveland | B62: =B61+1 -> 59 | C62: Appetizer | D62: Pirozhok B | E62: =VLOOKUP('Menu and cost - USA by city'!D62,'Menu and cost - Russia'!$D$4:$P$29,2,FALSE)*(VLOOKUP('Menu and cost - USA by city'!A62,COGS!$B$3:$I$10,8,FALSE)/3)*0.4 -> 1.4666667 | F62: =SUMPRODUCT(H62:L62,'Mean order price'!$C$5:$G$5)*G62+P62*'Mean order price'!$H$5 -> 1.5132167 | G62: 0.1 | H62: 0.1 | I62: 0.5 | J62: 0.25 | K62: 0.05 | L62: 0.1 | M62: =SUM(H62:L62) -> 1 | N62: 30 | O62: =60/N62 -> 2 | P62: =O62/60 -> 0.033333333 | Q62: =E62-F62 -> -0.04655 | R62: =Таблица1[[#This Row],[Profit]]/Таблица1[[#This Row],[Price]] -> -0.031738636 | S62: =VLOOKUP($A62,'Order Composition'!$B$2:$F$10,MATCH($C62,'Order Composition'!$B$2:$F$2,0),0) -> 0.4 | T62: =S62*Q62 -> -0.01862 | U62: =Таблица1[[#This Row],[Price]]*Таблица1[[#This Row],[Order]] -> 0.58666667 | V62: =Таблица1[[#This Row],[Cost(with labour)]]*Таблица1[[#This Row],[Order]] -> 0.60528667 | W62: =VLOOKUP($A62,'Mean order price'!$B$2:$H$10,7,0) -> 11 | X62: =W62*P62 -> 0.36666667
A63: Cleveland | B63: =B62+1 -> 60 | C63: Entry | D63: Blin A | E63: =VLOOKUP('Menu and cost - USA by city'!D63,'Menu and cost - Russia'!$D$4:$P$29,2,FALSE)*(VLOOKUP('Menu and cost - USA by city'!A63,COGS!$B$3:$I$10,8,FALSE)/3)*0.4 -> 4.4 | F63: =SUMPRODUCT(H63:L63,'Mean order price'!$C$5:$G$5)*G63+P63*'Mean order price'!$H$5 -> 2.8914333 | G63: 0.2 | H63: 0.1 | I63: 0 | J63: 0.75 | K63: 0.05 | L63: 0.1 | M63: =SUM(H63:L63) -> 1 | N63: 15 | O63: =60/N63 -> 4 | P63: =O63/60 -> 0.066666667 | Q63: =E63-F63 -> 1.5085667 | R63: =Таблица1[[#This Row],[Profit]]/Таблица1[[#This Row],[Price]] -> 0.34285606 | S63: =VLOOKUP($A63,'Order Composition'!$B$2:$F$10,MATCH($C63,'Order Composition'!$B$2:$F$2,0),0) -> 0.85 | T63: =S63*Q63 -> 1.2822817 | U63: =Таблица1[[#This Row],[Price]]*Таблица1[[#This Row],[Order]] -> 3.74 | V63: =Таблица1[[#This Row],[Cost(with labour)]]*Таблица1[[#This Row],[Order]] -> 2.4577183 | W63: =VLOOKUP($A63,'Mean order price'!$B$2:$H$10,7,0) -> 11 | X63: =W63*P63 -> 0.73333333
A64: Cleveland | B64: =B63+1 -> 61 | C64: Entry | D64: Blin B | E64: =VLOOKUP('Menu and cost - USA by city'!D64,'Menu and cost - Russia'!$D$4:$P$29,2,FALSE)*(VLOOKUP('Menu and cost - USA by city'!A64,COGS!$B$3:$I$10,8,FALSE)/3)*0.4 -> 4.4 | F64: =SUMPRODUCT(H64:L64,'Mean order price'!$C$5:$G$5)*G64+P64*'Mean order price'!$H$5 -> 3.5972833 | G64: 0.3 | H64: 0.3 | I64: 0 | J64: 0.55 | K64: 0.05 | L64: 0.1 | M64: =SUM(H64:L64) -> 1 | N64: 15 | O64: =60/N64 -> 4 | P64: =O64/60 -> 0.066666667 | Q64: =E64-F64 -> 0.80271667 | R64: =Таблица1[[#This Row],[Profit]]/Таблица1[[#This Row],[Price]] -> 0.18243561 | S64: =VLOOKUP($A64,'Order Composition'!$B$2:$F$10,MATCH($C64,'Order Composition'!$B$2:$F$2,0),0) -> 0.85 | T64: =S64*Q64 -> 0.68230917 | U64: =Таблица1[[#This Row],[Price]]*Таблица1[[#This Row],[Order]] -> 3.74 | V64: =Таблица1[[#This Row],[Cost(with labour)]]*Таблица1[[#This Row],[Order]] -> 3.0576908 | W64: =VLOOKUP($A64,'Mean order price'!$B$2:$H$10,7,0) -> 11 | X64: =W64*P64 -> 0.73333333
A65: Cleveland | B65: =B64+1 -> 62 | C65: Entry | D65: Blin C | E65: =VLOOKUP('Menu and cost - USA by city'!D65,'Menu and cost - Russia'!$D$4:$P$29,2,FALSE)*(VLOOKUP('Menu and cost - USA by city'!A65,COGS!$B$3:$I$10,8,FALSE)/3)*0.4 -> 4.4 | F65: =SUMPRODUCT(H65:L65,'Mean order price'!$C$5:$G$5)*G65+P65*'Mean order price'!$H$5 -> 4.0717333 | G65: 0.3 | H65: 0.1 | I65: 0.25 | J65: 0.5 | K65: 0.05 | L65: 0.1 | M65: =SUM(H65:L65) -> 1 | N65: 15 | O65: =60/N65 -> 4 | P65: =O65/60 -> 0.066666667 | Q65: =E65-F65 -> 0.32826667 | R65: =Таблица1[[#This Row],[Profit]]/Таблица1[[#This Row],[Price]] -> 0.074606061 | S65: =VLOOKUP($A65,'Order Composition'!$B$2:$F$10,MATCH($C65,'Order Composition'!$B$2:$F$2,0),0) -> 0.85 | T65: =S65*Q65 -> 0.27902667 | U65: =Таблица1[[#This Row],[Price]]*Таблица1[[#This Row],[Order]] -> 3.74 | V65: =Таблица1[[#This Row],[Cost(with labour)]]*Таблица1[[#This Row],[Order]] -> 3.4609733 | W65: =VLOOKUP($A65,'Mean order price'!$B$2:$H$10,7,0) -> 11 | X65: =W65*P65 -> 0.73333333
A66: Cleveland | B66: =B65+1 -> 63 | C66: Entry | D66: Blin D | E66: =VLOOKUP('Menu and cost - USA by city'!D66,'Menu and cost - Russia'!$D$4:$P$29,2,FALSE)*(VLOOKUP('Menu and cost - USA by city'!A66,COGS!$B$3:$I$10,8,FALSE)/3)*0.4 -> 4.4 | F66: =SUMPRODUCT(H66:L66,'Mean order price'!$C$5:$G$5)*G66+P66*'Mean order price'!$H$5 -> 3.2417 | G66: 0.2 | H66: 0.2 | I66: 0.4 | J66: 0.25 | K66: 0.05 | L66: 0.1 | M66: =SUM(H66:L66) -> 1 | N66: 10 | O66: =60/N66 -> 6 | P66: =O66/60 -> 0.1 | Q66: =E66-F66 -> 1.1583 | R66: =Таблица1[[#This Row],[Profit]]/Таблица1[[#This Row],[Price]] -> 0.26325 | S66: =VLOOKUP($A66,'Order Composition'!$B$2:$F$10,MATCH($C66,'Order Composition'!$B$2:$F$2,0),0) -> 0.85 | T66: =S66*Q66 -> 0.984555 | U66: =Таблица1[[#This Row],[Price]]*Таблица1[[#This Row],[Order]] -> 3.74 | V66: =Таблица1[[#This Row],[Cost(with labour)]]*Таблица1[[#This Row],[Order]] -> 2.755445 | W66: =VLOOKUP($A66,'Mean order price'!$B$2:$H$10,7,0) -> 11 | X66: =W66*P66 -> 1.1
A67: Cleveland | B67: =B66+1 -> 64 | C67: Entry | D67: Blin E | E67: =VLOOKUP('Menu and cost - USA by city'!D67,'Menu and cost - Russia'!$D$4:$P$29,2,FALSE)*(VLOOKUP('Menu and cost - USA by city'!A67,COGS!$B$3:$I$10,8,FALSE)/3)*0.4 -> 5.8666667 | F67: =SUMPRODUCT(H67:L67,'Mean order price'!$C$5:$G$5)*G67+P67*'Mean order price'!$H$5 -> 4.39355 | G67: 0.3 | H67: 0.2 | I67: 0.6 | J67: 0.05 | K67: 0.05 | L67: 0.1 | M67: =SUM(H67:L67) -> 1 | N67: 10 | O67: =60/N67 -> 6 | P67: =O67/60 -> 0.1 | Q67: =E67-F67 -> 1.4731167 | R67: =Таблица1[[#This Row],[Profit]]/Таблица1[[#This Row],[Price]] -> 0.25109943 | S67: =VLOOKUP($A67,'Order Composition'!$B$2:$F$10,MATCH($C67,'Order Composition'!$B$2:$F$2,0),0) -> 0.85 | T67: =S67*Q67 -> 1.2521492 | U67: =Таблица1[[#This Row],[Price]]*Таблица1[[#This Row],[Order]] -> 4.9866667 | V67: =Таблица1[[#This Row],[Cost(with labour)]]*Таблица1[[#This Row],[Order]] -> 3.7345175 | W67: =VLOOKUP($A67,'Mean order price'!$B$2:$H$10,7,0) -> 11 | X67: =W67*P67 -> 1.1
... A81: Cleveland | B81: =B80+1 -> 78 | C81: Beverages | D81: Hot Drink B | E81: =VLOOKUP('Menu and cost - USA by city'!D81,'Menu and cost - Russia'!$D$4:$P$29,2,FALSE)*(VLOOKUP('Menu and cost - USA by city'!A81,COGS!$B$3:$I$10,8,FALSE)/3)*0.4 -> 2.2 | F81: =SUMPRODUCT(H81:L81,'Mean order price'!$C$5:$G$5)*G81+P81*'Mean order price'!$H$5 -> 1.46 | G81: 0.2 | H81: 0 | I81: 0 | J81: 0.1 | K81: 0.9 | L81: 0 | M81: =SUM(H81:L81) -> 1 | N81: 40 | O81: =60/N81 -> 1.5 | P81: =O81/60 -> 0.025 | Q81: =E81-F81 -> 0.74 | R81: =Таблица1[[#This Row],[Profit]]/Таблица1[[#This Row],[Price]] -> 0.33636364 | S81: =VLOOKUP($A81,'Order Composition'!$B$2:$F$10,MATCH($C81,'Order Composition'!$B$2:$F$2,0),0) -> 0.75 | T81: =S81*Q81 -> 0.555 | U81: =Таблица1[[#This Row],[Price]]*Таблица1[[#This Row],[Order]] -> 1.65 | V81: =Таблица1[[#This Row],[Cost(with labour)]]*Таблица1[[#This Row],[Order]] -> 1.095 | W81: =VLOOKUP($A81,'Mean order price'!$B$2:$H$10,7,0) -> 11 | X81: =W81*P81 -> 0.275
A82: Las Vegas | B82: =B81+1 -> 79 | C82: Appetizer | D82: Salad A | E82: =VLOOKUP('Menu and cost - USA by city'!D82,'Menu and cost - Russia'!$D$4:$P$29,2,FALSE)*(VLOOKUP('Menu and cost - USA by city'!A82,COGS!$B$3:$I$10,8,FALSE)/3)*0.4 -> 3.6 | F82: =SUMPRODUCT(H82:L82,'Mean order price'!$C$6:$G$6)*G82+P82*'Mean order price'!$H$6 -> 3.4628 | G82: 0.2 | H82: 0 | I82: 0 | J82: 0.9 | K82: 0 | L82: 0.1 | M82: =SUM(H82:L82) -> 1 | N82: 20 | O82: =60/N82 -> 3 | P82: =O82/60 -> 0.05 | Q82: =E82-F82 -> 0.1372 | R82: =Таблица1[[#This Row],[Profit]]/Таблица1[[#This Row],[Price]] -> 0.038111111 | S82: =VLOOKUP($A82,'Order Composition'!$B$2:$F$10,MATCH($C82,'Order Composition'!$B$2:$F$2,0),0) -> 0.55 | T82: =S82*Q82 -> 0.07546 | U82: =Таблица1[[#This Row],[Price]]*Таблица1[[#This Row],[Order]] -> 1.98 | V82: =Таблица1[[#This Row],[Cost(with labour)]]*Таблица1[[#This Row],[Order]] -> 1.90454 | W82: =VLOOKUP($A82,'Mean order price'!$B$2:$H$10,7,0) -> 9 | X82: =W82*P82 -> 0.45
A83: Las Vegas | B83: =B82+1 -> 80 | C83: Appetizer | D83: Salad B | E83: =VLOOKUP('Menu and cost - USA by city'!D83,'Menu and cost - Russia'!$D$4:$P$29,2,FALSE)*(VLOOKUP('Menu and cost - USA by city'!A83,COGS!$B$3:$I$10,8,FALSE)/3)*0.4 -> 3.6 | F83: =SUMPRODUCT(H83:L83,'Mean order price'!$C$6:$G$6)*G83+P83*'Mean order price'!$H$6 -> 3.7164 | G83: 0.2 | H83: 0 | I83: 0.2 | J83: 0.7 | K83: 0 | L83: 0.1 | M83: =SUM(H83:L83) -> 1 | N83: 20 | O83: =60/N83 -> 3 | P83: =O83/60 -> 0.05 | Q83: =E83-F83 -> -0.1164 | R83: =Таблица1[[#This Row],[Profit]]/Таблица1[[#This Row],[Price]] -> -0.032333333 | S83: =VLOOKUP($A83,'Order Composition'!$B$2:$F$10,MATCH($C83,'Order Composition'!$B$2:$F$2,0),0) -> 0.55 | T83: =S83*Q83 -> -0.06402 | U83: =Таблица1[[#This Row],[Price]]*Таблица1[[#This Row],[Order]] -> 1.98 | V83: =Таблица1[[#This Row],[Cost(with labour)]]*Таблица1[[#This Row],[Order]] -> 2.04402 | W83: =VLOOKUP($A83,'Mean order price'!$B$2:$H$10,7,0) -> 9 | X83: =W83*P83 -> 0.45
A84: Las Vegas | B84: =B83+1 -> 81 | C84: Appetizer | D84: Salad C | E84: =VLOOKUP('Menu and cost - USA by city'!D84,'Menu and cost - Russia'!$D$4:$P$29,2,FALSE)*(VLOOKUP('Menu and cost - USA by city'!A84,COGS!$B$3:$I$10,8,FALSE)/3)*0.4 -> 3.6 | F84: =SUMPRODUCT(H84:L84,'Mean order price'!$C$6:$G$6)*G84+P84*'Mean order price'!$H$6 -> 4.0968 | G84: 0.2 | H84: 0 | I84: 0.5 | J84: 0.4 | K84: 0 | L84: 0.1 | M84: =SUM(H84:L84) -> 1 | N84: 20 | O84: =60/N84 -> 3 | P84: =O84/60 -> 0.05 | Q84: =E84-F84 -> -0.4968 | R84: =Таблица1[[#This Row],[Profit]]/Таблица1[[#This Row],[Price]] -> -0.138 | S84: =VLOOKUP($A84,'Order Composition'!$B$2:$F$10,MATCH($C84,'Order Composition'!$B$2:$F$2,0),0) -> 0.55 | T84: =S84*Q84 -> -0.27324 | U84: =Таблица1[[#This Row],[Price]]*Таблица1[[#This Row],[Order]] -> 1.98 | V84: =Таблица1[[#This Row],[Cost(with labour)]]*Таблица1[[#This Row],[Order]] -> 2.25324 | W84: =VLOOKUP($A84,'Mean order price'!$B$2:$H$10,7,0) -> 9 | X84: =W84*P84 -> 0.45
A85: Las Vegas | B85: =B84+1 -> 82 | C85: Appetizer | D85: Soup A | E85: =VLOOKUP('Menu and cost - USA by city'!D85,'Menu and cost - Russia'!$D$4:$P$29,2,FALSE)*(VLOOKUP('Menu and cost - USA by city'!A85,COGS!$B$3:$I$10,8,FALSE)/3)*0.4 -> 2.4 | F85: =SUMPRODUCT(H85:L85,'Mean order price'!$C$6:$G$6)*G85+P85*'Mean order price'!$H$6 -> 2.7434 | G85: 0.2 | H85: 0.1 | I85: 0 | J85: 0.4 | K85: 0.1 | L85: 0.4 | M85: =SUM(H85:L85) -> 1 | N85: 60 | O85: =60/N85 -> 1 | P85: =O85/60 -> 0.016666667 | Q85: =E85-F85 -> -0.3434 | R85: =Таблица1[[#This Row],[Profit]]/Таблица1[[#This Row],[Price]] -> -0.14308333 | S85: =VLOOKUP($A85,'Order Composition'!$B$2:$F$10,MATCH($C85,'Order Composition'!$B$2:$F$2,0),0) -> 0.55 | T85: =S85*Q85 -> -0.18887 | U85: =Таблица1[[#This Row],[Price]]*Таблица1[[#This Row],[Order]] -> 1.32 | V85: =Таблица1[[#This Row],[Cost(with labour)]]*Таблица1[[#This Row],[Order]] -> 1.50887 | W85: =VLOOKUP($A85,'Mean order price'!$B$2:$H$10,7,0) -> 9 | X85: =W85*P85 -> 0.15
A86: Las Vegas | B86: =B85+1 -> 83 | C86: Appetizer | D86: Soup B | E86: =VLOOKUP('Menu and cost - USA by city'!D86,'Menu and cost - Russia'!$D$4:$P$29,2,FALSE)*(VLOOKUP('Menu and cost - USA by city'!A86,COGS!$B$3:$I$10,8,FALSE)/3)*0.4 -> 2.4 | F86: =SUMPRODUCT(H86:L86,'Mean order price'!$C$6:$G$6)*G86+P86*'Mean order price'!$H$6 -> 3.0922 | G86: 0.2 | H86: 0.1 | I86: 0.2 | J86: 0.3 | K86: 0.1 | L86: 0.3 | M86: =SUM(H86:L86) -> 1 | N86: 60 | O86: =60/N86 -> 1 | P86: =O86/60 -> 0.016666667 | Q86: =E86-F86 -> -0.6922 | R86: =Таблица1[[#This Row],[Profit]]/Таблица1[[#This Row],[Price]] -> -0.28841667 | S86: =VLOOKUP($A86,'Order Composition'!$B$2:$F$10,MATCH($C86,'Order Composition'!$B$2:$F$2,0),0) -> 0.55 | T86: =S86*Q86 -> -0.38071 | U86: =Таблица1[[#This Row],[Price]]*Таблица1[[#This Row],[Order]] -> 1.32 | V86: =Таблица1[[#This Row],[Cost(with labour)]]*Таблица1[[#This Row],[Order]] -> 1.70071 | W86: =VLOOKUP($A86,'Mean order price'!$B$2:$H$10,7,0) -> 9 | X86: =W86*P86 -> 0.15
A87: Las Vegas | B87: =B86+1 -> 84 | C87: Appetizer | D87: Pirozhok A | E87: =VLOOKUP('Menu and cost - USA by city'!D87,'Menu and cost - Russia'!$D$4:$P$29,2,FALSE)*(VLOOKUP('Menu and cost - USA by city'!A87,COGS!$B$3:$I$10,8,FALSE)/3)*0.4 -> 1.2 | F87: =SUMPRODUCT(H87:L87,'Mean order price'!$C$6:$G$6)*G87+P87*'Mean order price'!$H$6 -> 1.76805 | G87: 0.1 | H87: 0.1 | I87: 0 | J87: 0.75 | K87: 0.05 | L87: 0.1 | M87: =SUM(H87:L87) -> 1 | N87: 30 | O87: =60/N87 -> 2 | P87: =O87/60 -> 0.033333333 | Q87: =E87-F87 -> -0.56805 | R87: =Таблица1[[#This Row],[Profit]]/Таблица1[[#This Row],[Price]] -> -0.473375 | S87: =VLOOKUP($A87,'Order Composition'!$B$2:$F$10,MATCH($C87,'Order Composition'!$B$2:$F$2,0),0) -> 0.55 | T87: =S87*Q87 -> -0.3124275 | U87: =Таблица1[[#This Row],[Price]]*Таблица1[[#This Row],[Order]] -> 0.66 | V87: =Таблица1[[#This Row],[Cost(with labour)]]*Таблица1[[#This Row],[Order]] -> 0.9724275 | W87: =VLOOKUP($A87,'Mean order price'!$B$2:$H$10,7,0) -> 9 | X87: =W87*P87 -> 0.3
A88: Las Vegas | B88: =B87+1 -> 85 | C88: Appetizer | D88: Pirozhok B | E88: =VLOOKUP('Menu and cost - USA by city'!D88,'Menu and cost - Russia'!$D$4:$P$29,2,FALSE)*(VLOOKUP('Menu and cost - USA by city'!A88,COGS!$B$3:$I$10,8,FALSE)/3)*0.4 -> 1.2 | F88: =SUMPRODUCT(H88:L88,'Mean order price'!$C$6:$G$6)*G88+P88*'Mean order price'!$H$6 -> 2.08505 | G88: 0.1 | H88: 0.1 | I88: 0.5 | J88: 0.25 | K88: 0.05 | L88: 0.1 | M88: =SUM(H88:L88) -> 1 | N88: 30 | O88: =60/N88 -> 2 | P88: =O88/60 -> 0.033333333 | Q88: =E88-F88 -> -0.88505 | R88: =Таблица1[[#This Row],[Profit]]/Таблица1[[#This Row],[Price]] -> -0.73754167 | S88: =VLOOKUP($A88,'Order Composition'!$B$2:$F$10,MATCH($C88,'Order Composition'!$B$2:$F$2,0),0) -> 0.55 | T88: =S88*Q88 -> -0.4867775 | U88: =Таблица1[[#This Row],[Price]]*Таблица1[[#This Row],[Order]] -> 0.66 | V88: =Таблица1[[#This Row],[Cost(with labour)]]*Таблица1[[#This Row],[Order]] -> 1.1467775 | W88: =VLOOKUP($A88,'Mean order price'!$B$2:$H$10,7,0) -> 9 | X88: =W88*P88 -> 0.3
A89: Las Vegas | B89: =B88+1 -> 86 | C89: Entry | D89: Blin A | E89: =VLOOKUP('Menu and cost - USA by city'!D89,'Menu and cost - Russia'!$D$4:$P$29,2,FALSE)*(VLOOKUP('Menu and cost - USA by city'!A89,COGS!$B$3:$I$10,8,FALSE)/3)*0.4 -> 3.6 | F89: =SUMPRODUCT(H89:L89,'Mean order price'!$C$6:$G$6)*G89+P89*'Mean order price'!$H$6 -> 3.5361 | G89: 0.2 | H89: 0.1 | I89: 0 | J89: 0.75 | K89: 0.05 | L89: 0.1 | M89: =SUM(H89:L89) -> 1 | N89: 15 | O89: =60/N89 -> 4 | P89: =O89/60 -> 0.066666667 | Q89: =E89-F89 -> 0.0639 | R89: =Таблица1[[#This Row],[Profit]]/Таблица1[[#This Row],[Price]] -> 0.01775 | S89: =VLOOKUP($A89,'Order Composition'!$B$2:$F$10,MATCH($C89,'Order Composition'!$B$2:$F$2,0),0) -> 0.9 | T89: =S89*Q89 -> 0.05751 | U89: =Таблица1[[#This Row],[Price]]*Таблица1[[#This Row],[Order]] -> 3.24 | V89: =Таблица1[[#This Row],[Cost(with labour)]]*Таблица1[[#This Row],[Order]] -> 3.18249 | W89: =VLOOKUP($A89,'Mean order price'!$B$2:$H$10,7,0) -> 9 | X89: =W89*P89 -> 0.6
A90: Las Vegas | B90: =B89+1 -> 87 | C90: Entry | D90: Blin B | E90: =VLOOKUP('Menu and cost - USA by city'!D90,'Menu and cost - Russia'!$D$4:$P$29,2,FALSE)*(VLOOKUP('Menu and cost - USA by city'!A90,COGS!$B$3:$I$10,8,FALSE)/3)*0.4 -> 3.6 | F90: =SUMPRODUCT(H90:L90,'Mean order price'!$C$6:$G$6)*G90+P90*'Mean order price'!$H$6 -> 4.94535 | G90: 0.3 | H90: 0.3 | I90: 0 | J90: 0.55 | K90: 0.05 | L90: 0.1 | M90: =SUM(H90:L90) -> 1 | N90: 15 | O90: =60/N90 -> 4 | P90: =O90/60 -> 0.066666667 | Q90: =E90-F90 -> -1.34535 | R90: =Таблица1[[#This Row],[Profit]]/Таблица1[[#This Row],[Price]] -> -0.37370833 | S90: =VLOOKUP($A90,'Order Composition'!$B$2:$F$10,MATCH($C90,'Order Composition'!$B$2:$F$2,0),0) -> 0.9 | T90: =S90*Q90 -> -1.210815 | U90: =Таблица1[[#This Row],[Price]]*Таблица1[[#This Row],[Order]] -> 3.24 | V90: =Таблица1[[#This Row],[Cost(with labour)]]*Таблица1[[#This Row],[Order]] -> 4.450815 | W90: =VLOOKUP($A90,'Mean order price'!$B$2:$H$10,7,0) -> 9 | X90: =W90*P90 -> 0.6
A91: Las Vegas | B91: =B90+1 -> 88 | C91: Entry | D91: Blin C | E91: =VLOOKUP('Menu and cost - USA by city'!D91,'Menu and cost - Russia'!$D$4:$P$29,2,FALSE)*(VLOOKUP('Menu and cost - USA by city'!A91,COGS!$B$3:$I$10,8,FALSE)/3)*0.4 -> 3.6 | F91: =SUMPRODUCT(H91:L91,'Mean order price'!$C$6:$G$6)*G91+P91*'Mean order price'!$H$6 -> 5.47965 | G91: 0.3 | H91: 0.1 | I91: 0.25 | J91: 0.5 | K91: 0.05 | L91: 0.1 | M91: =SUM(H91:L91) -> 1 | N91: 15 | O91: =60/N91 -> 4 | P91: =O91/60 -> 0.066666667 | Q91: =E91-F91 -> -1.87965 | R91: =Таблица1[[#This Row],[Profit]]/Таблица1[[#This Row],[Price]] -> -0.522125 | S91: =VLOOKUP($A91,'Order Composition'!$B$2:$F$10,MATCH($C91,'Order Composition'!$B$2:$F$2,0),0) -> 0.9 | T91: =S91*Q91 -> -1.691685 | U91: =Таблица1[[#This Row],[Price]]*Таблица1[[#This Row],[Order]] -> 3.24 | V91: =Таблица1[[#This Row],[Cost(with labour)]]*Таблица1[[#This Row],[Order]] -> 4.931685 | W91: =VLOOKUP($A91,'Mean order price'!$B$2:$H$10,7,0) -> 9 | X91: =W91*P91 -> 0.6
A92: Las Vegas | B92: =B91+1 -> 89 | C92: Entry | D92: Blin D | E92: =VLOOKUP('Menu and cost - USA by city'!D92,'Menu and cost - Russia'!$D$4:$P$29,2,FALSE)*(VLOOKUP('Menu and cost - USA by city'!A92,COGS!$B$3:$I$10,8,FALSE)/3)*0.4 -> 3.6 | F92: =SUMPRODUCT(H92:L92,'Mean order price'!$C$6:$G$6)*G92+P92*'Mean order price'!$H$6 -> 4.3237 | G92: 0.2 | H92: 0.2 | I92: 0.4 | J92: 0.25 | K92: 0.05 | L92: 0.1 | M92: =SUM(H92:L92) -> 1 | N92: 10 | O92: =60/N92 -> 6 | P92: =O92/60 -> 0.1 | Q92: =E92-F92 -> -0.7237 | R92: =Таблица1[[#This Row],[Profit]]/Таблица1[[#This Row],[Price]] -> -0.20102778 | S92: =VLOOKUP($A92,'Order Composition'!$B$2:$F$10,MATCH($C92,'Order Composition'!$B$2:$F$2,0),0) -> 0.9 | T92: =S92*Q92 -> -0.65133 | U92: =Таблица1[[#This Row],[Price]]*Таблица1[[#This Row],[Order]] -> 3.24 | V92: =Таблица1[[#This Row],[Cost(with labour)]]*Таблица1[[#This Row],[Order]] -> 3.89133 | W92: =VLOOKUP($A92,'Mean order price'!$B$2:$H$10,7,0) -> 9 | X92: =W92*P92 -> 0.9
A93: Las Vegas | B93: =B92+1 -> 90 | C93: Entry | D93: Blin E | E93: =VLOOKUP('Menu and cost - USA by city'!D93,'Menu and cost - Russia'!$D$4:$P$29,2,FALSE)*(VLOOKUP('Menu and cost - USA by city'!A93,COGS!$B$3:$I$10,8,FALSE)/3)*0.4 -> 4.8 | F93: =SUMPRODUCT(H93:L93,'Mean order price'!$C$6:$G$6)*G93+P93*'Mean order price'!$H$6 -> 6.41595 | G93: 0.3 | H93: 0.2 | I93: 0.6 | J93: 0.05 | K93: 0.05 | L93: 0.1 | M93: =SUM(H93:L93) -> 1 | N93: 10 | O93: =60/N93 -> 6 | P93: =O93/60 -> 0.1 | Q93: =E93-F93 -> -1.61595 | R93: =Таблица1[[#This Row],[Profit]]/Таблица1[[#This Row],[Price]] -> -0.33665625 | S93: =VLOOKUP($A93,'Order Composition'!$B$2:$F$10,MATCH($C93,'Order Composition'!$B$2:$F$2,0),0) -> 0.9 | T93: =S93*Q93 -> -1.454355 | U93: =Таблица1[[#This Row],[Price]]*Таблица1[[#This Row],[Order]] -> 4.32 | V93: =Таблица1[[#This Row],[Cost(with labour)]]*Таблица1[[#This Row],[Order]] -> 5.774355 | W93: =VLOOKUP($A93,'Mean order price'!$B$2:$H$10,7,0) -> 9 | X93: =W93*P93 -> 0.9
... A107: Las Vegas | B107: =B106+1 -> 104 | C107: Beverages | D107: Hot Drink B | E107: =VLOOKUP('Menu and cost - USA by city'!D107,'Menu and cost - Russia'!$D$4:$P$29,2,FALSE)*(VLOOKUP('Menu and cost - USA by city'!A107,COGS!$B$3:$I$10,8,FALSE)/3)*0.4 -> 1.8 | F107: =SUMPRODUCT(H107:L107,'Mean order price'!$C$6:$G$6)*G107+P107*'Mean order price'!$H$6 -> 2.3052 | G107: 0.2 | H107: 0 | I107: 0 | J107: 0.1 | K107: 0.9 | L107: 0 | M107: =SUM(H107:L107) -> 1 | N107: 40 | O107: =60/N107 -> 1.5 | P107: =O107/60 -> 0.025 | Q107: =E107-F107 -> -0.5052 | R107: =Таблица1[[#This Row],[Profit]]/Таблица1[[#This Row],[Price]] -> -0.28066667 | S107: =VLOOKUP($A107,'Order Composition'!$B$2:$F$10,MATCH($C107,'Order Composition'!$B$2:$F$2,0),0) -> 0.9 | T107: =S107*Q107 -> -0.45468 | U107: =Таблица1[[#This Row],[Price]]*Таблица1[[#This Row],[Order]] -> 1.62 | V107: =Таблица1[[#This Row],[Cost(with labour)]]*Таблица1[[#This Row],[Order]] -> 2.07468 | W107: =VLOOKUP($A107,'Mean order price'!$B$2:$H$10,7,0) -> 9 | X107: =W107*P107 -> 0.225
A108: Miami | B108: =B107+1 -> 105 | C108: Appetizer | D108: Salad A | E108: =VLOOKUP('Menu and cost - USA by city'!D108,'Menu and cost - Russia'!$D$4:$P$29,2,FALSE)*(VLOOKUP('Menu and cost - USA by city'!A108,COGS!$B$3:$I$10,8,FALSE)/3)*0.4 -> 3.8 | F108: =SUMPRODUCT(H108:L108,'Mean order price'!$C$7:$G$7)*G108+P108*'Mean order price'!$H$7 -> 3.3984 | G108: 0.2 | H108: 0 | I108: 0 | J108: 0.9 | K108: 0 | L108: 0.1 | M108: =SUM(H108:L108) -> 1 | N108: 20 | O108: =60/N108 -> 3 | P108: =O108/60 -> 0.05 | Q108: =E108-F108 -> 0.4016 | R108: =Таблица1[[#This Row],[Profit]]/Таблица1[[#This Row],[Price]] -> 0.10568421 | S108: =VLOOKUP($A108,'Order Composition'!$B$2:$F$10,MATCH($C108,'Order Composition'!$B$2:$F$2,0),0) -> 0.5 | T108: =S108*Q108 -> 0.2008 | U108: =Таблица1[[#This Row],[Price]]*Таблица1[[#This Row],[Order]] -> 1.9 | V108: =Таблица1[[#This Row],[Cost(with labour)]]*Таблица1[[#This Row],[Order]] -> 1.6992 | W108: =VLOOKUP($A108,'Mean order price'!$B$2:$H$10,7,0) -> 9.5 | X108: =W108*P108 -> 0.475
A109: Miami | B109: =B108+1 -> 106 | C109: Appetizer | D109: Salad B | E109: =VLOOKUP('Menu and cost - USA by city'!D109,'Menu and cost - Russia'!$D$4:$P$29,2,FALSE)*(VLOOKUP('Menu and cost - USA by city'!A109,COGS!$B$3:$I$10,8,FALSE)/3)*0.4 -> 3.8 | F109: =SUMPRODUCT(H109:L109,'Mean order price'!$C$7:$G$7)*G109+P109*'Mean order price'!$H$7 -> 3.5692 | G109: 0.2 | H109: 0 | I109: 0.2 | J109: 0.7 | K109: 0 | L109: 0.1 | M109: =SUM(H109:L109) -> 1 | N109: 20 | O109: =60/N109 -> 3 | P109: =O109/60 -> 0.05 | Q109: =E109-F109 -> 0.2308 | R109: =Таблица1[[#This Row],[Profit]]/Таблица1[[#This Row],[Price]] -> 0.060736842 | S109: =VLOOKUP($A109,'Order Composition'!$B$2:$F$10,MATCH($C109,'Order Composition'!$B$2:$F$2,0),0) -> 0.5 | T109: =S109*Q109 -> 0.1154 | U109: =Таблица1[[#This Row],[Price]]*Таблица1[[#This Row],[Order]] -> 1.9 | V109: =Таблица1[[#This Row],[Cost(with labour)]]*Таблица1[[#This Row],[Order]] -> 1.7846 | W109: =VLOOKUP($A109,'Mean order price'!$B$2:$H$10,7,0) -> 9.5 | X109: =W109*P109 -> 0.475
A110: Miami | B110: =B109+1 -> 107 | C110: Appetizer | D110: Salad C | E110: =VLOOKUP('Menu and cost - USA by city'!D110,'Menu and cost - Russia'!$D$4:$P$29,2,FALSE)*(VLOOKUP('Menu and cost - USA by city'!A110,COGS!$B$3:$I$10,8,FALSE)/3)*0.4 -> 3.8 | F110: =SUMPRODUCT(H110:L110,'Mean order price'!$C$7:$G$7)*G110+P110*'Mean order price'!$H$7 -> 3.8254 | G110: 0.2 | H110: 0 | I110: 0.5 | J110: 0.4 | K110: 0 | L110: 0.1 | M110: =SUM(H110:L110) -> 1 | N110: 20 | O110: =60/N110 -> 3 | P110: =O110/60 -> 0.05 | Q110: =E110-F110 -> -0.0254 | R110: =Таблица1[[#This Row],[Profit]]/Таблица1[[#This Row],[Price]] -> -0.0066842105 | S110: =VLOOKUP($A110,'Order Composition'!$B$2:$F$10,MATCH($C110,'Order Composition'!$B$2:$F$2,0),0) -> 0.5 | T110: =S110*Q110 -> -0.0127 | U110: =Таблица1[[#This Row],[Price]]*Таблица1[[#This Row],[Order]] -> 1.9 | V110: =Таблица1[[#This Row],[Cost(with labour)]]*Таблица1[[#This Row],[Order]] -> 1.9127 | W110: =VLOOKUP($A110,'Mean order price'!$B$2:$H$10,7,0) -> 9.5 | X110: =W110*P110 -> 0.475
A111: Miami | B111: =B110+1 -> 108 | C111: Appetizer | D111: Soup A | E111: =VLOOKUP('Menu and cost - USA by city'!D111,'Menu and cost - Russia'!$D$4:$P$29,2,FALSE)*(VLOOKUP('Menu and cost - USA by city'!A111,COGS!$B$3:$I$10,8,FALSE)/3)*0.4 -> 2.5333333 | F111: =SUMPRODUCT(H111:L111,'Mean order price'!$C$7:$G$7)*G111+P111*'Mean order price'!$H$7 -> 2.5723333 | G111: 0.2 | H111: 0.1 | I111: 0 | J111: 0.4 | K111: 0.1 | L111: 0.4 | M111: =SUM(H111:L111) -> 1 | N111: 60 | O111: =60/N111 -> 1 | P111: =O111/60 -> 0.016666667 | Q111: =E111-F111 -> -0.039 | R111: =Таблица1[[#This Row],[Profit]]/Таблица1[[#This Row],[Price]] -> -0.015394737 | S111: =VLOOKUP($A111,'Order Composition'!$B$2:$F$10,MATCH($C111,'Order Composition'!$B$2:$F$2,0),0) -> 0.5 | T111: =S111*Q111 -> -0.0195 | U111: =Таблица1[[#This Row],[Price]]*Таблица1[[#This Row],[Order]] -> 1.2666667 | V111: =Таблица1[[#This Row],[Cost(with labour)]]*Таблица1[[#This Row],[Order]] -> 1.2861667 | W111: =VLOOKUP($A111,'Mean order price'!$B$2:$H$10,7,0) -> 9.5 | X111: =W111*P111 -> 0.15833333
A112: Miami | B112: =B111+1 -> 109 | C112: Appetizer | D112: Soup B | E112: =VLOOKUP('Menu and cost - USA by city'!D112,'Menu and cost - Russia'!$D$4:$P$29,2,FALSE)*(VLOOKUP('Menu and cost - USA by city'!A112,COGS!$B$3:$I$10,8,FALSE)/3)*0.4 -> 2.5333333 | F112: =SUMPRODUCT(H112:L112,'Mean order price'!$C$7:$G$7)*G112+P112*'Mean order price'!$H$7 -> 2.8677333 | G112: 0.2 | H112: 0.1 | I112: 0.2 | J112: 0.3 | K112: 0.1 | L112: 0.3 | M112: =SUM(H112:L112) -> 1 | N112: 60 | O112: =60/N112 -> 1 | P112: =O112/60 -> 0.016666667 | Q112: =E112-F112 -> -0.3344 | R112: =Таблица1[[#This Row],[Profit]]/Таблица1[[#This Row],[Price]] -> -0.132 | S112: =VLOOKUP($A112,'Order Composition'!$B$2:$F$10,MATCH($C112,'Order Composition'!$B$2:$F$2,0),0) -> 0.5 | T112: =S112*Q112 -> -0.1672 | U112: =Таблица1[[#This Row],[Price]]*Таблица1[[#This Row],[Order]] -> 1.2666667 | V112: =Таблица1[[#This Row],[Cost(with labour)]]*Таблица1[[#This Row],[Order]] -> 1.4338667 | W112: =VLOOKUP($A112,'Mean order price'!$B$2:$H$10,7,0) -> 9.5 | X112: =W112*P112 -> 0.15833333
A113: Miami | B113: =B112+1 -> 110 | C113: Appetizer | D113: Pirozhok A | E113: =VLOOKUP('Menu and cost - USA by city'!D113,'Menu and cost - Russia'!$D$4:$P$29,2,FALSE)*(VLOOKUP('Menu and cost - USA by city'!A113,COGS!$B$3:$I$10,8,FALSE)/3)*0.4 -> 1.2666667 | F113: =SUMPRODUCT(H113:L113,'Mean order price'!$C$7:$G$7)*G113+P113*'Mean order price'!$H$7 -> 1.7392667 | G113: 0.1 | H113: 0.1 | I113: 0 | J113: 0.75 | K113: 0.05 | L113: 0.1 | M113: =SUM(H113:L113) -> 1 | N113: 30 | O113: =60/N113 -> 2 | P113: =O113/60 -> 0.033333333 | Q113: =E113-F113 -> -0.4726 | R113: =Таблица1[[#This Row],[Profit]]/Таблица1[[#This Row],[Price]] -> -0.37310526 | S113: =VLOOKUP($A113,'Order Composition'!$B$2:$F$10,MATCH($C113,'Order Composition'!$B$2:$F$2,0),0) -> 0.5 | T113: =S113*Q113 -> -0.2363 | U113: =Таблица1[[#This Row],[Price]]*Таблица1[[#This Row],[Order]] -> 0.63333333 | V113: =Таблица1[[#This Row],[Cost(with labour)]]*Таблица1[[#This Row],[Order]] -> 0.86963333 | W113: =VLOOKUP($A113,'Mean order price'!$B$2:$H$10,7,0) -> 9.5 | X113: =W113*P113 -> 0.31666667
A114: Miami | B114: =B113+1 -> 111 | C114: Appetizer | D114: Pirozhok B | E114: =VLOOKUP('Menu and cost - USA by city'!D114,'Menu and cost - Russia'!$D$4:$P$29,2,FALSE)*(VLOOKUP('Menu and cost - USA by city'!A114,COGS!$B$3:$I$10,8,FALSE)/3)*0.4 -> 1.2666667 | F114: =SUMPRODUCT(H114:L114,'Mean order price'!$C$7:$G$7)*G114+P114*'Mean order price'!$H$7 -> 1.9527667 | G114: 0.1 | H114: 0.1 | I114: 0.5 | J114: 0.25 | K114: 0.05 | L114: 0.1 | M114: =SUM(H114:L114) -> 1 | N114: 30 | O114: =60/N114 -> 2 | P114: =O114/60 -> 0.033333333 | Q114: =E114-F114 -> -0.6861 | R114: =Таблица1[[#This Row],[Profit]]/Таблица1[[#This Row],[Price]] -> -0.54165789 | S114: =VLOOKUP($A114,'Order Composition'!$B$2:$F$10,MATCH($C114,'Order Composition'!$B$2:$F$2,0),0) -> 0.5 | T114: =S114*Q114 -> -0.34305 | U114: =Таблица1[[#This Row],[Price]]*Таблица1[[#This Row],[Order]] -> 0.63333333 | V114: =Таблица1[[#This Row],[Cost(with labour)]]*Таблица1[[#This Row],[Order]] -> 0.97638333 | W114: =VLOOKUP($A114,'Mean order price'!$B$2:$H$10,7,0) -> 9.5 | X114: =W114*P114 -> 0.31666667
A115: Miami | B115: =B114+1 -> 112 | C115: Entry | D115: Blin A | E115: =VLOOKUP('Menu and cost - USA by city'!D115,'Menu and cost - Russia'!$D$4:$P$29,2,FALSE)*(VLOOKUP('Menu and cost - USA by city'!A115,COGS!$B$3:$I$10,8,FALSE)/3)*0.4 -> 3.8 | F115: =SUMPRODUCT(H115:L115,'Mean order price'!$C$7:$G$7)*G115+P115*'Mean order price'!$H$7 -> 3.4785333 | G115: 0.2 | H115: 0.1 | I115: 0 | J115: 0.75 | K115: 0.05 | L115: 0.1 | M115: =SUM(H115:L115) -> 1 | N115: 15 | O115: =60/N115 -> 4 | P115: =O115/60 -> 0.066666667 | Q115: =E115-F115 -> 0.32146667 | R115: =Таблица1[[#This Row],[Profit]]/Таблица1[[#This Row],[Price]] -> 0.084596491 | S115: =VLOOKUP($A115,'Order Composition'!$B$2:$F$10,MATCH($C115,'Order Composition'!$B$2:$F$2,0),0) -> 0.85 | T115: =S115*Q115 -> 0.27324667 | U115: =Таблица1[[#This Row],[Price]]*Таблица1[[#This Row],[Order]] -> 3.23 | V115: =Таблица1[[#This Row],[Cost(with labour)]]*Таблица1[[#This Row],[Order]] -> 2.9567533 | W115: =VLOOKUP($A115,'Mean order price'!$B$2:$H$10,7,0) -> 9.5 | X115: =W115*P115 -> 0.63333333
A116: Miami | B116: =B115+1 -> 113 | C116: Entry | D116: Blin B | E116: =VLOOKUP('Menu and cost - USA by city'!D116,'Menu and cost - Russia'!$D$4:$P$29,2,FALSE)*(VLOOKUP('Menu and cost - USA by city'!A116,COGS!$B$3:$I$10,8,FALSE)/3)*0.4 -> 3.8 | F116: =SUMPRODUCT(H116:L116,'Mean order price'!$C$7:$G$7)*G116+P116*'Mean order price'!$H$7 -> 4.8387333 | G116: 0.3 | H116: 0.3 | I116: 0 | J116: 0.55 | K116: 0.05 | L116: 0.1 | M116: =SUM(H116:L116) -> 1 | N116: 15 | O116: =60/N116 -> 4 | P116: =O116/60 -> 0.066666667 | Q116: =E116-F116 -> -1.0387333 | R116: =Таблица1[[#This Row],[Profit]]/Таблица1[[#This Row],[Price]] -> -0.27335088 | S116: =VLOOKUP($A116,'Order Composition'!$B$2:$F$10,MATCH($C116,'Order Composition'!$B$2:$F$2,0),0) -> 0.85 | T116: =S116*Q116 -> -0.88292333 | U116: =Таблица1[[#This Row],[Price]]*Таблица1[[#This Row],[Order]] -> 3.23 | V116: =Таблица1[[#This Row],[Cost(with labour)]]*Таблица1[[#This Row],[Order]] -> 4.1129233 | W116: =VLOOKUP($A116,'Mean order price'!$B$2:$H$10,7,0) -> 9.5 | X116: =W116*P116 -> 0.63333333
A117: Miami | B117: =B116+1 -> 114 | C117: Entry | D117: Blin C | E117: =VLOOKUP('Menu and cost - USA by city'!D117,'Menu and cost - Russia'!$D$4:$P$29,2,FALSE)*(VLOOKUP('Menu and cost - USA by city'!A117,COGS!$B$3:$I$10,8,FALSE)/3)*0.4 -> 3.8 | F117: =SUMPRODUCT(H117:L117,'Mean order price'!$C$7:$G$7)*G117+P117*'Mean order price'!$H$7 -> 5.2213833 | G117: 0.3 | H117: 0.1 | I117: 0.25 | J117: 0.5 | K117: 0.05 | L117: 0.1 | M117: =SUM(H117:L117) -> 1 | N117: 15 | O117: =60/N117 -> 4 | P117: =O117/60 -> 0.066666667 | Q117: =E117-F117 -> -1.4213833 | R117: =Таблица1[[#This Row],[Profit]]/Таблица1[[#This Row],[Price]] -> -0.37404825 | S117: =VLOOKUP($A117,'Order Composition'!$B$2:$F$10,MATCH($C117,'Order Composition'!$B$2:$F$2,0),0) -> 0.85 | T117: =S117*Q117 -> -1.2081758 | U117: =Таблица1[[#This Row],[Price]]*Таблица1[[#This Row],[Order]] -> 3.23 | V117: =Таблица1[[#This Row],[Cost(with labour)]]*Таблица1[[#This Row],[Order]] -> 4.4381758 | W117: =VLOOKUP($A117,'Mean order price'!$B$2:$H$10,7,0) -> 9.5 | X117: =W117*P117 -> 0.63333333
A118: Miami | B118: =B117+1 -> 115 | C118: Entry | D118: Blin D | E118: =VLOOKUP('Menu and cost - USA by city'!D118,'Menu and cost - Russia'!$D$4:$P$29,2,FALSE)*(VLOOKUP('Menu and cost - USA by city'!A118,COGS!$B$3:$I$10,8,FALSE)/3)*0.4 -> 3.8 | F118: =SUMPRODUCT(H118:L118,'Mean order price'!$C$7:$G$7)*G118+P118*'Mean order price'!$H$7 -> 4.116 | G118: 0.2 | H118: 0.2 | I118: 0.4 | J118: 0.25 | K118: 0.05 | L118: 0.1 | M118: =SUM(H118:L118) -> 1 | N118: 10 | O118: =60/N118 -> 6 | P118: =O118/60 -> 0.1 | Q118: =E118-F118 -> -0.316 | R118: =Таблица1[[#This Row],[Profit]]/Таблица1[[#This Row],[Price]] -> -0.083157895 | S118: =VLOOKUP($A118,'Order Composition'!$B$2:$F$10,MATCH($C118,'Order Composition'!$B$2:$F$2,0),0) -> 0.85 | T118: =S118*Q118 -> -0.2686 | U118: =Таблица1[[#This Row],[Price]]*Таблица1[[#This Row],[Order]] -> 3.23 | V118: =Таблица1[[#This Row],[Cost(with labour)]]*Таблица1[[#This Row],[Order]] -> 3.4986 | W118: =VLOOKUP($A118,'Mean order price'!$B$2:$H$10,7,0) -> 9.5 | X118: =W118*P118 -> 0.95
A119: Miami | B119: =B118+1 -> 116 | C119: Entry | D119: Blin E | E119: =VLOOKUP('Menu and cost - USA by city'!D119,'Menu and cost - Russia'!$D$4:$P$29,2,FALSE)*(VLOOKUP('Menu and cost - USA by city'!A119,COGS!$B$3:$I$10,8,FALSE)/3)*0.4 -> 5.0666667 | F119: =SUMPRODUCT(H119:L119,'Mean order price'!$C$7:$G$7)*G119+P119*'Mean order price'!$H$7 -> 5.9552 | G119: 0.3 | H119: 0.2 | I119: 0.6 | J119: 0.05 | K119: 0.05 | L119: 0.1 | M119: =SUM(H119:L119) -> 1 | N119: 10 | O119: =60/N119 -> 6 | P119: =O119/60 -> 0.1 | Q119: =E119-F119 -> -0.88853333 | R119: =Таблица1[[#This Row],[Profit]]/Таблица1[[#This Row],[Price]] -> -0.17536842 | S119: =VLOOKUP($A119,'Order Composition'!$B$2:$F$10,MATCH($C119,'Order Composition'!$B$2:$F$2,0),0) -> 0.85 | T119: =S119*Q119 -> -0.75525333 | U119: =Таблица1[[#This Row],[Price]]*Таблица1[[#This Row],[Order]] -> 4.3066667 | V119: =Таблица1[[#This Row],[Cost(with labour)]]*Таблица1[[#This Row],[Order]] -> 5.06192 | W119: =VLOOKUP($A119,'Mean order price'!$B$2:$H$10,7,0) -> 9.5 | X119: =W119*P119 -> 0.95
... A133: Miami | B133: =B132+1 -> 130 | C133: Beverages | D133: Hot Drink B | E133: =VLOOKUP('Menu and cost - USA by city'!D133,'Menu and cost - Russia'!$D$4:$P$29,2,FALSE)*(VLOOKUP('Menu and cost - USA by city'!A133,COGS!$B$3:$I$10,8,FALSE)/3)*0.4 -> 1.9 | F133: =SUMPRODUCT(H133:L133,'Mean order price'!$C$7:$G$7)*G133+P133*'Mean order price'!$H$7 -> 2.2523 | G133: 0.2 | H133: 0 | I133: 0 | J133: 0.1 | K133: 0.9 | L133: 0 | M133: =SUM(H133:L133) -> 1 | N133: 40 | O133: =60/N133 -> 1.5 | P133: =O133/60 -> 0.025 | Q133: =E133-F133 -> -0.3523 | R133: =Таблица1[[#This Row],[Profit]]/Таблица1[[#This Row],[Price]] -> -0.18542105 | S133: =VLOOKUP($A133,'Order Composition'!$B$2:$F$10,MATCH($C133,'Order Composition'!$B$2:$F$2,0),0) -> 0.95 | T133: =S133*Q133 -> -0.334685 | U133: =Таблица1[[#This Row],[Price]]*Таблица1[[#This Row],[Order]] -> 1.805 | V133: =Таблица1[[#This Row],[Cost(with labour)]]*Таблица1[[#This Row],[Order]] -> 2.139685 | W133: =VLOOKUP($A133,'Mean order price'!$B$2:$H$10,7,0) -> 9.5 | X133: =W133*P133 -> 0.2375
A134: Indianapolis | B134: =B133+1 -> 131 | C134: Appetizer | D134: Salad A | E134: =VLOOKUP('Menu and cost - USA by city'!D134,'Menu and cost - Russia'!$D$4:$P$29,2,FALSE)*(VLOOKUP('Menu and cost - USA by city'!A134,COGS!$B$3:$I$10,8,FALSE)/3)*0.4 -> 3.2 | F134: =SUMPRODUCT(H134:L134,'Mean order price'!$C$8:$G$8)*G134+P134*'Mean order price'!$H$8 -> 2.35 | G134: 0.2 | H134: 0 | I134: 0 | J134: 0.9 | K134: 0 | L134: 0.1 | M134: =SUM(H134:L134) -> 1 | N134: 20 | O134: =60/N134 -> 3 | P134: =O134/60 -> 0.05 | Q134: =E134-F134 -> 0.85 | R134: =Таблица1[[#This Row],[Profit]]/Таблица1[[#This Row],[Price]] -> 0.265625 | S134: =VLOOKUP($A134,'Order Composition'!$B$2:$F$10,MATCH($C134,'Order Composition'!$B$2:$F$2,0),0) -> 0.4 | T134: =S134*Q134 -> 0.34 | U134: =Таблица1[[#This Row],[Price]]*Таблица1[[#This Row],[Order]] -> 1.28 | V134: =Таблица1[[#This Row],[Cost(with labour)]]*Таблица1[[#This Row],[Order]] -> 0.94 | W134: =VLOOKUP($A134,'Mean order price'!$B$2:$H$10,7,0) -> 8 | X134: =W134*P134 -> 0.4
A135: Indianapolis | B135: =B134+1 -> 132 | C135: Appetizer | D135: Salad B | E135: =VLOOKUP('Menu and cost - USA by city'!D135,'Menu and cost - Russia'!$D$4:$P$29,2,FALSE)*(VLOOKUP('Menu and cost - USA by city'!A135,COGS!$B$3:$I$10,8,FALSE)/3)*0.4 -> 3.2 | F135: =SUMPRODUCT(H135:L135,'Mean order price'!$C$8:$G$8)*G135+P135*'Mean order price'!$H$8 -> 2.4552 | G135: 0.2 | H135: 0 | I135: 0.2 | J135: 0.7 | K135: 0 | L135: 0.1 | M135: =SUM(H135:L135) -> 1 | N135: 20 | O135: =60/N135 -> 3 | P135: =O135/60 -> 0.05 | Q135: =E135-F135 -> 0.7448 | R135: =Таблица1[[#This Row],[Profit]]/Таблица1[[#This Row],[Price]] -> 0.23275 | S135: =VLOOKUP($A135,'Order Composition'!$B$2:$F$10,MATCH($C135,'Order Composition'!$B$2:$F$2,0),0) -> 0.4 | T135: =S135*Q135 -> 0.29792 | U135: =Таблица1[[#This Row],[Price]]*Таблица1[[#This Row],[Order]] -> 1.28 | V135: =Таблица1[[#This Row],[Cost(with labour)]]*Таблица1[[#This Row],[Order]] -> 0.98208 | W135: =VLOOKUP($A135,'Mean order price'!$B$2:$H$10,7,0) -> 8 | X135: =W135*P135 -> 0.4
A136: Indianapolis | B136: =B135+1 -> 133 | C136: Appetizer | D136: Salad C | E136: =VLOOKUP('Menu and cost - USA by city'!D136,'Menu and cost - Russia'!$D$4:$P$29,2,FALSE)*(VLOOKUP('Menu and cost - USA by city'!A136,COGS!$B$3:$I$10,8,FALSE)/3)*0.4 -> 3.2 | F136: =SUMPRODUCT(H136:L136,'Mean order price'!$C$8:$G$8)*G136+P136*'Mean order price'!$H$8 -> 2.613 | G136: 0.2 | H136: 0 | I136: 0.5 | J136: 0.4 | K136: 0 | L136: 0.1 | M136: =SUM(H136:L136) -> 1 | N136: 20 | O136: =60/N136 -> 3 | P136: =O136/60 -> 0.05 | Q136: =E136-F136 -> 0.587 | R136: =Таблица1[[#This Row],[Profit]]/Таблица1[[#This Row],[Price]] -> 0.1834375 | S136: =VLOOKUP($A136,'Order Composition'!$B$2:$F$10,MATCH($C136,'Order Composition'!$B$2:$F$2,0),0) -> 0.4 | T136: =S136*Q136 -> 0.2348 | U136: =Таблица1[[#This Row],[Price]]*Таблица1[[#This Row],[Order]] -> 1.28 | V136: =Таблица1[[#This Row],[Cost(with labour)]]*Таблица1[[#This Row],[Order]] -> 1.0452 | W136: =VLOOKUP($A136,'Mean order price'!$B$2:$H$10,7,0) -> 8 | X136: =W136*P136 -> 0.4
A137: Indianapolis | B137: =B136+1 -> 134 | C137: Appetizer | D137: Soup A | E137: =VLOOKUP('Menu and cost - USA by city'!D137,'Menu and cost - Russia'!$D$4:$P$29,2,FALSE)*(VLOOKUP('Menu and cost - USA by city'!A137,COGS!$B$3:$I$10,8,FALSE)/3)*0.4 -> 2.1333333 | F137: =SUMPRODUCT(H137:L137,'Mean order price'!$C$8:$G$8)*G137+P137*'Mean order price'!$H$8 -> 1.5413333 | G137: 0.2 | H137: 0.1 | I137: 0 | J137: 0.4 | K137: 0.1 | L137: 0.4 | M137: =SUM(H137:L137) -> 1 | N137: 60 | O137: =60/N137 -> 1 | P137: =O137/60 -> 0.016666667 | Q137: =E137-F137 -> 0.592 | R137: =Таблица1[[#This Row],[Profit]]/Таблица1[[#This Row],[Price]] -> 0.2775 | S137: =VLOOKUP($A137,'Order Composition'!$B$2:$F$10,MATCH($C137,'Order Composition'!$B$2:$F$2,0),0) -> 0.4 | T137: =S137*Q137 -> 0.2368 | U137: =Таблица1[[#This Row],[Price]]*Таблица1[[#This Row],[Order]] -> 0.85333333 | V137: =Таблица1[[#This Row],[Cost(with labour)]]*Таблица1[[#This Row],[Order]] -> 0.61653333 | W137: =VLOOKUP($A137,'Mean order price'!$B$2:$H$10,7,0) -> 8 | X137: =W137*P137 -> 0.13333333
A138: Indianapolis | B138: =B137+1 -> 135 | C138: Appetizer | D138: Soup B | E138: =VLOOKUP('Menu and cost - USA by city'!D138,'Menu and cost - Russia'!$D$4:$P$29,2,FALSE)*(VLOOKUP('Menu and cost - USA by city'!A138,COGS!$B$3:$I$10,8,FALSE)/3)*0.4 -> 2.1333333 | F138: =SUMPRODUCT(H138:L138,'Mean order price'!$C$8:$G$8)*G138+P138*'Mean order price'!$H$8 -> 1.7565333 | G138: 0.2 | H138: 0.1 | I138: 0.2 | J138: 0.3 | K138: 0.1 | L138: 0.3 | M138: =SUM(H138:L138) -> 1 | N138: 60 | O138: =60/N138 -> 1 | P138: =O138/60 -> 0.016666667 | Q138: =E138-F138 -> 0.3768 | R138: =Таблица1[[#This Row],[Profit]]/Таблица1[[#This Row],[Price]] -> 0.176625 | S138: =VLOOKUP($A138,'Order Composition'!$B$2:$F$10,MATCH($C138,'Order Composition'!$B$2:$F$2,0),0) -> 0.4 | T138: =S138*Q138 -> 0.15072 | U138: =Таблица1[[#This Row],[Price]]*Таблица1[[#This Row],[Order]] -> 0.85333333 | V138: =Таблица1[[#This Row],[Cost(with labour)]]*Таблица1[[#This Row],[Order]] -> 0.70261333 | W138: =VLOOKUP($A138,'Mean order price'!$B$2:$H$10,7,0) -> 8 | X138: =W138*P138 -> 0.13333333
A139: Indianapolis | B139: =B138+1 -> 136 | C139: Appetizer | D139: Pirozhok A | E139: =VLOOKUP('Menu and cost - USA by city'!D139,'Menu and cost - Russia'!$D$4:$P$29,2,FALSE)*(VLOOKUP('Menu and cost - USA by city'!A139,COGS!$B$3:$I$10,8,FALSE)/3)*0.4 -> 1.0666667 | F139: =SUMPRODUCT(H139:L139,'Mean order price'!$C$8:$G$8)*G139+P139*'Mean order price'!$H$8 -> 1.1639667 | G139: 0.1 | H139: 0.1 | I139: 0 | J139: 0.75 | K139: 0.05 | L139: 0.1 | M139: =SUM(H139:L139) -> 1 | N139: 30 | O139: =60/N139 -> 2 | P139: =O139/60 -> 0.033333333 | Q139: =E139-F139 -> -0.0973 | R139: =Таблица1[[#This Row],[Profit]]/Таблица1[[#This Row],[Price]] -> -0.09121875 | S139: =VLOOKUP($A139,'Order Composition'!$B$2:$F$10,MATCH($C139,'Order Composition'!$B$2:$F$2,0),0) -> 0.4 | T139: =S139*Q139 -> -0.03892 | U139: =Таблица1[[#This Row],[Price]]*Таблица1[[#This Row],[Order]] -> 0.42666667 | V139: =Таблица1[[#This Row],[Cost(with labour)]]*Таблица1[[#This Row],[Order]] -> 0.46558667 | W139: =VLOOKUP($A139,'Mean order price'!$B$2:$H$10,7,0) -> 8 | X139: =W139*P139 -> 0.26666667
A140: Indianapolis | B140: =B139+1 -> 137 | C140: Appetizer | D140: Pirozhok B | E140: =VLOOKUP('Menu and cost - USA by city'!D140,'Menu and cost - Russia'!$D$4:$P$29,2,FALSE)*(VLOOKUP('Menu and cost - USA by city'!A140,COGS!$B$3:$I$10,8,FALSE)/3)*0.4 -> 1.0666667 | F140: =SUMPRODUCT(H140:L140,'Mean order price'!$C$8:$G$8)*G140+P140*'Mean order price'!$H$8 -> 1.2954667 | G140: 0.1 | H140: 0.1 | I140: 0.5 | J140: 0.25 | K140: 0.05 | L140: 0.1 | M140: =SUM(H140:L140) -> 1 | N140: 30 | O140: =60/N140 -> 2 | P140: =O140/60 -> 0.033333333 | Q140: =E140-F140 -> -0.2288 | R140: =Таблица1[[#This Row],[Profit]]/Таблица1[[#This Row],[Price]] -> -0.2145 | S140: =VLOOKUP($A140,'Order Composition'!$B$2:$F$10,MATCH($C140,'Order Composition'!$B$2:$F$2,0),0) -> 0.4 | T140: =S140*Q140 -> -0.09152 | U140: =Таблица1[[#This Row],[Price]]*Таблица1[[#This Row],[Order]] -> 0.42666667 | V140: =Таблица1[[#This Row],[Cost(with labour)]]*Таблица1[[#This Row],[Order]] -> 0.51818667 | W140: =VLOOKUP($A140,'Mean order price'!$B$2:$H$10,7,0) -> 8 | X140: =W140*P140 -> 0.26666667
A141: Indianapolis | B141: =B140+1 -> 138 | C141: Entry | D141: Blin A | E141: =VLOOKUP('Menu and cost - USA by city'!D141,'Menu and cost - Russia'!$D$4:$P$29,2,FALSE)*(VLOOKUP('Menu and cost - USA by city'!A141,COGS!$B$3:$I$10,8,FALSE)/3)*0.4 -> 3.2 | F141: =SUMPRODUCT(H141:L141,'Mean order price'!$C$8:$G$8)*G141+P141*'Mean order price'!$H$8 -> 2.3279333 | G141: 0.2 | H141: 0.1 | I141: 0 | J141: 0.75 | K141: 0.05 | L141: 0.1 | M141: =SUM(H141:L141) -> 1 | N141: 15 | O141: =60/N141 -> 4 | P141: =O141/60 -> 0.066666667 | Q141: =E141-F141 -> 0.87206667 | R141: =Таблица1[[#This Row],[Profit]]/Таблица1[[#This Row],[Price]] -> 0.27252083 | S141: =VLOOKUP($A141,'Order Composition'!$B$2:$F$10,MATCH($C141,'Order Composition'!$B$2:$F$2,0),0) -> 0.6 | T141: =S141*Q141 -> 0.52324 | U141: =Таблица1[[#This Row],[Price]]*Таблица1[[#This Row],[Order]] -> 1.92 | V141: =Таблица1[[#This Row],[Cost(with labour)]]*Таблица1[[#This Row],[Order]] -> 1.39676 | W141: =VLOOKUP($A141,'Mean order price'!$B$2:$H$10,7,0) -> 8 | X141: =W141*P141 -> 0.53333333
A142: Indianapolis | B142: =B141+1 -> 139 | C142: Entry | D142: Blin B | E142: =VLOOKUP('Menu and cost - USA by city'!D142,'Menu and cost - Russia'!$D$4:$P$29,2,FALSE)*(VLOOKUP('Menu and cost - USA by city'!A142,COGS!$B$3:$I$10,8,FALSE)/3)*0.4 -> 3.2 | F142: =SUMPRODUCT(H142:L142,'Mean order price'!$C$8:$G$8)*G142+P142*'Mean order price'!$H$8 -> 2.9288333 | G142: 0.3 | H142: 0.3 | I142: 0 | J142: 0.55 | K142: 0.05 | L142: 0.1 | M142: =SUM(H142:L142) -> 1 | N142: 15 | O142: =60/N142 -> 4 | P142: =O142/60 -> 0.066666667 | Q142: =E142-F142 -> 0.27116667 | R142: =Таблица1[[#This Row],[Profit]]/Таблица1[[#This Row],[Price]] -> 0.084739583 | S142: =VLOOKUP($A142,'Order Composition'!$B$2:$F$10,MATCH($C142,'Order Composition'!$B$2:$F$2,0),0) -> 0.6 | T142: =S142*Q142 -> 0.1627 | U142: =Таблица1[[#This Row],[Price]]*Таблица1[[#This Row],[Order]] -> 1.92 | V142: =Таблица1[[#This Row],[Cost(with labour)]]*Таблица1[[#This Row],[Order]] -> 1.7573 | W142: =VLOOKUP($A142,'Mean order price'!$B$2:$H$10,7,0) -> 8 | X142: =W142*P142 -> 0.53333333
A143: Indianapolis | B143: =B142+1 -> 140 | C143: Entry | D143: Blin C | E143: =VLOOKUP('Menu and cost - USA by city'!D143,'Menu and cost - Russia'!$D$4:$P$29,2,FALSE)*(VLOOKUP('Menu and cost - USA by city'!A143,COGS!$B$3:$I$10,8,FALSE)/3)*0.4 -> 3.2 | F143: =SUMPRODUCT(H143:L143,'Mean order price'!$C$8:$G$8)*G143+P143*'Mean order price'!$H$8 -> 3.4224833 | G143: 0.3 | H143: 0.1 | I143: 0.25 | J143: 0.5 | K143: 0.05 | L143: 0.1 | M143: =SUM(H143:L143) -> 1 | N143: 15 | O143: =60/N143 -> 4 | P143: =O143/60 -> 0.066666667 | Q143: =E143-F143 -> -0.22248333 | R143: =Таблица1[[#This Row],[Profit]]/Таблица1[[#This Row],[Price]] -> -0.069526042 | S143: =VLOOKUP($A143,'Order Composition'!$B$2:$F$10,MATCH($C143,'Order Composition'!$B$2:$F$2,0),0) -> 0.6 | T143: =S143*Q143 -> -0.13349 | U143: =Таблица1[[#This Row],[Price]]*Таблица1[[#This Row],[Order]] -> 1.92 | V143: =Таблица1[[#This Row],[Cost(with labour)]]*Таблица1[[#This Row],[Order]] -> 2.05349 | W143: =VLOOKUP($A143,'Mean order price'!$B$2:$H$10,7,0) -> 8 | X143: =W143*P143 -> 0.53333333
A144: Indianapolis | B144: =B143+1 -> 141 | C144: Entry | D144: Blin D | E144: =VLOOKUP('Menu and cost - USA by city'!D144,'Menu and cost - Russia'!$D$4:$P$29,2,FALSE)*(VLOOKUP('Menu and cost - USA by city'!A144,COGS!$B$3:$I$10,8,FALSE)/3)*0.4 -> 3.2 | F144: =SUMPRODUCT(H144:L144,'Mean order price'!$C$8:$G$8)*G144+P144*'Mean order price'!$H$8 -> 2.7062 | G144: 0.2 | H144: 0.2 | I144: 0.4 | J144: 0.25 | K144: 0.05 | L144: 0.1 | M144: =SUM(H144:L144) -> 1 | N144: 10 | O144: =60/N144 -> 6 | P144: =O144/60 -> 0.1 | Q144: =E144-F144 -> 0.4938 | R144: =Таблица1[[#This Row],[Profit]]/Таблица1[[#This Row],[Price]] -> 0.1543125 | S144: =VLOOKUP($A144,'Order Composition'!$B$2:$F$10,MATCH($C144,'Order Composition'!$B$2:$F$2,0),0) -> 0.6 | T144: =S144*Q144 -> 0.29628 | U144: =Таблица1[[#This Row],[Price]]*Таблица1[[#This Row],[Order]] -> 1.92 | V144: =Таблица1[[#This Row],[Cost(with labour)]]*Таблица1[[#This Row],[Order]] -> 1.62372 | W144: =VLOOKUP($A144,'Mean order price'!$B$2:$H$10,7,0) -> 8 | X144: =W144*P144 -> 0.8
A145: Indianapolis | B145: =B144+1 -> 142 | C145: Entry | D145: Blin E | E145: =VLOOKUP('Menu and cost - USA by city'!D145,'Menu and cost - Russia'!$D$4:$P$29,2,FALSE)*(VLOOKUP('Menu and cost - USA by city'!A145,COGS!$B$3:$I$10,8,FALSE)/3)*0.4 -> 4.2666667 | F145: =SUMPRODUCT(H145:L145,'Mean order price'!$C$8:$G$8)*G145+P145*'Mean order price'!$H$8 -> 3.8171 | G145: 0.3 | H145: 0.2 | I145: 0.6 | J145: 0.05 | K145: 0.05 | L145: 0.1 | M145: =SUM(H145:L145) -> 1 | N145: 10 | O145: =60/N145 -> 6 | P145: =O145/60 -> 0.1 | Q145: =E145-F145 -> 0.44956667 | R145: =Таблица1[[#This Row],[Profit]]/Таблица1[[#This Row],[Price]] -> 0.10536719 | S145: =VLOOKUP($A145,'Order Composition'!$B$2:$F$10,MATCH($C145,'Order Composition'!$B$2:$F$2,0),0) -> 0.6 | T145: =S145*Q145 -> 0.26974 | U145: =Таблица1[[#This Row],[Price]]*Таблица1[[#This Row],[Order]] -> 2.56 | V145: =Таблица1[[#This Row],[Cost(with labour)]]*Таблица1[[#This Row],[Order]] -> 2.29026 | W145: =VLOOKUP($A145,'Mean order price'!$B$2:$H$10,7,0) -> 8 | X145: =W145*P145 -> 0.8
... A159: Indianapolis | B159: =B158+1 -> 156 | C159: Beverages | D159: Hot Drink B | E159: =VLOOKUP('Menu and cost - USA by city'!D159,'Menu and cost - Russia'!$D$4:$P$29,2,FALSE)*(VLOOKUP('Menu and cost - USA by city'!A159,COGS!$B$3:$I$10,8,FALSE)/3)*0.4 -> 1.6 | F159: =SUMPRODUCT(H159:L159,'Mean order price'!$C$8:$G$8)*G159+P159*'Mean order price'!$H$8 -> 1.2412 | G159: 0.2 | H159: 0 | I159: 0 | J159: 0.1 | K159: 0.9 | L159: 0 | M159: =SUM(H159:L159) -> 1 | N159: 40 | O159: =60/N159 -> 1.5 | P159: =O159/60 -> 0.025 | Q159: =E159-F159 -> 0.3588 | R159: =Таблица1[[#This Row],[Profit]]/Таблица1[[#This Row],[Price]] -> 0.22425 | S159: =VLOOKUP($A159,'Order Composition'!$B$2:$F$10,MATCH($C159,'Order Composition'!$B$2:$F$2,0),0) -> 0.8 | T159: =S159*Q159 -> 0.28704 | U159: =Таблица1[[#This Row],[Price]]*Таблица1[[#This Row],[Order]] -> 1.28 | V159: =Таблица1[[#This Row],[Cost(with labour)]]*Таблица1[[#This Row],[Order]] -> 0.99296 | W159: =VLOOKUP($A159,'Mean order price'!$B$2:$H$10,7,0) -> 8 | X159: =W159*P159 -> 0.2
A160: Birmingham | B160: =B159+1 -> 157 | C160: Appetizer | D160: Salad A | E160: =VLOOKUP('Menu and cost - USA by city'!D160,'Menu and cost - Russia'!$D$4:$P$29,2,FALSE)*(VLOOKUP('Menu and cost - USA by city'!A160,COGS!$B$3:$I$10,8,FALSE)/3)*0.4 -> 4 | F160: =SUMPRODUCT(H160:L160,'Mean order price'!$C$9:$G$9)*G160+P160*'Mean order price'!$H$9 -> 3.26 | G160: 0.2 | H160: 0 | I160: 0 | J160: 0.9 | K160: 0 | L160: 0.1 | M160: =SUM(H160:L160) -> 1 | N160: 20 | O160: =60/N160 -> 3 | P160: =O160/60 -> 0.05 | Q160: =E160-F160 -> 0.74 | R160: =Таблица1[[#This Row],[Profit]]/Таблица1[[#This Row],[Price]] -> 0.185 | S160: =VLOOKUP($A160,'Order Composition'!$B$2:$F$10,MATCH($C160,'Order Composition'!$B$2:$F$2,0),0) -> 0.2 | T160: =S160*Q160 -> 0.148 | U160: =Таблица1[[#This Row],[Price]]*Таблица1[[#This Row],[Order]] -> 0.8 | V160: =Таблица1[[#This Row],[Cost(with labour)]]*Таблица1[[#This Row],[Order]] -> 0.652 | W160: =VLOOKUP($A160,'Mean order price'!$B$2:$H$10,7,0) -> 10 | X160: =W160*P160 -> 0.5
A161: Birmingham | B161: =B160+1 -> 158 | C161: Appetizer | D161: Salad B | E161: =VLOOKUP('Menu and cost - USA by city'!D161,'Menu and cost - Russia'!$D$4:$P$29,2,FALSE)*(VLOOKUP('Menu and cost - USA by city'!A161,COGS!$B$3:$I$10,8,FALSE)/3)*0.4 -> 4 | F161: =SUMPRODUCT(H161:L161,'Mean order price'!$C$9:$G$9)*G161+P161*'Mean order price'!$H$9 -> 3.274 | G161: 0.2 | H161: 0 | I161: 0.2 | J161: 0.7 | K161: 0 | L161: 0.1 | M161: =SUM(H161:L161) -> 1 | N161: 20 | O161: =60/N161 -> 3 | P161: =O161/60 -> 0.05 | Q161: =E161-F161 -> 0.726 | R161: =Таблица1[[#This Row],[Profit]]/Таблица1[[#This Row],[Price]] -> 0.1815 | S161: =VLOOKUP($A161,'Order Composition'!$B$2:$F$10,MATCH($C161,'Order Composition'!$B$2:$F$2,0),0) -> 0.2 | T161: =S161*Q161 -> 0.1452 | U161: =Таблица1[[#This Row],[Price]]*Таблица1[[#This Row],[Order]] -> 0.8 | V161: =Таблица1[[#This Row],[Cost(with labour)]]*Таблица1[[#This Row],[Order]] -> 0.6548 | W161: =VLOOKUP($A161,'Mean order price'!$B$2:$H$10,7,0) -> 10 | X161: =W161*P161 -> 0.5
A162: Birmingham | B162: =B161+1 -> 159 | C162: Appetizer | D162: Salad C | E162: =VLOOKUP('Menu and cost - USA by city'!D162,'Menu and cost - Russia'!$D$4:$P$29,2,FALSE)*(VLOOKUP('Menu and cost - USA by city'!A162,COGS!$B$3:$I$10,8,FALSE)/3)*0.4 -> 4 | F162: =SUMPRODUCT(H162:L162,'Mean order price'!$C$9:$G$9)*G162+P162*'Mean order price'!$H$9 -> 3.295 | G162: 0.2 | H162: 0 | I162: 0.5 | J162: 0.4 | K162: 0 | L162: 0.1 | M162: =SUM(H162:L162) -> 1 | N162: 20 | O162: =60/N162 -> 3 | P162: =O162/60 -> 0.05 | Q162: =E162-F162 -> 0.705 | R162: =Таблица1[[#This Row],[Profit]]/Таблица1[[#This Row],[Price]] -> 0.17625 | S162: =VLOOKUP($A162,'Order Composition'!$B$2:$F$10,MATCH($C162,'Order Composition'!$B$2:$F$2,0),0) -> 0.2 | T162: =S162*Q162 -> 0.141 | U162: =Таблица1[[#This Row],[Price]]*Таблица1[[#This Row],[Order]] -> 0.8 | V162: =Таблица1[[#This Row],[Cost(with labour)]]*Таблица1[[#This Row],[Order]] -> 0.659 | W162: =VLOOKUP($A162,'Mean order price'!$B$2:$H$10,7,0) -> 10 | X162: =W162*P162 -> 0.5
A163: Birmingham | B163: =B162+1 -> 160 | C163: Appetizer | D163: Soup A | E163: =VLOOKUP('Menu and cost - USA by city'!D163,'Menu and cost - Russia'!$D$4:$P$29,2,FALSE)*(VLOOKUP('Menu and cost - USA by city'!A163,COGS!$B$3:$I$10,8,FALSE)/3)*0.4 -> 2.6666667 | F163: =SUMPRODUCT(H163:L163,'Mean order price'!$C$9:$G$9)*G163+P163*'Mean order price'!$H$9 -> 2.3314667 | G163: 0.2 | H163: 0.1 | I163: 0 | J163: 0.4 | K163: 0.1 | L163: 0.4 | M163: =SUM(H163:L163) -> 1 | N163: 60 | O163: =60/N163 -> 1 | P163: =O163/60 -> 0.016666667 | Q163: =E163-F163 -> 0.3352 | R163: =Таблица1[[#This Row],[Profit]]/Таблица1[[#This Row],[Price]] -> 0.1257 | S163: =VLOOKUP($A163,'Order Composition'!$B$2:$F$10,MATCH($C163,'Order Composition'!$B$2:$F$2,0),0) -> 0.2 | T163: =S163*Q163 -> 0.06704 | U163: =Таблица1[[#This Row],[Price]]*Таблица1[[#This Row],[Order]] -> 0.53333333 | V163: =Таблица1[[#This Row],[Cost(with labour)]]*Таблица1[[#This Row],[Order]] -> 0.46629333 | W163: =VLOOKUP($A163,'Mean order price'!$B$2:$H$10,7,0) -> 10 | X163: =W163*P163 -> 0.16666667
A164: Birmingham | B164: =B163+1 -> 161 | C164: Appetizer | D164: Soup B | E164: =VLOOKUP('Menu and cost - USA by city'!D164,'Menu and cost - Russia'!$D$4:$P$29,2,FALSE)*(VLOOKUP('Menu and cost - USA by city'!A164,COGS!$B$3:$I$10,8,FALSE)/3)*0.4 -> 2.6666667 | F164: =SUMPRODUCT(H164:L164,'Mean order price'!$C$9:$G$9)*G164+P164*'Mean order price'!$H$9 -> 2.4734667 | G164: 0.2 | H164: 0.1 | I164: 0.2 | J164: 0.3 | K164: 0.1 | L164: 0.3 | M164: =SUM(H164:L164) -> 1 | N164: 60 | O164: =60/N164 -> 1 | P164: =O164/60 -> 0.016666667 | Q164: =E164-F164 -> 0.1932 | R164: =Таблица1[[#This Row],[Profit]]/Таблица1[[#This Row],[Price]] -> 0.07245 | S164: =VLOOKUP($A164,'Order Composition'!$B$2:$F$10,MATCH($C164,'Order Composition'!$B$2:$F$2,0),0) -> 0.2 | T164: =S164*Q164 -> 0.03864 | U164: =Таблица1[[#This Row],[Price]]*Таблица1[[#This Row],[Order]] -> 0.53333333 | V164: =Таблица1[[#This Row],[Cost(with labour)]]*Таблица1[[#This Row],[Order]] -> 0.49469333 | W164: =VLOOKUP($A164,'Mean order price'!$B$2:$H$10,7,0) -> 10 | X164: =W164*P164 -> 0.16666667
A165: Birmingham | B165: =B164+1 -> 162 | C165: Appetizer | D165: Pirozhok A | E165: =VLOOKUP('Menu and cost - USA by city'!D165,'Menu and cost - Russia'!$D$4:$P$29,2,FALSE)*(VLOOKUP('Menu and cost - USA by city'!A165,COGS!$B$3:$I$10,8,FALSE)/3)*0.4 -> 1.3333333 | F165: =SUMPRODUCT(H165:L165,'Mean order price'!$C$9:$G$9)*G165+P165*'Mean order price'!$H$9 -> 1.6364333 | G165: 0.1 | H165: 0.1 | I165: 0 | J165: 0.75 | K165: 0.05 | L165: 0.1 | M165: =SUM(H165:L165) -> 1 | N165: 30 | O165: =60/N165 -> 2 | P165: =O165/60 -> 0.033333333 | Q165: =E165-F165 -> -0.3031 | R165: =Таблица1[[#This Row],[Profit]]/Таблица1[[#This Row],[Price]] -> -0.227325 | S165: =VLOOKUP($A165,'Order Composition'!$B$2:$F$10,MATCH($C165,'Order Composition'!$B$2:$F$2,0),0) -> 0.2 | T165: =S165*Q165 -> -0.06062 | U165: =Таблица1[[#This Row],[Price]]*Таблица1[[#This Row],[Order]] -> 0.26666667 | V165: =Таблица1[[#This Row],[Cost(with labour)]]*Таблица1[[#This Row],[Order]] -> 0.32728667 | W165: =VLOOKUP($A165,'Mean order price'!$B$2:$H$10,7,0) -> 10 | X165: =W165*P165 -> 0.33333333
A166: Birmingham | B166: =B165+1 -> 163 | C166: Appetizer | D166: Pirozhok B | E166: =VLOOKUP('Menu and cost - USA by city'!D166,'Menu and cost - Russia'!$D$4:$P$29,2,FALSE)*(VLOOKUP('Menu and cost - USA by city'!A166,COGS!$B$3:$I$10,8,FALSE)/3)*0.4 -> 1.3333333 | F166: =SUMPRODUCT(H166:L166,'Mean order price'!$C$9:$G$9)*G166+P166*'Mean order price'!$H$9 -> 1.6539333 | G166: 0.1 | H166: 0.1 | I166: 0.5 | J166: 0.25 | K166: 0.05 | L166: 0.1 | M166: =SUM(H166:L166) -> 1 | N166: 30 | O166: =60/N166 -> 2 | P166: =O166/60 -> 0.033333333 | Q166: =E166-F166 -> -0.3206 | R166: =Таблица1[[#This Row],[Profit]]/Таблица1[[#This Row],[Price]] -> -0.24045 | S166: =VLOOKUP($A166,'Order Composition'!$B$2:$F$10,MATCH($C166,'Order Composition'!$B$2:$F$2,0),0) -> 0.2 | T166: =S166*Q166 -> -0.06412 | U166: =Таблица1[[#This Row],[Price]]*Таблица1[[#This Row],[Order]] -> 0.26666667 | V166: =Таблица1[[#This Row],[Cost(with labour)]]*Таблица1[[#This Row],[Order]] -> 0.33078667 | W166: =VLOOKUP($A166,'Mean order price'!$B$2:$H$10,7,0) -> 10 | X166: =W166*P166 -> 0.33333333
A167: Birmingham | B167: =B166+1 -> 164 | C167: Entry | D167: Blin A | E167: =VLOOKUP('Menu and cost - USA by city'!D167,'Menu and cost - Russia'!$D$4:$P$29,2,FALSE)*(VLOOKUP('Menu and cost - USA by city'!A167,COGS!$B$3:$I$10,8,FALSE)/3)*0.4 -> 4 | F167: =SUMPRODUCT(H167:L167,'Mean order price'!$C$9:$G$9)*G167+P167*'Mean order price'!$H$9 -> 3.2728667 | G167: 0.2 | H167: 0.1 | I167: 0 | J167: 0.75 | K167: 0.05 | L167: 0.1 | M167: =SUM(H167:L167) -> 1 | N167: 15 | O167: =60/N167 -> 4 | P167: =O167/60 -> 0.066666667 | Q167: =E167-F167 -> 0.72713333 | R167: =Таблица1[[#This Row],[Profit]]/Таблица1[[#This Row],[Price]] -> 0.18178333 | S167: =VLOOKUP($A167,'Order Composition'!$B$2:$F$10,MATCH($C167,'Order Composition'!$B$2:$F$2,0),0) -> 0.65 | T167: =S167*Q167 -> 0.47263667 | U167: =Таблица1[[#This Row],[Price]]*Таблица1[[#This Row],[Order]] -> 2.6 | V167: =Таблица1[[#This Row],[Cost(with labour)]]*Таблица1[[#This Row],[Order]] -> 2.1273633 | W167: =VLOOKUP($A167,'Mean order price'!$B$2:$H$10,7,0) -> 10 | X167: =W167*P167 -> 0.66666667
A168: Birmingham | B168: =B167+1 -> 165 | C168: Entry | D168: Blin B | E168: =VLOOKUP('Menu and cost - USA by city'!D168,'Menu and cost - Russia'!$D$4:$P$29,2,FALSE)*(VLOOKUP('Menu and cost - USA by city'!A168,COGS!$B$3:$I$10,8,FALSE)/3)*0.4 -> 4 | F168: =SUMPRODUCT(H168:L168,'Mean order price'!$C$9:$G$9)*G168+P168*'Mean order price'!$H$9 -> 4.2867667 | G168: 0.3 | H168: 0.3 | I168: 0 | J168: 0.55 | K168: 0.05 | L168: 0.1 | M168: =SUM(H168:L168) -> 1 | N168: 15 | O168: =60/N168 -> 4 | P168: =O168/60 -> 0.066666667 | Q168: =E168-F168 -> -0.28676667 | R168: =Таблица1[[#This Row],[Profit]]/Таблица1[[#This Row],[Price]] -> -0.071691667 | S168: =VLOOKUP($A168,'Order Composition'!$B$2:$F$10,MATCH($C168,'Order Composition'!$B$2:$F$2,0),0) -> 0.65 | T168: =S168*Q168 -> -0.18639833 | U168: =Таблица1[[#This Row],[Price]]*Таблица1[[#This Row],[Order]] -> 2.6 | V168: =Таблица1[[#This Row],[Cost(with labour)]]*Таблица1[[#This Row],[Order]] -> 2.7863983 | W168: =VLOOKUP($A168,'Mean order price'!$B$2:$H$10,7,0) -> 10 | X168: =W168*P168 -> 0.66666667
A169: Birmingham | B169: =B168+1 -> 166 | C169: Entry | D169: Blin C | E169: =VLOOKUP('Menu and cost - USA by city'!D169,'Menu and cost - Russia'!$D$4:$P$29,2,FALSE)*(VLOOKUP('Menu and cost - USA by city'!A169,COGS!$B$3:$I$10,8,FALSE)/3)*0.4 -> 4 | F169: =SUMPRODUCT(H169:L169,'Mean order price'!$C$9:$G$9)*G169+P169*'Mean order price'!$H$9 -> 4.6022167 | G169: 0.3 | H169: 0.1 | I169: 0.25 | J169: 0.5 | K169: 0.05 | L169: 0.1 | M169: =SUM(H169:L169) -> 1 | N169: 15 | O169: =60/N169 -> 4 | P169: =O169/60 -> 0.066666667 | Q169: =E169-F169 -> -0.60221667 | R169: =Таблица1[[#This Row],[Profit]]/Таблица1[[#This Row],[Price]] -> -0.15055417 | S169: =VLOOKUP($A169,'Order Composition'!$B$2:$F$10,MATCH($C169,'Order Composition'!$B$2:$F$2,0),0) -> 0.65 | T169: =S169*Q169 -> -0.39144083 | U169: =Таблица1[[#This Row],[Price]]*Таблица1[[#This Row],[Order]] -> 2.6 | V169: =Таблица1[[#This Row],[Cost(with labour)]]*Таблица1[[#This Row],[Order]] -> 2.9914408 | W169: =VLOOKUP($A169,'Mean order price'!$B$2:$H$10,7,0) -> 10 | X169: =W169*P169 -> 0.66666667
A170: Birmingham | B170: =B169+1 -> 167 | C170: Entry | D170: Blin D | E170: =VLOOKUP('Menu and cost - USA by city'!D170,'Menu and cost - Russia'!$D$4:$P$29,2,FALSE)*(VLOOKUP('Menu and cost - USA by city'!A170,COGS!$B$3:$I$10,8,FALSE)/3)*0.4 -> 4 | F170: =SUMPRODUCT(H170:L170,'Mean order price'!$C$9:$G$9)*G170+P170*'Mean order price'!$H$9 -> 3.5378 | G170: 0.2 | H170: 0.2 | I170: 0.4 | J170: 0.25 | K170: 0.05 | L170: 0.1 | M170: =SUM(H170:L170) -> 1 | N170: 10 | O170: =60/N170 -> 6 | P170: =O170/60 -> 0.1 | Q170: =E170-F170 -> 0.4622 | R170: =Таблица1[[#This Row],[Profit]]/Таблица1[[#This Row],[Price]] -> 0.11555 | S170: =VLOOKUP($A170,'Order Composition'!$B$2:$F$10,MATCH($C170,'Order Composition'!$B$2:$F$2,0),0) -> 0.65 | T170: =S170*Q170 -> 0.30043 | U170: =Таблица1[[#This Row],[Price]]*Таблица1[[#This Row],[Order]] -> 2.6 | V170: =Таблица1[[#This Row],[Cost(with labour)]]*Таблица1[[#This Row],[Order]] -> 2.29957 | W170: =VLOOKUP($A170,'Mean order price'!$B$2:$H$10,7,0) -> 10 | X170: =W170*P170 -> 1
A171: Birmingham | B171: =B170+1 -> 168 | C171: Entry | D171: Blin E | E171: =VLOOKUP('Menu and cost - USA by city'!D171,'Menu and cost - Russia'!$D$4:$P$29,2,FALSE)*(VLOOKUP('Menu and cost - USA by city'!A171,COGS!$B$3:$I$10,8,FALSE)/3)*0.4 -> 5.3333333 | F171: =SUMPRODUCT(H171:L171,'Mean order price'!$C$9:$G$9)*G171+P171*'Mean order price'!$H$9 -> 4.8277 | G171: 0.3 | H171: 0.2 | I171: 0.6 | J171: 0.05 | K171: 0.05 | L171: 0.1 | M171: =SUM(H171:L171) -> 1 | N171: 10 | O171: =60/N171 -> 6 | P171: =O171/60 -> 0.1 | Q171: =E171-F171 -> 0.50563333 | R171: =Таблица1[[#This Row],[Profit]]/Таблица1[[#This Row],[Price]] -> 0.09480625 | S171: =VLOOKUP($A171,'Order Composition'!$B$2:$F$10,MATCH($C171,'Order Composition'!$B$2:$F$2,0),0) -> 0.65 | T171: =S171*Q171 -> 0.32866167 | U171: =Таблица1[[#This Row],[Price]]*Таблица1[[#This Row],[Order]] -> 3.4666667 | V171: =Таблица1[[#This Row],[Cost(with labour)]]*Таблица1[[#This Row],[Order]] -> 3.138005 | W171: =VLOOKUP($A171,'Mean order price'!$B$2:$H$10,7,0) -> 10 | X171: =W171*P171 -> 1
... A185: Birmingham | B185: =B184+1 -> 182 | C185: Beverages | D185: Hot Drink B | E185: =VLOOKUP('Menu and cost - USA by city'!D185,'Menu and cost - Russia'!$D$4:$P$29,2,FALSE)*(VLOOKUP('Menu and cost - USA by city'!A185,COGS!$B$3:$I$10,8,FALSE)/3)*0.4 -> 2 | F185: =SUMPRODUCT(H185:L185,'Mean order price'!$C$9:$G$9)*G185+P185*'Mean order price'!$H$9 -> 2.1048 | G185: 0.2 | H185: 0 | I185: 0 | J185: 0.1 | K185: 0.9 | L185: 0 | M185: =SUM(H185:L185) -> 1 | N185: 40 | O185: =60/N185 -> 1.5 | P185: =O185/60 -> 0.025 | Q185: =E185-F185 -> -0.1048 | R185: =Таблица1[[#This Row],[Profit]]/Таблица1[[#This Row],[Price]] -> -0.0524 | S185: =VLOOKUP($A185,'Order Composition'!$B$2:$F$10,MATCH($C185,'Order Composition'!$B$2:$F$2,0),0) -> 0.75 | T185: =S185*Q185 -> -0.0786 | U185: =Таблица1[[#This Row],[Price]]*Таблица1[[#This Row],[Order]] -> 1.5 | V185: =Таблица1[[#This Row],[Cost(with labour)]]*Таблица1[[#This Row],[Order]] -> 1.5786 | W185: =VLOOKUP($A185,'Mean order price'!$B$2:$H$10,7,0) -> 10 | X185: =W185*P185 -> 0.25
A186: Portland | B186: =B185+1 -> 183 | C186: Appetizer | D186: Salad A | E186: =VLOOKUP('Menu and cost - USA by city'!D186,'Menu and cost - Russia'!$D$4:$P$29,2,FALSE)*(VLOOKUP('Menu and cost - USA by city'!A186,COGS!$B$3:$I$10,8,FALSE)/3)*0.4 -> 5.6 | F186: =SUMPRODUCT(H186:L186,'Mean order price'!$C$10:$G$10)*G186+P186*'Mean order price'!$H$10 -> 3.2678 | G186: 0.2 | H186: 0 | I186: 0 | J186: 0.9 | K186: 0 | L186: 0.1 | M186: =SUM(H186:L186) -> 1 | N186: 20 | O186: =60/N186 -> 3 | P186: =O186/60 -> 0.05 | Q186: =E186-F186 -> 2.3322 | R186: =Таблица1[[#This Row],[Profit]]/Таблица1[[#This Row],[Price]] -> 0.41646429 | S186: =VLOOKUP($A186,'Order Composition'!$B$2:$F$10,MATCH($C186,'Order Composition'!$B$2:$F$2,0),0) -> 0.35 | T186: =S186*Q186 -> 0.81627 | U186: =Таблица1[[#This Row],[Price]]*Таблица1[[#This Row],[Order]] -> 1.96 | V186: =Таблица1[[#This Row],[Cost(with labour)]]*Таблица1[[#This Row],[Order]] -> 1.14373 | W186: =VLOOKUP($A186,'Mean order price'!$B$2:$H$10,7,0) -> 14 | X186: =W186*P186 -> 0.7
A187: Portland | B187: =B186+1 -> 184 | C187: Appetizer | D187: Salad B | E187: =VLOOKUP('Menu and cost - USA by city'!D187,'Menu and cost - Russia'!$D$4:$P$29,2,FALSE)*(VLOOKUP('Menu and cost - USA by city'!A187,COGS!$B$3:$I$10,8,FALSE)/3)*0.4 -> 5.6 | F187: =SUMPRODUCT(H187:L187,'Mean order price'!$C$10:$G$10)*G187+P187*'Mean order price'!$H$10 -> 3.2998 | G187: 0.2 | H187: 0 | I187: 0.2 | J187: 0.7 | K187: 0 | L187: 0.1 | M187: =SUM(H187:L187) -> 1 | N187: 20 | O187: =60/N187 -> 3 | P187: =O187/60 -> 0.05 | Q187: =E187-F187 -> 2.3002 | R187: =Таблица1[[#This Row],[Profit]]/Таблица1[[#This Row],[Price]] -> 0.41075 | S187: =VLOOKUP($A187,'Order Composition'!$B$2:$F$10,MATCH($C187,'Order Composition'!$B$2:$F$2,0),0) -> 0.35 | T187: =S187*Q187 -> 0.80507 | U187: =Таблица1[[#This Row],[Price]]*Таблица1[[#This Row],[Order]] -> 1.96 | V187: =Таблица1[[#This Row],[Cost(with labour)]]*Таблица1[[#This Row],[Order]] -> 1.15493 | W187: =VLOOKUP($A187,'Mean order price'!$B$2:$H$10,7,0) -> 14 | X187: =W187*P187 -> 0.7
A188: Portland | B188: =B187+1 -> 185 | C188: Appetizer | D188: Salad C | E188: =VLOOKUP('Menu and cost - USA by city'!D188,'Menu and cost - Russia'!$D$4:$P$29,2,FALSE)*(VLOOKUP('Menu and cost - USA by city'!A188,COGS!$B$3:$I$10,8,FALSE)/3)*0.4 -> 5.6 | F188: =SUMPRODUCT(H188:L188,'Mean order price'!$C$10:$G$10)*G188+P188*'Mean order price'!$H$10 -> 3.3478 | G188: 0.2 | H188: 0 | I188: 0.5 | J188: 0.4 | K188: 0 | L188: 0.1 | M188: =SUM(H188:L188) -> 1 | N188: 20 | O188: =60/N188 -> 3 | P188: =O188/60 -> 0.05 | Q188: =E188-F188 -> 2.2522 | R188: =Таблица1[[#This Row],[Profit]]/Таблица1[[#This Row],[Price]] -> 0.40217857 | S188: =VLOOKUP($A188,'Order Composition'!$B$2:$F$10,MATCH($C188,'Order Composition'!$B$2:$F$2,0),0) -> 0.35 | T188: =S188*Q188 -> 0.78827 | U188: =Таблица1[[#This Row],[Price]]*Таблица1[[#This Row],[Order]] -> 1.96 | V188: =Таблица1[[#This Row],[Cost(with labour)]]*Таблица1[[#This Row],[Order]] -> 1.17173 | W188: =VLOOKUP($A188,'Mean order price'!$B$2:$H$10,7,0) -> 14 | X188: =W188*P188 -> 0.7
A189: Portland | B189: =B188+1 -> 186 | C189: Appetizer | D189: Soup A | E189: =VLOOKUP('Menu and cost - USA by city'!D189,'Menu and cost - Russia'!$D$4:$P$29,2,FALSE)*(VLOOKUP('Menu and cost - USA by city'!A189,COGS!$B$3:$I$10,8,FALSE)/3)*0.4 -> 3.7333333 | F189: =SUMPRODUCT(H189:L189,'Mean order price'!$C$10:$G$10)*G189+P189*'Mean order price'!$H$10 -> 2.1831333 | G189: 0.2 | H189: 0.1 | I189: 0 | J189: 0.4 | K189: 0.1 | L189: 0.4 | M189: =SUM(H189:L189) -> 1 | N189: 60 | O189: =60/N189 -> 1 | P189: =O189/60 -> 0.016666667 | Q189: =E189-F189 -> 1.5502 | R189: =Таблица1[[#This Row],[Profit]]/Таблица1[[#This Row],[Price]] -> 0.41523214 | S189: =VLOOKUP($A189,'Order Composition'!$B$2:$F$10,MATCH($C189,'Order Composition'!$B$2:$F$2,0),0) -> 0.35 | T189: =S189*Q189 -> 0.54257 | U189: =Таблица1[[#This Row],[Price]]*Таблица1[[#This Row],[Order]] -> 1.3066667 | V189: =Таблица1[[#This Row],[Cost(with labour)]]*Таблица1[[#This Row],[Order]] -> 0.76409667 | W189: =VLOOKUP($A189,'Mean order price'!$B$2:$H$10,7,0) -> 14 | X189: =W189*P189 -> 0.23333333
A190: Portland | B190: =B189+1 -> 187 | C190: Appetizer | D190: Soup B | E190: =VLOOKUP('Menu and cost - USA by city'!D190,'Menu and cost - Russia'!$D$4:$P$29,2,FALSE)*(VLOOKUP('Menu and cost - USA by city'!A190,COGS!$B$3:$I$10,8,FALSE)/3)*0.4 -> 3.7333333 | F190: =SUMPRODUCT(H190:L190,'Mean order price'!$C$10:$G$10)*G190+P190*'Mean order price'!$H$10 -> 2.3573333 | G190: 0.2 | H190: 0.1 | I190: 0.2 | J190: 0.3 | K190: 0.1 | L190: 0.3 | M190: =SUM(H190:L190) -> 1 | N190: 60 | O190: =60/N190 -> 1 | P190: =O190/60 -> 0.016666667 | Q190: =E190-F190 -> 1.376 | R190: =Таблица1[[#This Row],[Profit]]/Таблица1[[#This Row],[Price]] -> 0.36857143 | S190: =VLOOKUP($A190,'Order Composition'!$B$2:$F$10,MATCH($C190,'Order Composition'!$B$2:$F$2,0),0) -> 0.35 | T190: =S190*Q190 -> 0.4816 | U190: =Таблица1[[#This Row],[Price]]*Таблица1[[#This Row],[Order]] -> 1.3066667 | V190: =Таблица1[[#This Row],[Cost(with labour)]]*Таблица1[[#This Row],[Order]] -> 0.82506667 | W190: =VLOOKUP($A190,'Mean order price'!$B$2:$H$10,7,0) -> 14 | X190: =W190*P190 -> 0.23333333
A191: Portland | B191: =B190+1 -> 188 | C191: Appetizer | D191: Pirozhok A | E191: =VLOOKUP('Menu and cost - USA by city'!D191,'Menu and cost - Russia'!$D$4:$P$29,2,FALSE)*(VLOOKUP('Menu and cost - USA by city'!A191,COGS!$B$3:$I$10,8,FALSE)/3)*0.4 -> 1.8666667 | F191: =SUMPRODUCT(H191:L191,'Mean order price'!$C$10:$G$10)*G191+P191*'Mean order price'!$H$10 -> 1.6814167 | G191: 0.1 | H191: 0.1 | I191: 0 | J191: 0.75 | K191: 0.05 | L191: 0.1 | M191: =SUM(H191:L191) -> 1 | N191: 30 | O191: =60/N191 -> 2 | P191: =O191/60 -> 0.033333333 | Q191: =E191-F191 -> 0.18525 | R191: =Таблица1[[#This Row],[Profit]]/Таблица1[[#This Row],[Price]] -> 0.099241071 | S191: =VLOOKUP($A191,'Order Composition'!$B$2:$F$10,MATCH($C191,'Order Composition'!$B$2:$F$2,0),0) -> 0.35 | T191: =S191*Q191 -> 0.0648375 | U191: =Таблица1[[#This Row],[Price]]*Таблица1[[#This Row],[Order]] -> 0.65333333 | V191: =Таблица1[[#This Row],[Cost(with labour)]]*Таблица1[[#This Row],[Order]] -> 0.58849583 | W191: =VLOOKUP($A191,'Mean order price'!$B$2:$H$10,7,0) -> 14 | X191: =W191*P191 -> 0.46666667
A192: Portland | B192: =B191+1 -> 189 | C192: Appetizer | D192: Pirozhok B | E192: =VLOOKUP('Menu and cost - USA by city'!D192,'Menu and cost - Russia'!$D$4:$P$29,2,FALSE)*(VLOOKUP('Menu and cost - USA by city'!A192,COGS!$B$3:$I$10,8,FALSE)/3)*0.4 -> 1.8666667 | F192: =SUMPRODUCT(H192:L192,'Mean order price'!$C$10:$G$10)*G192+P192*'Mean order price'!$H$10 -> 1.7214167 | G192: 0.1 | H192: 0.1 | I192: 0.5 | J192: 0.25 | K192: 0.05 | L192: 0.1 | M192: =SUM(H192:L192) -> 1 | N192: 30 | O192: =60/N192 -> 2 | P192: =O192/60 -> 0.033333333 | Q192: =E192-F192 -> 0.14525 | R192: =Таблица1[[#This Row],[Profit]]/Таблица1[[#This Row],[Price]] -> 0.0778125 | S192: =VLOOKUP($A192,'Order Composition'!$B$2:$F$10,MATCH($C192,'Order Composition'!$B$2:$F$2,0),0) -> 0.35 | T192: =S192*Q192 -> 0.0508375 | U192: =Таблица1[[#This Row],[Price]]*Таблица1[[#This Row],[Order]] -> 0.65333333 | V192: =Таблица1[[#This Row],[Cost(with labour)]]*Таблица1[[#This Row],[Order]] -> 0.60249583 | W192: =VLOOKUP($A192,'Mean order price'!$B$2:$H$10,7,0) -> 14 | X192: =W192*P192 -> 0.46666667
...

Sheet Pivot tables
A1: Category | B1: (Все)
G2: Среднее по категориям
A3: Названия строк | B3: Среднее по полю Price | C3: Среднее по полю Cost(with labour) | D3: Среднее по полю Profit | G3: Названия строк | H3: Среднее по полю Gross profit margin
A4: Portland | B4: 4.9179487 | C4: 3.0146462 | D4: 1.9033026 | G4: Birmingham | H4: 0.15490164
A5: Cleveland | B5: 3.8641026 | C5: 2.5339865 | D5: 1.330116 | G5: Cincinnati | H5: 0.352317
A6: Cincinnati | B6: 3.6884615 | C6: 2.3889538 | D6: 1.2995077 | G6: Cleveland | H6: 0.34422379
A7: Columbus | B7: 3.5128205 | C7: 2.6082115 | D7: 0.90460897 | G7: Columbus | H7: 0.25751642
A8: Indianapolis | B8: 2.8102564 | C8: 2.123125 | D8: 0.68713141 | G8: Indianapolis | H8: 0.24450844
A9: Birmingham | B9: 3.5128205 | C9: 2.9686788 | D9: 0.54414167 | G9: Las Vegas | H9: -0.10839173
A10: Miami | B10: 3.3371795 | C10: 3.3444288 | D10: -0.007249359 | G10: Miami | H10: -0.0021723012
A11: Las Vegas | B11: 3.1615385 | C11: 3.5042231 | D11: -0.34268462 | G11: Portland | H11: 0.38701147
A12: Общий итог | B12: 3.600641 | C12: 2.8107817 | D12: 0.78985929 | G12: Общий итог | H12: 0.2193663
G16: Profit each Order
G17: Среднее по полю Order * Profit | H17: Названия столбцов
A18: Названия строк | B18: Сумма по полю Order * Profit | C18: Сумма по полю Order * Profit2 | G18: Названия строк | H18: Appetizer | I18: Beverages | J18: Dessert | K18: Entry | L18: Summ Order Profit
A19: Fruit Blin B | B19: 0.25090302 | C19: 6.3257717 | G19: Birmingham | H19: 0.059305714 | I19: 0.16491667 | J19: 0.63164 | K19: 0.42521158 | L19: =SUM(H19:K19) -> 1.281074
A20: Portland | B20: 0.29370224 | C20: 1.8578933 | G20: Cincinnati | H20: 0.48623143 | I20: 0.90666667 | J20: 0.7764 | K20: 0.898548 | L20: =SUM(H20:K20) -> 3.0678461
A21: Cleveland | B21: 0.2194233 | C21: 1.3880217 | G21: Cleveland | H21: 0.35544 | I21: 0.82520833 | J21: 1.1081156 | K21: 1.3359351 | L21: =SUM(H21:K21) -> 3.624699
A22: Cincinnati | B22: 0.15193087 | C22: 0.96108 | G22: Columbus | H22: 0.16909714 | I22: 0.60364444 | J22: 0.57079556 | K22: 0.55849017 | L22: =SUM(H22:K22) -> 1.9020273
A23: Columbus | B23: 0.10036457 | C23: 0.63488333 | G23: Indianapolis | H23: 0.1614 | I23: 0.49768889 | J23: 0.86707111 | K23: 0.438383 | L23: =SUM(H23:K23) -> 1.964543
A24: Indianapolis | B24: 0.092086789 | C24: 0.58252 | G24: Las Vegas | H24: -0.23294071 | I24: -0.19005 | J24: 0.55617333 | K24: -0.635553 | L24: =SUM(H24:K24) -> -0.50237038
A25: Birmingham | B25: 0.08462156 | C25: 0.53529667 | G25: Miami | H25: -0.066078571 | I25: -0.040744444 | J25: 0.83372444 | K25: -0.18126392 | L25: =SUM(H25:K25) -> 0.54563751
A26: Miami | B26: 0.0459907 | C26: 0.29092667 | G26: Portland | H26: 0.507065 | I26: 1.0842139 | J26: 1.3567778 | K26: 1.9484987 | L26: =SUM(H26:K26) -> 4.8965553
A27: Las Vegas | B27: 0.011879974 | C27: 0.07515 | G27: Общий итог | H27: 0.17994 | I27: 0.48144306 | J27: 0.83758722 | K27: 0.5985312
A28: Veggie Blin A | B28: 0.23364775 | C28: 5.8907317
A29: Portland | B29: 0.30382191 | C29: 1.7897333
A30: Cleveland | B30: 0.21767783 | C30: 1.2822817 | P30: =15*12 -> 180
A31: Cincinnati | B31: 0.15388241 | C31: 0.90648 | P31: =1000000/180000 -> 5.5555556
A32: Columbus | B32: 0.099410967 | C32: 0.58560333
A33: Indianapolis | B33: 0.08882428 | C33: 0.52324 | G33: Среднее по полю Profit | H33: Названия столбцов
A34: Birmingham | B34: 0.080233949 | C34: 0.47263667 | G34: Названия строк | H34: Appetizer | I34: Beverages | J34: Dessert | K34: Entry | L34: Общий итог
A35: Miami | B35: 0.046385862 | C35: 0.27324667 | G35: Birmingham | H35: 0.29652857 | I35: 0.21988889 | J35: 1.4036444 | K35: 0.65417167 | L35: 0.54414167
A36: Las Vegas | B36: 0.009762794 | C36: 0.05751 | G36: Cincinnati | H36: 0.88405714 | I36: 1.1333333 | J36: 1.941 | K36: 1.49758 | L36: 1.2995077
A37: Blin A | B37: 0.23364775 | C37: 5.8907317 | G37: Cleveland | H37: 0.8886 | I37: 1.1002778 | J37: 2.0147556 | K37: 1.5716883 | L37: 1.330116
A38: Portland | B38: 0.30382191 | C38: 1.7897333 | G38: Columbus | H38: 0.56365714 | I38: 0.75455556 | J38: 1.6308444 | K38: 1.0154367 | L38: 0.90460897
A39: Cleveland | B39: 0.21767783 | C39: 1.2822817 | G39: Indianapolis | H39: 0.4035 | I39: 0.62211111 | J39: 1.3339556 | K39: 0.73063833 | L39: 0.68713141
A40: Cincinnati | B40: 0.15388241 | C40: 0.90648 | G40: Las Vegas | H40: -0.42352857 | I40: -0.21116667 | J40: 0.79453333 | K40: -0.70617 | L40: -0.34268462
A41: Columbus | B41: 0.099410967 | C41: 0.58560333 | G41: Miami | H41: -0.13215714 | I41: -0.042888889 | J41: 1.0421556 | K41: -0.21325167 | L41: -0.007249359
A42: Indianapolis | B42: 0.08882428 | C42: 0.52324 | G42: Portland | H42: 1.4487571 | I42: 1.1412778 | J42: 2.7135556 | K42: 2.4356233 | L42: 1.9033026
A43: Birmingham | B43: 0.080233949 | C43: 0.47263667 | G43: Общий итог | H43: 0.49117679 | I43: 0.58967361 | J43: 1.6093056 | K43: 0.87321458 | L43: 0.78985929
A44: Miami | B44: 0.046385862 | C44: 0.27324667
A45: Las Vegas | B45: 0.009762794 | C45: 0.05751
A46: Blin F | B46: 0.12906539 | C46: 3.2539992
A47: Portland | B47: 0.59747198 | C47: 1.9441733
A48: Cleveland | B48: 0.39538245 | C48: 1.2865742
A49: Cincinnati | B49: 0.25255692 | C49: 0.82182
A50: Columbus | B50: 0.14702165 | C50: 0.47840833
A51: Birmingham | B51: 0.1030998 | C51: 0.33548667 | G51: Costs each Order
A52: Indianapolis | B52: 0.097443172 | C52: 0.31708 | G52: Среднее по полю Costs per Average Order | H52: Названия столбцов
A53: Miami | B53: -0.19863814 | C53: -0.64636833 | G53: Названия строк | H53: Appetizer | I53: Beverages | J53: Dessert | K53: Entry | L53: Summ Costs per avg order
A54: Las Vegas | B54: -0.39433784 | C54: -1.283175 | G54: Birmingham | H54: 0.51212286 | I54: 1.50175 | J54: 0.86836 | K54: 2.6947884 | L54: =SUM(H54:K54) -> 5.5770213
A55: Blin D | B55: 0.12428854 | C55: 3.133565 | G55: Cincinnati | H55: 1.1637686 | I55: 0.96 | J55: 0.6236 | K55: 2.125452 | L55: =SUM(H55:K55) -> 4.8728206
A56: Portland | B56: 0.4574215 | C56: 1.43336 | G56: Cleveland | H56: 0.90170286 | I56: 1.008125 | J56: 0.90855111 | K56: 3.1520649 | L56: =SUM(H56:K56) -> 5.9704439
A57: Cleveland | B57: 0.31419645 | C57: 0.984555 | G57: Columbus | H57: 0.68804571 | I57: 1.1741333 | J57: 0.59587111 | K57: 2.0815098 | L57: =SUM(H57:K57) -> 4.53956
A58: Cincinnati | B58: 0.20568266 | C58: 0.64452 | G58: Indianapolis | H58: 0.75288571 | I58: 0.92453333 | J58: 0.86626222 | K58: 1.865617 | L58: =SUM(H58:K58) -> 4.4092983
A59: Columbus | B59: 0.12584708 | C59: 0.39435 | G59: Las Vegas | H59: 1.6472264 | I59: 1.99005 | J59: 1.5438267 | K59: 4.523553 | L59: =SUM(H59:K59) -> 9.7046561
A60: Birmingham | B60: 0.095874826 | C60: 0.30043 | G60: Miami | H60: 1.4232214 | I60: 2.0463 | J60: 1.6996089 | K60: 4.0572639 | L60: =SUM(H60:K60) -> 9.2263942
A61: Indianapolis | B61: 0.094550456 | C61: 0.29628 | G61: Portland | H61: 0.892935 | I61: 1.8713417 | J61: 0.97655556 | K61: 3.4275013 | L61: =SUM(H61:K61) -> 7.1683336
A62: Miami | B62: -0.085717067 | C62: -0.2686 | G62: Общий итог | H62: 0.99773857 | I62: 1.4345292 | J62: 1.0103294 | K62: 2.9909688
A63: Las Vegas | B63: -0.20785591 | C63: -0.65133
A64: Blin E | B64: 0.11124592 | C64: 2.8047342
A65: Portland | B65: 0.68633005 | C65: 1.9249733
A66: Cleveland | B66: 0.4464413 | C66: 1.2521492 | G66: City | H66: Среднее из Labour cost, $ | I66: Среднее из Labor costs per avg order
A67: Cincinnati | B67: 0.27876439 | C67: 0.78186 | G67: Birmingham | H67: 10 | I67: 0.5
A68: Columbus | B68: 0.16292394 | C68: 0.45695833 | G68: Cincinnati | H68: 10.5 | I68: 0.525
A69: Birmingham | B69: 0.11718104 | C69: 0.32866167 | G69: Cleveland | H69: 11 | I69: 0.55
A70: Indianapolis | B70: 0.096173107 | C70: 0.26974 | G70: Columbus | H70: 10 | I70: 0.5
A71: Miami | B71: -0.26927805 | C71: -0.75525333 | G71: Indianapolis | H71: 8 | I71: 0.4
A72: Las Vegas | B72: -0.51853577 | C72: -1.454355 | G72: Las Vegas | H72: 9 | I72: 0.45
A73: Blin B | B73: 0.0067580532 | C73: 0.17038417 | G73: Miami | H73: 9.5 | I73: 0.475
A74: Portland | B74: 6.0006358 | C74: 1.0224133 | G74: Portland | H74: 14 | I74: 0.7
A75: Cleveland | B75: 4.0045339 | C75: 0.68230917 | G75: Общий итог | H75: 10.25 | I75: 0.5125
A76: Cincinnati | B76: 2.7791315 | C76: 0.47352
A77: Indianapolis | B77: 0.95490093 | C77: 0.1627
A78: Columbus | B78: 0.64312509 | C78: 0.10957833
A79: Birmingham | B79: -1.0939886 | C79: -0.18639833
A80: Miami | B80: -5.1819565 | C80: -0.88292333
A81: Las Vegas | B81: -7.1063821 | C81: -1.210815
A82: Blin C | B82: -0.089556426 | C82: -2.2578983
A83: Portland | B83: -0.34099557 | C83: 0.76993333
A84: Cleveland | B84: -0.12357805 | C84: 0.27902667
A85: Cincinnati | B85: -0.092927125 | C85: 0.20982
A86: Columbus | B86: 0.040695662 | C86: -0.091886667
A87: Indianapolis | B87: 0.059121351 | C87: -0.13349
... A91: Общий итог | B91: 1 | C91: 25.212019

Sheet Revenue&Margin
A1: Tables | B1: =B3+B4 -> 10
A2: Seats at the table | B2: =4*2+6*4 -> 32
A3: table for 4 person | B3: 6
A4: table for 2 person | B4: 4
A5: Hours opening per day (8-20) | B5: =B7-B6 -> 12
A6: open | B6: 8
A7: close | B7: 20
A8: Hours inside | B8: =B5*0.8 -> 9.6
A9: Orders per day (one person/table) | B9: 10
A10: Summary order for all (one) persons/day | B10: =B9*B2 -> 320
A11: Days working per month | B11: =25 -> 25
B15: Mean order, $ | C15: Revenue per month, $ | D15: Revenue per year, $ | F15: Profit per each order, $ | G15: Gross profit, $, month
A16: Columbus | B16: ='Mean order price'!V3 -> 6.4415873 | C16: =B16*$B$10*$B$11 -> 51532.698 | D16: =C16*12 -> 618392.38 | F16: 1.9020273 | G16: =F16*$B$10*$B$11 -> 15216.218 | I16: =F16/B16 -> 0.29527308
A17: Cincinnati | B17: ='Mean order price'!V4 -> 7.9406667 | C17: =B17*$B$10*$B$11 -> 63525.333 | D17: =C17*12 -> 762304 | F17: 3.0678461 | G17: =F17*$B$10*$B$11 -> 24542.769 | I17: =F17/B17 -> 0.38634616
A18: Cleveland | B18: ='Mean order price'!V5 -> 9.5951429 | C18: =B18*$B$10*$B$11 -> 76761.143 | D18: =C18*12 -> 921133.71 | F18: 3.624699 | G18: =F18*$B$10*$B$11 -> 28997.592 | I18: =F18/B18 -> 0.37776394
A19: Las Vegas | B19: ='Mean order price'!V6 -> 9.2022857 | C19: =B19*$B$10*$B$11 -> 73618.286 | D19: =C19*12 -> 883419.43 | F19: -0.50237038 | G19: =F19*$B$10*$B$11 -> -4018.963 | I19: =F19/B19 -> -0.054591913
A20: Miami | B20: ='Mean order price'!V7 -> 9.7720317 | C20: =B20*$B$10*$B$11 -> 78176.254 | D20: =C20*12 -> 938115.05 | F20: 0.54563751 | G20: =F20*$B$10*$B$11 -> 4365.1001 | I20: =F20/B20 -> 0.05583665
A21: Indianapolis | B21: ='Mean order price'!V8 -> 6.3738413 | C21: =B21*$B$10*$B$11 -> 50990.73 | D21: =C21*12 -> 611888.76 | F21: 1.964543 | G21: =F21*$B$10*$B$11 -> 15716.344 | I21: =F21/B21 -> 0.30821963
A22: Birmingham | B22: ='Mean order price'!V9 -> 6.8580952 | C22: =B22*$B$10*$B$11 -> 54864.762 | D22: =C22*12 -> 658377.14 | F22: 1.281074 | G22: =F22*$B$10*$B$11 -> 10248.592 | I22: =F22/B22 -> 0.18679734
A23: Portland | B23: ='Mean order price'!V10 -> 12.064889 | C23: =B23*$B$10*$B$11 -> 96519.111 | D23: =C23*12 -> 1158229.3 | F23: 4.8965553 | G23: =F23*$B$10*$B$11 -> 39172.443 | I23: =F23/B23 -> 0.40585167
A25: =A17 -> Cincinnati | B25: Per month, $ | C25: Per year, $
A26: Revenue | B26: =C17 -> 63525.333 | C26: =B26*12 -> 762304
A27: Cost of goods sold | B27: =B26-B28 -> 38982.565 | C27: =C26-C28 -> 467790.77
A28: Gross profit | B28: =G17 -> 24542.769 | C28: =B28*12 -> 294513.23
A29: Gross profit margin, % | B29: =B28/B26 -> 0.38634616 | C29: =C28/C26 -> 0.38634616
A30: Operating costs | B30: =SUM(B31:B34) -> 13400 | C30: =SUM(C31:C34) -> 160800
A31: rent+utility costs | B31: 4000 | C31: =B31*12 -> 48000
A32: salary for another personal | B32: =7*B5*B11*4 -> 8400 | C32: =B32*12 -> 100800
A33: marketing | B33: 500 | C33: =B33*12 -> 6000
A34: another costs (reserve) | B34: 500 | C34: =B34*12 -> 6000
A35: EBITDA | B35: =B28-SUM(B31:B34) -> 11142.769 | C35: =C28-SUM(C31:C34) -> 133713.23
A36: Depreсiation | B36: =60000/10/12 -> 500 | C36: =60000/10 -> 6000 | D36: 60000$ CAPEX (equipment and furniture)
A37: EBIT | B37: =B35-B36 -> 10642.769 | C37: =C35-C36 -> 127713.23
A38: EBIT margin, % | B38: =B37/B26 -> 0.16753582 | C38: =C37/C26 -> 0.16753582
A39: Taxes | B39: =B37*0.07 -> 744.99381 | C39: =C37*0.05 -> 6385.6613 | D39: от 2,5% до 9,8%
A40: Net profit | B40: =B37-B39 -> 9897.7749 | C40: =C37-C39 -> 121327.56
A41: Net profit margin | B41: =B40/B26 -> 0.15580831 | C41: =C40/C26 -> 0.15915903

Sheet Priority
B3: Метрика | C3: балльная оценка | D3: Cincinnati OH | E3: Columbus OH | F3: Indianapolis IN | G3: Cleveland OH | H3: Portland OR | I3: Birmingham AL
B4: Население города, тыс. чел. | C4: до 300 - 0 баллов 300 - 600 - 0,5 баллов от 600 - 1 балл | D4: 311.097 | E4: 913.175 | F4: 879.293 | G4: 362.656 | H4: 630.498 | I4: 196.644
B5: Доля населения от 18 до 35 лет, % | C5: до 25 - 0 баллов 25 - 30 - 0,5 баллов от 30 - 1 | D5: 32.4 | E5: 25.7 | F5: 26.4 | G5: 27 | H5: 26.6 | I5: 29.9
B6: Median household income, тыс. долл | C6: до 50 - 0 баллов 50 - 70 - 0,5 баллов от 70 - 1 балл | D6: 51.707 | E6: 78.538 | F6: 62.995 | G6: 39.187 | H6: 88.792 | I6: 44.376
B7: Коэффициент концентрации на 1 кв. км | C7: до 0,3 - 0 баллов 0,4-0,6 - 1 балл от 0,6 - 0,5 баллов | D7: 0.9936985 | E7: 0.28327645 | F7: 0.16894019 | G7: 0.51029963 | H7: 0.28753994 | I7: 0.2091402
B8: Коэффициент концентрации на 1 тыс. чел. | C8: до 0,4 - 0 баллов 0,4-0,6 - 1 балл от 0,6 - 0,5 баллов | D8: =D14/D4 -> 0.65895846 | E8: =E14/E4 -> 0.18178334 | F8: =F14/F4 -> 0.18310165 | G8: =G14/G4 -> 0.30056031 | H8: =H14/H4 -> 0.17129317 | I8: =I14/I4 -> 0.41191188
B9: Order Profit | C9: до 1 - 0 баллов 1 - 3 - 0,5 баллов от 3 - 1 балл | D9: 3.0678461 | E9: 1.9020273 | F9: 1.964543 | G9: 3.624699 | H9: 4.8965553 | I9: 1.281074
B10: Уровень преступности на 1 тыс. чел., % | C10: до 40 - 1 балл 40 - 50 - 0,5 баллов от 50 - 0 баллов | D10: 50.06 | E10: 31.52 | F10: 46.56 | G10: 64.35 | H10: 66.99 | I10: 62.65
B12: Информация для справки:
B13: Площадь города, кв. км | D13: 206.3 | E13: 586 | F13: 953 | G13: 213.6 | H13: 375.6 | I13: 387.3
B14: Количество конкурентов | D14: 205 | E14: 166 | F14: 161 | G14: 109 | H14: 108 | I14: 81
B15: Average Profit | D15: 1.2995077 | E15: 0.90460897 | F15: 0.68713141 | G15: 1.330116 | H15: 1.9033026 | I15: 0.54414167

Sheet Total Score
B2: Оценка городов
B3: Метрика | C3: балльная оценка | D3: Cincinnati, OH | E3: Columbus OH | F3: Indianapolis IN | G3: Cleveland OH | H3: Portland OR | I3: Birmingham AL
B4: Население города, тыс. чел. | C4: до 300 - 0 баллов 300 - 600 - 0,5 баллов от 600 - 1 балл | D4: 0.5 | E4: 1 | F4: 1 | G4: 0.5 | H4: 1 | I4: 0
B5: Доля населения от 18 до 35 лет, % | C5: до 25 - 0 баллов 25 - 30 - 0,5 баллов от 30 - 1 | D5: 1 | E5: 0.5 | F5: 0.5 | G5: 0.5 | H5: 0.5 | I5: 0.5
B6: Median household income, тыс. долл | C6: до 50 - 0 баллов 50 - 70 - 0,5 баллов от 70 - 1 балл | D6: 0.5 | E6: 1 | F6: 0.5 | G6: 0 | H6: 1 | I6: 0
B7: Коэффициент концентрации на 1 кв. км | C7: до 0,4 - 0 баллов 0,4-0,6 - 1 балл от 0,6 - 0,5 баллов | D7: 0.5 | E7: 0 | F7: 0 | G7: 1 | H7: 0 | I7: 0
B8: Коэффициент концентрации на 1 тыс. чел. | C8: до 0,4 - 0 баллов 0,4-0,6 - 1 балл от 0,6 - 0,5 баллов | D8: 0.5 | E8: 0 | F8: 0 | G8: 0 | H8: 0 | I8: 1
B9: Order Profit | C9: до 1 - 0 баллов 1 - 3 - 0,5 баллов от 3 - 1 балл | D9: 1 | E9: 0.5 | F9: 0.5 | G9: 1 | H9: 1 | I9: 0.5
B10: Уровень преступности на 1 тыс. чел., % | C10: до 40 - 1 балл 40 - 50 - 0,5 баллов от 50 - 0 баллов | D10: 0 | E10: 1 | F10: 0.5 | G10: 0 | H10: 0 | I10: 0
B11: Итого: | D11: =SUM(D4:D10) -> 4 | E11: =SUM(E4:E10) -> 4 | F11: =SUM(F4:F10) -> 3 | G11: =SUM(G4:G10) -> 3 | H11: =SUM(H4:H10) -> 3.5 | I11: =SUM(I4:I10) -> 2
B12: Приоритет отрытия кафе | D12: 1 | E12: 2 | F12: 5 | G12: 4 | H12: 3 | I12: 6
B14: Площадь города, кв. км | D14: 206.3 | E14: 586 | F14: 953 | G14: 213.6 | H14: 375.6 | I14: 387.3
B15: Количество конкурентов | D15: 205 | E15: 166 | F15: 161 | G15: 109 | H15: 108 | I15: 81
B16: Average Profit | D16: 1.2995077 | E16: 0.90460897 | F16: 0.68713141 | G16: 1.330116 | H16: 1.9033026 | I16: 0.54414167
